Workbook

Sheet Sheet1
A2: FUND | B2: PLAY
B4: Sum of Shares | F4: Sum of Weight (%) | J4: Average of Price
B5: 45657 | C5: 45930 | D5: 45961 | E5: 45987 | F5: 45657 | G5: 45930 | H5: 45961 | I5: 45987 | J5: 45657 | K5: 45930 | L5: 45961 | M5: 45987
A6: ADVANCED MICRO DEVICES INC | B6: 14759 | C6: 29087 | D6: 29087 | E6: 31566 | F6: 3.9 | G6: 6.49 | H6: 10.08 | I6: 9.31 | J6: 120.79 | K6: 161.79 | L6: 256.12 | M6: 214.24 | N6: =M6/J6-1 -> 0.77365676
A7: SAMSUNG ELECTRONICS LTD | B7: 38388 | C7: 73018 | D7: 73018 | E7: 79200 | F7: 3.04 | G7: 6.03 | H7: 7.45 | I7: 7.65 | J7: 36.14 | K7: 59.8 | L7: 75.45 | M7: 70.14 | N7: =M7/J7-1 -> 0.94078583
A8: APPLE INC | B8: 11336 | C8: 17690 | D8: 17690 | E8: 19195 | F8: 6.21 | G8: 6.22 | H8: 6.47 | I8: 7.33 | J8: 250.42 | K8: 254.63 | L8: 270.37 | M8: 277.55 | N8: =M8/J8-1 -> 0.10833799
A9: NVIDIA CORP | B9: 19373 | C9: 24895 | D9: 24895 | E9: 27023 | F9: 5.69 | G9: 6.41 | H9: 6.82 | I9: 6.7 | J9: 134.29 | K9: 186.58 | L9: 202.49 | M9: 180.26 | N9: =M9/J9-1 -> 0.34231886
A10: ELECTRONIC ARTS INC | B10: 13113 | C10: 18684 | D10: 18684 | E10: 20274 | F10: 4.2 | G10: 5.2 | H10: 5.06 | I10: 5.63 | J10: 146.3 | K10: 201.7 | L10: 200.06 | M10: 201.92 | N10: =M10/J10-1 -> 0.38017772
A11: NETFLIX INC | B11: 3619 | C11: 2978 | D11: 2978 | E11: 32320 | F11: 7.06 | G11: 4.93 | H11: 4.51 | I11: 4.72 | J11: 891.32 | K11: 1198.92 | L11: 1118.86 | M11: 106.14 | N11: =M11/J11-1 -> -0.88091819
A12: TAKE TWO INTERACTIVE SOFTWARE INC | B12: 9710 | C12: 12135 | D12: 12135 | E12: 13170 | F12: 3.91 | G12: 4.33 | H12: 4.21 | I12: 4.42 | J12: 184.08 | K12: 258.36 | L12: 256.37 | M12: 243.63 | N12: =M12/J12-1 -> 0.32350065
A13: NINTENDO LTD | B13: 32400 | C13: 34100 | D13: 34100 | E13: 37000 | F13: 4.18 | G13: 4.08 | H13: 3.91 | I13: 4.31 | J13: 58.95 | K13: 86.7 | L13: 84.68 | M13: 84.61 | N13: =M13/J13-1 -> 0.43528414
A14: ROBLOX CORP CLASS A | B14: 32506 | C14: 30425 | D14: 30425 | E14: 33011 | F14: 4.12 | G14: 5.82 | H14: 4.68 | I14: 4.21 | J14: 57.86 | K14: 138.52 | L14: 113.72 | M14: 92.73 | N14: =M14/J14-1 -> 0.6026616
A15: XIAOMI CORP | B15: 808600 | C15: 527000 | D15: 527000 | E15: 571200 | F15: 7.86 | G15: 5.05 | H15: 3.96 | I15: 4.05 | J15: 4.44 | K15: 6.94 | L15: 5.56 | M15: 5.16 | N15: =M15/J15-1 -> 0.16216216
A16: SPOTIFY TECHNOLOGY SA | B16: 5768 | C16: 4112 | D16: 4112 | E16: 4462 | F16: 5.65 | G16: 3.96 | H16: 3.64 | I16: 3.64 | J16: 447.38 | K16: 698 | L16: 655.32 | M16: 592.69 | N16: =M16/J16-1 -> 0.32480218
A17: REDDIT INC CLASS A | C17: 10066 | D17: 10066 | E17: 10928 | G17: 3.19 | H17: 2.84 | I17: 3.12 | K17: 229.99 | L17: 208.95 | M17: 207.56 | N17: =M17/J17-1 -> #DIV/0!
A18: ARISTOCRAT LEISURE LTD | B18: 38986 | C18: 51762 | D18: 51762 | E18: 56119 | F18: 3.61 | G18: 3.31 | H18: 2.9 | I18: 2.94 | J18: 42.33 | K18: 46.38 | L18: 41.47 | M18: 38.09 | N18: =M18/J18-1 -> -0.10016537
A19: ZOOM COMMUNICATIONS INC CLASS A | B19: 15843 | C19: 21723 | D19: 21723 | E19: 23561 | F19: 2.83 | G19: 2.47 | H19: 2.56 | I19: 2.74 | J19: 81.61 | K19: 82.5 | L19: 87.23 | M19: 84.43 | N19: =M19/J19-1 -> 0.034554589
A20: TRADE DESK INC CLASS A | B20: 19441 | C20: 37041 | D20: 37041 | E20: 40207 | F20: 5 | G20: 2.51 | H20: 2.52 | I20: 2.16 | J20: 117.53 | K20: 49.01 | L20: 50.28 | M20: 39.11 | N20: =M20/J20-1 -> -0.6672339
A21: LOGITECH INTERNATIONAL SA | B21: 9439 | C21: 12218 | D21: 12218 | E21: 13223 | F21: 1.71 | G21: 1.84 | H21: 1.99 | I21: 2.03 | J21: 82.8 | K21: 109.07 | L21: 120.44 | M21: 111.71 | N21: =M21/J21-1 -> 0.34915459
A22: KONAMI GROUP CORP | B22: 6300 | C22: 8500 | D22: 8500 | E22: 9200 | F22: 1.3 | G22: 1.7 | H22: 1.92 | I22: 1.92 | J22: 94.17 | K22: 144.56 | L22: 167.08 | M22: 151.89 | N22: =M22/J22-1 -> 0.61293406
A23: PINTEREST INC CLASS A | B23: 36401 | C23: 49140 | D23: 49140 | E23: 53315 | F23: 2.31 | G23: 2.18 | H23: 2.2 | I23: 1.88 | J23: 29 | K23: 32.17 | L23: 33.1 | M23: 25.57 | N23: =M23/J23-1 -> -0.11827586
A24: ROKU INC CLASS A | B24: 7723 | C24: 10688 | D24: 10688 | E24: 11622 | F24: 1.26 | G24: 1.48 | H24: 1.53 | I24: 1.53 | J24: 74.34 | K24: 100.13 | L24: 106.13 | M24: 95.63 | N24: =M24/J24-1 -> 0.28638687
A25: LENOVO GROUP LTD | B25: 520000 | C25: 708000 | D25: 708000 | E25: 766000 | F25: 1.48 | G25: 1.45 | H25: 1.4 | I25: 1.31 | J25: 1.3 | K25: 1.48 | L25: 1.46 | M25: 1.25 | N25: =M25/J25-1 -> -0.038461538
A26: EVOLUTION | B26: 11803 | C26: 12331 | D26: 12331 | E26: 13369 | F26: 1.99 | G26: 1.4 | H26: 1.12 | I26: 1.24 | J26: 77.18 | K26: 82.23 | L26: 66.92 | M26: 67.33 | N26: =M26/J26-1 -> -0.12762374
A27: NEXON LTD | B27: 21300 | C27: 34100 | D27: 34100 | E27: 37000 | F27: 0.7 | G27: 1.03 | H27: 0.94 | I27: 1.2 | J27: 15.12 | K27: 21.99 | L27: 20.45 | M27: 23.59 | N27: =M27/J27-1 -> 0.56018519
A28: CAPCOM LTD | B28: 22900 | C28: 31000 | D28: 31000 | E28: 33600 | F28: 1.11 | G28: 1.17 | H28: 1.1 | I28: 1.12 | J28: 22.1 | K28: 27.24 | L28: 26.19 | M28: 24.25 | N28: =M28/J28-1 -> 0.097285068
A29: SNAP INC CLASS A | B29: 66688 | C29: 98070 | D29: 98070 | E29: 106261 | F29: 1.57 | G29: 1.04 | H29: 1.03 | I29: 1.11 | J29: 10.77 | K29: 7.71 | L29: 7.8 | M29: 7.61 | N29: =M29/J29-1 -> -0.29340761
... A32: DUOLINGO INC CLASS A | B32: 2189 | C32: 3245 | D32: 3245 | E32: 3522 | F32: 1.55 | G32: 1.44 | H32: 1.19 | I32: 0.91 | J32: 324.23 | K32: 321.84 | L32: 270.64 | M32: 188.43 | N32: =M32/J32-1 -> -0.41883848
A33: LIFE360 INC | C33: 6334 | D33: 6334 | E33: 6866 | G33: 0.93 | H33: 0.85 | I33: 0.74 | K33: 106.3 | L33: 98.71 | M33: 78.46 | N33: =M33/J33-1 -> #DIV/0!
A34: KRAFTON INC | B34: 2108 | C34: 2626 | D34: 2626 | E34: 2814 | F34: 0.98 | G34: 0.76 | H34: 0.69 | I34: 0.69 | J34: 212.27 | K34: 208.47 | L34: 193.72 | M34: 177.39 | N34: =M34/J34-1 -> -0.16431903
A35: SQUARE ENIX HLDG LTD | B35: 5600 | C35: 22800 | D35: 22800 | E35: 24800 | F35: 0.48 | G35: 0.68 | H35: 0.6 | I35: 0.68 | J35: 39.11 | K35: 21.55 | L35: 19.38 | M35: 19.81 | N35: =M35/J35-1 -> -0.49347993
A36: CD PROJEKT SA | B36: 4291 | C36: 5816 | D36: 5816 | E36: 6233 | F36: 0.44 | G36: 0.6 | H36: 0.54 | I36: 0.57 | J36: 46.35 | K36: 74.56 | L36: 68.78 | M36: 66.56 | N36: =M36/J36-1 -> 0.4360302
A37: GRAND CANYON EDUCATION INC | B37: 1841 | C37: 2352 | D37: 2352 | E37: 2521 | F37: 0.66 | G37: 0.71 | H37: 0.6 | I37: 0.54 | J37: 163.8 | K37: 219.52 | L37: 188.3 | M37: 156.43 | N37: =M37/J37-1 -> -0.044993895
A38: SOUNDHOUND AI INC CLASS A | B38: 18055 | C38: 30562 | D38: 30562 | E38: 32752 | F38: 0.78 | G38: 0.68 | H38: 0.73 | I38: 0.53 | J38: 19.84 | K38: 16.08 | L38: 17.62 | M38: 11.82 | N38: =M38/J38-1 -> -0.40423387
A39: SANKYO LTD | B39: 13100 | C39: 18200 | D39: 18200 | E39: 19500 | F39: 0.39 | G39: 0.44 | H39: 0.43 | I39: 0.46 | J39: 13.54 | K39: 17.41 | L39: 17.37 | M39: 17 | N39: =M39/J39-1 -> 0.25553914
A40: AMBARELLA INC | B40: 2463 | C40: 3515 | D40: 3515 | E40: 3767 | F40: 0.39 | G40: 0.4 | H40: 0.41 | I40: 0.38 | J40: 72.74 | K40: 82.52 | L40: 85.23 | M40: 73.89 | N40: =M40/J40-1 -> 0.015809733
A41: STRIDE INC | B41: 2658 | C41: 3607 | D41: 3607 | E41: 3865 | F41: 0.6 | G41: 0.74 | H41: 0.33 | I41: 0.34 | J41: 103.93 | K41: 148.94 | L41: 68.04 | M41: 63.8 | N41: =M41/J41-1 -> -0.38612528
A42: SPORTRADAR GROUP AG CLASS A | C42: 9762 | D42: 9762 | E42: 10461 | G42: 0.36 | H42: 0.34 | I42: 0.31 | K42: 26.9 | L42: 25.61 | M42: 21.71 | N42: =M42/J42-1 -> #DIV/0!
A43: PELOTON INTERACTIVE CLASS A INC | B43: 21246 | C43: 31646 | D43: 31646 | E43: 33913 | F43: 0.4 | G43: 0.39 | H43: 0.31 | I43: 0.31 | J43: 8.7 | K43: 9 | L43: 7.26 | M43: 6.72 | N43: =M43/J43-1 -> -0.22758621
A44: SONOS INC | B44: 7494 | C44: 9927 | D44: 9927 | E44: 10638 | F44: 0.25 | G44: 0.22 | H44: 0.23 | I44: 0.27 | J44: 15.04 | K44: 15.8 | L44: 17.17 | M44: 18.63 | N44: =M44/J44-1 -> 0.23869681
A45: MAGNITE INC | B45: 8433 | C45: 11690 | D45: 11690 | E45: 12528 | F45: 0.29 | G45: 0.35 | H45: 0.28 | I45: 0.25 | J45: 15.92 | K45: 21.78 | L45: 17.88 | M45: 14.68 | N45: =M45/J45-1 -> -0.077889447
A46: SINCH | C46: 57093 | D46: 57093 | E46: 61184 | G46: 0.25 | H46: 0.28 | I46: 0.24 | K46: 3.22 | L46: 3.64 | M46: 2.87 | N46: =M46/J46-1 -> #DIV/0!
A47: NCSOFT CORP | B47: 1068 | C47: 1047 | D47: 1047 | E47: 1122 | F47: 0.29 | G47: 0.22 | H47: 0.22 | I47: 0.22 | J47: 124.38 | K47: 153.95 | L47: 154.76 | M47: 145.66 | N47: =M47/J47-1 -> 0.1710886
A48: KOEI TECMO HOLDINGS LTD | B48: 8600 | C48: 9600 | D48: 9600 | E48: 10300 | F48: 0.22 | G48: 0.17 | H48: 0.18 | I48: 0.19 | J48: 11.81 | K48: 13.03 | L48: 13.5 | M48: 13.68 | N48: =M48/J48-1 -> 0.15834039
A49: EMBRACER GROUP CLASS B | B49: 54418 | C49: 13655 | D49: 13655 | E49: 14633 | F49: 0.33 | G49: 0.21 | H49: 0.19 | I49: 0.18 | J49: 2.73 | K49: 11.08 | L49: 10.45 | M49: 9.03 | N49: =M49/J49-1 -> 2.3076923
A50: DOUBLEVERIFY HOLDINGS INC | B50: 7095 | C50: 11266 | D50: 11266 | E50: 12073 | F50: 0.3 | G50: 0.19 | H50: 0.17 | I50: 0.17 | J50: 19.21 | K50: 11.98 | L50: 11.38 | M50: 10.44 | N50: =M50/J50-1 -> -0.45653306
A51: TCL ELECTRONICS HOLDINGS LTD | B51: 48000 | C51: 94000 | D51: 94000 | E51: 101000 | F51: 0.09 | G51: 0.18 | H51: 0.15 | I51: 0.17 | J51: 0.82 | K51: 1.35 | L51: 1.19 | M51: 1.25 | N51: =M51/J51-1 -> 0.52439024
A52: ADEIA INC | B52: 6510 | C52: 8957 | D52: 8957 | E52: 9599 | F52: 0.2 | G52: 0.21 | H52: 0.21 | I52: 0.16 | J52: 13.98 | K52: 16.8 | L52: 17.04 | M52: 12.31 | N52: =M52/J52-1 -> -0.11945637
A53: HTC CORP | B53: 48000 | C53: 65000 | D53: 65000 | E53: 70000 | F53: 0.16 | G53: 0.18 | H53: 0.14 | I53: 0.15 | J53: 1.5 | K53: 1.96 | L53: 1.64 | M53: 1.57 | N53: =M53/J53-1 -> 0.046666667
A54: PRIMAX ELECTRONICS LTD | B54: 28500 | C54: 37500 | D54: 37500 | E54: 40500 | F54: 0.14 | G54: 0.13 | H54: 0.14 | I54: 0.15 | J54: 2.32 | K54: 2.58 | L54: 2.7 | M54: 2.66 | N54: =M54/J54-1 -> 0.14655172
A55: UNIVERSAL TECHNICAL INSTITUTE INC | C55: 4479 | D55: 4479 | E55: 4800 | G55: 0.2 | H55: 0.18 | I55: 0.15 | K55: 32.55 | L55: 29.72 | M55: 23.12 | N55: =M55/J55-1 -> #DIV/0!
A56: MODERN TIMES GROUP MTG CLASS B | B56: 5831 | C56: 7655 | D56: 7655 | E56: 8203 | F56: 0.11 | G56: 0.12 | H56: 0.14 | I56: 0.14 | J56: 8.59 | K56: 11.72 | L56: 13.48 | M56: 12.36 | N56: =M56/J56-1 -> 0.43888242
A57: DENA LTD | B57: 4800 | C57: 6300 | D57: 6300 | E57: 6800 | F57: 0.21 | G57: 0.14 | H57: 0.15 | I57: 0.14 | J57: 19.95 | K57: 15.71 | L57: 17.58 | M57: 15.43 | N57: =M57/J57-1 -> -0.22656642
A58: VOBILE GROUP LTD | B58: 105000 | C58: 144000 | D58: 144000 | E58: 154000 | F58: 0.11 | G58: 0.15 | H58: 0.13 | I58: 0.14 | J58: 0.48 | K58: 0.77 | L58: 0.67 | M58: 0.64 | N58: =M58/J58-1 -> 0.33333333
A59: COURSERA INC | B59: 7728 | C59: 11063 | D59: 11063 | E59: 11856 | F59: 0.14 | G59: 0.18 | H59: 0.13 | I59: 0.13 | J59: 8.5 | K59: 11.71 | L59: 8.42 | M59: 7.94 | N59: =M59/J59-1 -> -0.065882353
A60: NETMARBLE CORP | B60: 1303 | C60: 2443 | D60: 2443 | E60: 2618 | F60: 0.1 | G60: 0.15 | H60: 0.13 | I60: 0.13 | J60: 35.12 | K60: 43.98 | L60: 37.97 | M60: 36.71 | N60: =M60/J60-1 -> 0.045273349
A61: HARMONIC INC | B61: 6845 | C61: 9335 | D61: 9335 | E61: 10004 | F61: 0.2 | G61: 0.13 | H61: 0.14 | I61: 0.13 | J61: 13.23 | K61: 10.18 | L61: 10.7 | M61: 9.54 | N61: =M61/J61-1 -> -0.27891156
A62: FUBOTV INC CLASS A | B62: 17339 | C62: 28105 | D62: 28105 | E62: 30119 | F62: 0.05 | G62: 0.16 | H62: 0.14 | I62: 0.12 | J62: 1.26 | K62: 4.15 | L62: 3.78 | M62: 3.01 | N62: =M62/J62-1 -> 1.3888889
A63: PLAYTECH PLC | B63: 17371 | C63: 23647 | D63: 23647 | E63: 25341 | F63: 0.34 | G63: 0.16 | H63: 0.11 | I63: 0.12 | J63: 8.95 | K63: 4.97 | L63: 3.46 | M63: 3.39 | N63: =M63/J63-1 -> -0.62122905
A64: IDP EDUCATION PTY LTDINARY | B64: 17130 | C64: 23246 | D64: 23246 | E64: 24912 | F64: 0.29 | G64: 0.14 | H64: 0.12 | I64: 0.11 | J64: 7.82 | K64: 4.35 | L64: 3.67 | M64: 3.33 | N64: =M64/J64-1 -> -0.5741688
A65: PEARLABYSS CORP | B65: 2288 | C65: 3085 | D65: 3085 | E65: 3306 | F65: 0.09 | G65: 0.11 | H65: 0.1 | I65: 0.11 | J65: 18.82 | K65: 25.27 | L65: 24.28 | M65: 24.63 | N65: =M65/J65-1 -> 0.30871413
A66: MERRY ELECTRONICS LTD | B66: 14008 | C66: 20008 | D66: 20008 | E66: 23008 | F66: 0.1 | G66: 0.09 | H66: 0.09 | I66: 0.1 | J66: 3.29 | K66: 3.33 | L66: 3.33 | M66: 3.29 | N66: =M66/J66-1 -> 0
A67: UBISOFT ENTERTAINMENT SA CAT A | B67: 5819 | C67: 8175 | D67: 8175 | E67: 8761 | F67: 0.17 | G67: 0.13 | H67: 0.1 | I67: 0.09 | J67: 13.62 | K67: 11.44 | L67: 8.94 | M67: 7.7 | N67: =M67/J67-1 -> -0.43465492
... A77: AUD CASH | B77: 6761 | C77: 10740 | D77: 10740 | E77: 58457 | F77: 0.01 | G77: 0.01 | H77: 0.01 | I77: 0.05 | J77: 61.91 | K77: 66.28 | L77: 65.47 | M77: 65.1 | N77: =M77/J77-1 -> 0.051526409
A78: IGG INC | C78: 64000 | D78: 64000 | E78: 69000 | G78: 0.05 | H78: 0.04 | I78: 0.05 | K78: 0.58 | L78: 0.5 | M78: 0.49 | N78: =M78/J78-1 -> #DIV/0!
A79: KAKAO GAMES CORP | B79: 2799 | C79: 3359 | D79: 3359 | E79: 3600 | F79: 0.07 | G79: 0.05 | H79: 0.05 | I79: 0.05 | J79: 11.13 | K79: 11.13 | L79: 11.31 | M79: 10.69 | N79: =M79/J79-1 -> -0.039532794
A80: DOUBLEU GAMES LTD | B80: 640 | C80: 907 | D80: 907 | E80: 972 | F80: 0.05 | G80: 0.05 | H80: 0.04 | I80: 0.05 | J80: 36.61 | K80: 37.06 | L80: 35.23 | M80: 35.96 | N80: =M80/J80-1 -> -0.017754712
A81: KRW CASH | B81: 27588580 | C81: 30932926 | D81: 31579504 | E81: 52171690 | F81: 0.04 | G81: 0.03 | H81: 0.03 | I81: 0.05 | J81: 0.07 | K81: 0.07 | L81: 0.07 | M81: 0.07 | N81: =M81/J81-1 -> 0
A82: WEM ADE LTD | B82: 1160 | C82: 1686 | D82: 1686 | E82: 1807 | F82: 0.06 | G82: 0.04 | H82: 0.04 | I82: 0.04 | J82: 23.88 | K82: 18.99 | L82: 18.85 | M82: 17.06 | N82: =M82/J82-1 -> -0.28559464
A83: PUBMATIC INC CLASS A | B83: 2518 | C83: 3319 | D83: 3319 | E83: 3557 | F83: 0.08 | G83: 0.04 | H83: 0.04 | I83: 0.04 | J83: 14.69 | K83: 8.28 | L83: 8.36 | M83: 9.1
A84: PLAYTIKA HOLDING CORP | B84: 2400 | C84: 6077 | D84: 6077 | E84: 6512 | F84: 0.04 | G84: 0.03 | H84: 0.03 | I84: 0.04 | J84: 6.94 | K84: 3.89 | L84: 3.67 | M84: 4.05
A85: NETDRAGON WEBSOFT LTD | C85: 20500 | D85: 20500 | E85: 22000 | G85: 0.06 | H85: 0.04 | I85: 0.04 | K85: 1.99 | L85: 1.56 | M85: 1.47
A86: INSOURCE LTD | C86: 4400 | D86: 4400 | E86: 4700 | G86: 0.04 | H86: 0.03 | I86: 0.04 | K86: 6.51 | L86: 5.67 | M86: 5.47
A87: MARS GROUP HOLDINGS CORP | C87: 1300 | D87: 1300 | E87: 1400 | G87: 0.04 | H87: 0.04 | I87: 0.04 | K87: 20.79 | L87: 19.93 | M87: 19.98
A88: SOOP LTD | B88: 509 | C88: 611 | D88: 611 | E88: 655 | F88: 0.07 | G88: 0.05 | H88: 0.04 | I88: 0.04 | J88: 61.75 | K88: 53.45 | L88: 51.03 | M88: 46.74
A89: HANCOM INC | C89: 1406 | D89: 1406 | E89: 1507 | G89: 0.04 | H89: 0.03 | I89: 0.03 | K89: 18.25 | L89: 17.44 | M89: 16.2
A90: NEXON GAMES LTD | C90: 2056 | D90: 2056 | E90: 2203 | G90: 0.03 | H90: 0.03 | I90: 0.03 | K90: 9.99 | L90: 9.38 | M90: 8.71
A91: BUMBLE INC CLASS A | B91: 8343 | C91: 6347 | D91: 6347 | E91: 6802 | F91: 0.15 | G91: 0.05 | H91: 0.05 | I91: 0.03 | J91: 8.14 | K91: 6.09 | L91: 5.55 | M91: 3.53
A92: DEAR U LTD | B92: 701 | C92: 841 | D92: 841 | E92: 901 | F92: 0.04 | G92: 0.04 | H92: 0.03 | I92: 0.03 | J92: 24.49 | K92: 31.22 | L92: 26.85 | M92: 21.08
A93: MNC DIGITAL ENTERTAINMENT | C93: 716700 | D93: 716700 | E93: 768100 | G93: 0.03 | H93: 0.03 | I93: 0.03 | K93: 0.03 | L93: 0.03 | M93: 0.02
A94: GREE HOLDINGS INC | B94: 4000 | C94: 5700 | D94: 5700 | E94: 6100 | F94: 0.03 | G94: 0.02 | H94: 0.02 | I94: 0.02 | J94: 2.9 | K94: 2.97 | L94: 2.62 | M94: 2.68
A95: DEVSISTERS CORP | B95: 409 | C95: 623 | D95: 623 | E95: 668 | F95: 0.02 | G95: 0.03 | H95: 0.03 | I95: 0.02 | J95: 18.82 | K95: 35.39 | L95: 29.69 | M95: 20.67
A96: HKD CASH | B96: 19009 | C96: 179765 | D96: 179765 | E96: 52946 | F96: 0.01 | G96: 0.03 | H96: 0.03 | I96: 0.01 | J96: 12.87 | K96: 12.85 | L96: 12.87 | M96: 12.86
A97: SEK CASH | B97: 69846 | C97: 45669 | D97: 45669 | E97: 52960 | F97: 0.01 | G97: 0.01 | H97: 0.01 | I97: 0.01 | J97: 9.05 | K97: 10.63 | L97: 10.53 | M97: 10.52
A98: CASH COLLATERAL USD MLIFT | B98: 10000 | C98: 19000 | D98: 19000 | E98: 7000 | F98: 0.02 | G98: 0.03 | H98: 0.03 | I98: 0.01 | J98: 100 | K98: 100 | L98: 100 | M98: 100
A99: GBP CASH | B99: 3444 | C99: 2657 | D99: 3132 | E99: 3051 | F99: 0.01 | G99: 0 | H99: 0.01 | I99: 0.01 | J99: 125.24 | K99: 134.63 | L99: 131.39 | M99: 132.28
A100: CHF CASH | B100: 3849 | C100: 15060 | D100: 15060 | E100: 6746 | F100: 0.01 | G100: 0.03 | H100: 0.03 | I100: 0.01 | J100: 110.34 | K100: 125.68 | L100: 124.57 | M100: 124.12
A101: IDR CASH | C101: 112841584 | D101: 112841584 | E101: 112551723 | G101: 0.01 | H101: 0.01 | I101: 0.01 | K101: 0.01 | L101: 0.01 | M101: 0.01
A102: BLK ICS USD LIQ AGENCY DIS | B102: 55105 | C102: 81092 | D102: 118984 | F102: 0.12 | G102: 0.11 | H102: 0.16 | J102: 1 | K102: 1 | L102: 1
A103: PHIHONG TECHNOLOGY LTD | B103: 20000 | F103: 0.05 | J103: 1.14
A104: MYR CASH | B104: 14536 | C104: 14536 | D104: 14536 | E104: 14536 | F104: 0.01 | G104: 0 | H104: 0 | I104: 0 | J104: 22.36 | K104: 23.76 | L104: 23.88 | M104: 24.18
A105: KINPO ELECTRONICS INC | B105: 81000 | F105: 0.14 | J105: 0.8
A106: COM2US | B106: 565 | F106: 0.04 | J106: 31.59
A107: PLAYAGS INC | B107: 2350 | F107: 0.06 | J107: 11.53
A108: LIGHT WONDER INC | C108: 6988 | D108: 6988 | G108: 0.81 | H108: 0.69 | K108: 83.94 | L108: 72.7
A109: 8X8 INC | B109: 6811 | F109: 0.04 | J109: 2.67
A110: CHEGG INC | B110: 6666 | F110: 0.02 | J110: 1.61
A111: MEDIATEK INC | B111: 45709 | F111: 4.32 | J111: 43.16
A112: MICRO E-MINI NASDAQ 100 MAR 25 | B112: 4 | F112: 0 | J112: 21226.5
A113: JPY/USD | C113: -2346605 | E113: -2102437 | G113: 0 | I113: 0 | K113: 1 | M113: 1
...

Sheet Sheet9
A2: FUND | B2: DFEU
B4: Column Labels
B5: Sum of Weight (%) | I5: Sum of Price
A6: Row Labels | B6: 45930 | C6: 45989 | D6: 46022 | E6: 46024 | F6: 46028 | G6: 46031 | H6: 46051 | I6: 45930 | J6: 45989 | K6: 46022 | L6: 46024 | M6: 46028 | N6: 46031 | O6: 46051
A7: BAE SYSTEMS PLC | B7: 13.95 | C7: 13.56 | D7: 13.33 | E7: 13.27 | F7: 13.43 | G7: 13.57 | H7: 13.47 | I7: 23.59 | J7: 18.84 | K7: 19.63 | L7: 20.15 | M7: 21.73 | N7: 23.66 | O7: 22.77
A8: RHEINMETALL AG | B8: 14.85 | C8: 13.49 | D8: 13.42 | E8: 13.36 | F8: 13.62 | G8: 13.79 | H8: 13.45 | I8: 1984.5 | J8: 1480.5 | K8: 1561 | L8: 1602 | M8: 1740.5 | N8: 1900 | O8: 1795.5
A9: THALES SA | B9: 13.05 | C9: 13.43 | D9: 12.91 | E9: 12.81 | F9: 12.68 | G9: 12.63 | H9: 12.53 | I9: 266.6 | J9: 225.4 | K9: 229.8 | L9: 235 | M9: 247.9 | N9: 266 | O9: 255.9
A10: ROLLS-ROYCE HOLDINGS PLC | B10: 12.22 | C10: 13.29 | D10: 13.54 | E10: 13.72 | F10: 13.45 | G10: 12.95 | H10: 12.42 | I10: 13.63 | J10: 12.19 | K10: 13.17 | L10: 13.75 | M10: 14.37 | N10: 14.91 | O10: 13.86
A11: LEONARDO FINMECCANICA SPA | B11: 11.07 | C11: 11.69 | D11: 11.56 | E11: 11.69 | F11: 11.68 | G11: 11.62 | H11: 11.52 | I11: 54.02 | J11: 46.91 | K11: 49.16 | L11: 51.22 | M11: 54.58 | N11: 58.48 | O11: 56.22
A12: SAAB CLASS B | B12: 8.77 | C12: 8.91 | D12: 9.61 | E12: 9.73 | F12: 9.4 | G12: 10.4 | H12: 11.14 | I12: 51.99 | J12: 43.45 | K12: 49.65 | L12: 51.8 | M12: 55.41 | N12: 63.62 | O12: 66.05
A13: EUR CASH | B13: 0.14 | C13: 0.09 | D13: 0.19 | E13: 0.19 | F13: 1.95 | G13: 0.17 | H13: 4.56 | I13: 100 | J13: 100 | K13: 100 | L13: 100 | M13: 100 | N13: 100 | O13: 100
A14: BABCOCK INTERNATIONAL GROUP PLC | B14: 3.92 | C14: 4.04 | D14: 4.2 | E14: 4.18 | F14: 4.3 | G14: 4.22 | H14: 4.32 | I14: 15.24 | J14: 12.94 | K14: 14.24 | L14: 14.62 | M14: 16.03 | N14: 16.93 | O14: 16.81
A15: ASELSAN ELEKTRONIK SANAYI VE TICAR | B15: 2.64 | C15: 2.71 | D15: 3.15 | E15: 3.03 | F15: 3.19 | G15: 3.23 | H15: 3.69 | I15: 4.4 | J15: 3.72 | K15: 4.59 | L15: 4.55 | M15: 5.11 | N15: 5.58 | O15: 6.16
A16: DASSAULT AVIATION SA | B16: 2.63 | C16: 3.04 | D16: 2.9 | E16: 2.88 | F16: 2.81 | G16: 2.76 | H16: 2.95 | I16: 284.6 | J16: 270.6 | K16: 273.8 | L16: 280.4 | M16: 291.6 | N16: 308.6 | O16: 320
A17: HENSOLDT AG | B17: 3.37 | C17: 2.54 | D17: 2.57 | E17: 2.6 | F17: 2.62 | G17: 2.7 | H17: 2.58 | I17: 110.3 | J17: 68.35 | K17: 73.4 | L17: 76.4 | M17: 82 | N17: 91.3 | O17: 84.55
... A34: OTOKAR OTOMOTIV SAVUNMA SANAYI | B34: 0.01 | C34: 0.01 | D34: 0.01 | E34: 0.01 | F34: 0.01 | G34: 0.01 | H34: 0.01 | I34: 10.49 | J34: 9.3 | K34: 9.63 | L34: 9.51 | M34: 9.93 | N34: 10.15 | O34: 8.33
A35: STOXX 600 INDUS DEC 25 | B35: 0 | C35: 0 | I35: 1070.7 | J35: 1036.2
A36: GBP/EUR | F36: 0 | H36: 0 | M36: 1 | O36: 4
A37: STOXX 600 INDUS MAR 26 | D37: 0 | E37: 0 | F37: 0 | G37: 0 | H37: 0 | K37: 1076.9 | L37: 1083.5 | M37: 1120.7 | N37: 1145.5 | O37: 1131.9
A38: SEK/EUR | F38: 0 | H38: 0 | M38: 1 | O38: 4
A39: TRY/EUR | F39: 0 | H39: 0 | M39: 1 | O39: 4
A40: NOK/EUR | F40: 0 | H40: 0 | M40: 1 | O40: 4
A41: CZK/EUR | F41: 0 | H41: 0 | M41: 1 | O41: 4
A42: CZK CASH | B42: 0 | C42: 0 | D42: 0 | E42: 0 | F42: -0.01 | G42: 0 | H42: -0.02 | I42: 4.11 | J42: 4.14 | K42: 4.14 | L42: 4.14 | M42: 4.14 | N42: 4.12 | O42: 4.11
A43: NOK CASH | B43: 0 | C43: 0 | D43: 0 | E43: 0 | F43: -0.04 | G43: 0 | H43: -0.11 | I43: 8.53 | J43: 8.52 | K43: 8.44 | L43: 8.47 | M43: 8.51 | N43: 8.51 | O43: 8.73
A44: TRY CASH | B44: 0 | C44: 0.01 | D44: 0.01 | E44: 0.01 | F44: -0.11 | G44: 0 | H44: -0.31 | I44: 2.05 | J44: 2.03 | K44: 1.98 | L44: 1.98 | M44: 1.99 | N44: 1.99 | O44: 1.93
A45: SEK CASH | B45: 0 | C45: 0 | D45: 0 | E45: 0 | F45: 0 | G45: 0 | H45: -0.99 | I45: 9.05 | J45: 9.14 | K45: 9.24 | L45: 9.25 | M45: 9.28 | N45: 9.33 | O45: 9.46
A46: GBP CASH | B46: 0.01 | C46: 0.11 | D46: 0.01 | E46: 0.01 | F46: -1.26 | G46: 0.02 | H46: -2.89 | I46: 114.58 | J46: 114.17 | K46: 114.53 | L46: 114.88 | M46: 115.48 | N46: 115.27 | O46: 115.38
A47: Grand Total | B47: 99.98 | C47: 100.02 | D47: 100 | E47: 100.04 | F47: 100 | G47: 99.99 | H47: 99.98 | I47: 5043.97 | J47: 4320.05 | K47: 4472.97 | L47: 4562.06 | M47: 4809.73 | N47: 5076.42 | O47: 4919.76

Sheet Funds
A1: FUND | B1: Date | C1: Ticker | D1: Name | E1: Type | F1: Sector | G1: Asset Class | H1: Market Value | I1: Weight (%) | J1: Notional Value | K1: Shares | L1: Price | M1: Location | N1: Exchange | O1: Market Currency
A2: AINF | B2: 45657 | C2: AVGO | D2: BROADCOM INC | E2: EQUITY | F2: Information Technology | G2: Equity | H2: 944052.48 | I2: 6.29 | J2: 944052.48 | K2: 4072 | L2: 231.84 | M2: United States | N2: NASDAQ | O2: USD
A3: AINF | B3: 45657 | C3: AAPL | D3: APPLE INC | E3: EQUITY | F3: Information Technology | G3: Equity | H3: 742996.14 | I3: 4.95 | J3: 742996.14 | K3: 2967 | L3: 250.42 | M3: United States | N3: NASDAQ | O3: USD
A4: AINF | B4: 45657 | C4: CSCO | D4: CISCO SYSTEMS INC | E4: EQUITY | F4: Information Technology | G4: Equity | H4: 740177.6 | I4: 4.93 | J4: 740177.6 | K4: 12503 | L4: 59.2 | M4: United States | N4: NASDAQ | O4: USD
A5: AINF | B5: 45657 | C5: 2330 | D5: TAIWAN SEMICONDUCTOR MANUFACTURING | E5: EQUITY | F5: Information Technology | G5: Equity | H5: 739280.76 | I5: 4.93 | J5: 739280.76 | K5: 22546 | L5: 32.79 | M5: Taiwan | N5: Taiwan Stock Exchange | O5: TWD
A6: AINF | B6: 45657 | C6: ASML | D6: ASML HOLDING NV | E6: EQUITY | F6: Information Technology | G6: Equity | H6: 723174.87 | I6: 4.82 | J6: 723174.87 | K6: 1029 | L6: 702.79 | M6: Netherlands | N6: Euronext Amsterdam | O6: EUR
A7: AINF | B7: 45657 | C7: NVDA | D7: NVIDIA CORP | E7: EQUITY | F7: Information Technology | G7: Equity | H7: 719257.24 | I7: 4.8 | J7: 719257.24 | K7: 5356 | L7: 134.29 | M7: United States | N7: NASDAQ | O7: USD
A8: AINF | B8: 45657 | C8: AMZN | D8: AMAZON COM INC | E8: EQUITY | F8: Consumer Discretionary | G8: Equity | H8: 705338.85 | I8: 4.7 | J8: 705338.85 | K8: 3215 | L8: 219.39 | M8: United States | N8: NASDAQ | O8: USD
A9: AINF | B9: 45657 | C9: ORCL | D9: ORACLE CORP | E9: EQUITY | F9: Information Technology | G9: Equity | H9: 700054.64 | I9: 4.67 | J9: 700054.64 | K9: 4201 | L9: 166.64 | M9: United States | N9: New York Stock Exchange Inc. | O9: USD
A10: AINF | B10: 45657 | C10: IBM | D10: INTERNATIONAL BUSINESS MACHINES CO | E10: EQUITY | F10: Information Technology | G10: Equity | H10: 696641.27 | I10: 4.64 | J10: 696641.27 | K10: 3169 | L10: 219.83 | M10: United States | N10: New York Stock Exchange Inc. | O10: USD
A11: AINF | B11: 45657 | C11: MSFT | D11: MICROSOFT CORP | E11: EQUITY | F11: Information Technology | G11: Equity | H11: 689152.5 | I11: 4.59 | J11: 689152.5 | K11: 1635 | L11: 421.5 | M11: United States | N11: NASDAQ | O11: USD
A12: AINF | B12: 45657 | C12: AMD | D12: ADVANCED MICRO DEVICES INC | E12: EQUITY | F12: Information Technology | G12: Equity | H12: 680772.44 | I12: 4.54 | J12: 680772.44 | K12: 5636 | L12: 120.79 | M12: United States | N12: NASDAQ | O12: USD
A13: AINF | B13: 45657 | C13: QCOM | D13: QUALCOMM INC | E13: EQUITY | F13: Information Technology | G13: Equity | H13: 672087.5 | I13: 4.48 | J13: 672087.5 | K13: 4375 | L13: 153.62 | M13: United States | N13: NASDAQ | O13: USD
A14: AINF | B14: 45657 | C14: PLTR | D14: PALANTIR TECHNOLOGIES INC CLASS A | E14: EQUITY | F14: Information Technology | G14: Equity | H14: 650266.74 | I14: 4.34 | J14: 650266.74 | K14: 8598 | L14: 75.63 | M14: United States | N14: NASDAQ | O14: USD
A15: AINF | B15: 45657 | C15: 5930 | D15: SAMSUNG ELECTRONICS LTD | E15: EQUITY | F15: Information Technology | G15: Equity | H15: 601366.17 | I15: 4.01 | J15: 601366.17 | K15: 16641 | L15: 36.14 | M15: Korea (South) | N15: Korea Exchange (Stock Market) | O15: KRW
A16: AINF | B16: 45657 | C16: PANW | D16: PALO ALTO NETWORKS INC | E16: EQUITY | F16: Information Technology | G16: Equity | H16: 472550.12 | I16: 3.15 | J16: 472550.12 | K16: 2597 | L16: 181.96 | M16: United States | N16: NASDAQ | O16: USD
A17: AINF | B17: 45657 | C17: MRVL | D17: MARVELL TECHNOLOGY INC | E17: EQUITY | F17: Information Technology | G17: Equity | H17: 377076.3 | I17: 2.51 | J17: 377076.3 | K17: 3414 | L17: 110.45 | M17: United States | N17: NASDAQ | O17: USD
A18: AINF | B18: 45657 | C18: GOOGL | D18: ALPHABET INC CLASS A | E18: EQUITY | F18: Communication | G18: Equity | H18: 370649.4 | I18: 2.47 | J18: 370649.4 | K18: 1958 | L18: 189.3 | M18: United States | N18: NASDAQ | O18: USD
A19: AINF | B19: 45657 | C19: MU | D19: MICRON TECHNOLOGY INC | E19: EQUITY | F19: Information Technology | G19: Equity | H19: 367610.88 | I19: 2.45 | J19: 367610.88 | K19: 4368 | L19: 84.16 | M19: United States | N19: NASDAQ | O19: USD
A20: AINF | B20: 45657 | C20: GOOG | D20: ALPHABET INC CLASS C | E20: EQUITY | F20: Communication | G20: Equity | H20: 355741.92 | I20: 2.37 | J20: 355741.92 | K20: 1868 | L20: 190.44 | M20: United States | N20: NASDAQ | O20: USD
A21: AINF | B21: 45657 | C21: EQIX | D21: EQUINIX REIT INC | E21: EQUITY | F21: Real Estate | G21: Equity | H21: 352640.86 | I21: 2.35 | J21: 352640.86 | K21: 374 | L21: 942.89 | M21: United States | N21: NASDAQ | O21: USD
A22: AINF | B22: 45657 | C22: INTC | D22: INTEL CORPORATION CORP | E22: EQUITY | F22: Information Technology | G22: Equity | H22: 337702.15 | I22: 2.25 | J22: 337702.15 | K22: 16843 | L22: 20.05 | M22: United States | N22: NASDAQ | O22: USD
A23: AINF | B23: 45657 | C23: KLAC | D23: KLA CORP | E23: EQUITY | F23: Information Technology | G23: Equity | H23: 331443.12 | I23: 2.21 | J23: 331443.12 | K23: 526 | L23: 630.12 | M23: United States | N23: NASDAQ | O23: USD
A24: AINF | B24: 45657 | C24: 8035 | D24: TOKYO ELECTRON LTD | E24: EQUITY | F24: Information Technology | G24: Equity | H24: 292386.74 | I24: 1.95 | J24: 292386.74 | K24: 1900 | L24: 153.89 | M24: Japan | N24: Tokyo Stock Exchange | O24: JPY
A25: AINF | B25: 45657 | C25: 2454 | D25: MEDIATEK INC | E25: EQUITY | F25: Information Technology | G25: Equity | H25: 271048.82 | I25: 1.81 | J25: 271048.82 | K25: 6280 | L25: 43.16 | M25: Taiwan | N25: Taiwan Stock Exchange | O25: TWD
A26: AINF | B26: 45657 | C26: 2317 | D26: HON HAI PRECISION INDUSTRY LTD | E26: EQUITY | F26: Information Technology | G26: Equity | H26: 270574.2 | I26: 1.8 | J26: 270574.2 | K26: 48210 | L26: 5.61 | M26: Taiwan | N26: Taiwan Stock Exchange | O26: TWD
A27: AINF | B27: 45657 | C27: SNOW | D27: SNOWFLAKE INC | E27: EQUITY | F27: Information Technology | G27: Equity | H27: 204438.84 | I27: 1.36 | J27: 204438.84 | K27: 1324 | L27: 154.41 | M27: United States | N27: New York Stock Exchange Inc. | O27: USD
A28: AINF | B28: 45657 | C28: DELL | D28: DELL TECHNOLOGIES INC CLASS C | E28: EQUITY | F28: Information Technology | G28: Equity | H28: 144626.2 | I28: 0.96 | J28: 144626.2 | K28: 1255 | L28: 115.24 | M28: United States | N28: New York Stock Exchange Inc. | O28: USD
A29: AINF | B29: 45657 | C29: MCHP | D29: MICROCHIP TECHNOLOGY INC | E29: EQUITY | F29: Information Technology | G29: Equity | H29: 120779.1 | I29: 0.81 | J29: 120779.1 | K29: 2106 | L29: 57.35 | M29: United States | N29: NASDAQ | O29: USD
A30: AINF | B30: 45657 | C30: HPE | D30: HEWLETT PACKARD ENTERPRISE | E30: EQUITY | F30: Information Technology | G30: Equity | H30: 110166 | I30: 0.73 | J30: 110166 | K30: 5160 | L30: 21.35 | M30: United States | N30: New York Stock Exchange Inc. | O30: USD
A31: AINF | B31: 45657 | C31: NTAP | D31: NETAPP INC | E31: EQUITY | F31: Information Technology | G31: Equity | H31: 94256.96 | I31: 0.63 | J31: 94256.96 | K31: 812 | L31: 116.08 | M31: United States | N31: NASDAQ | O31: USD
A32: AINF | B32: 45657 | C32: PSTG | D32: PURE STORAGE INC CLASS A | E32: EQUITY | F32: Information Technology | G32: Equity | H32: 80104.72 | I32: 0.53 | J32: 80104.72 | K32: 1304 | L32: 61.43 | M32: United States | N32: New York Stock Exchange Inc. | O32: USD
A33: AINF | B33: 45657 | C33: ZBRA | D33: ZEBRA TECHNOLOGIES CORP CLASS A | E33: EQUITY | F33: Information Technology | G33: Equity | H33: 79175.1 | I33: 0.53 | J33: 79175.1 | K33: 205 | L33: 386.22 | M33: United States | N33: NASDAQ | O33: USD
A34: AINF | B34: 45657 | C34: 5935 | D34: SAMSUNG ELECTRONICS NON VOTING PRE | E34: EQUITY | F34: Information Technology | G34: Equity | H34: 78693.2 | I34: 0.52 | J34: 78693.2 | K34: 2621 | L34: 30.02 | M34: Korea (South) | N34: Korea Exchange (Stock Market) | O34: KRW
A35: AINF | B35: 45657 | C35: MDB | D35: MONGODB INC CLASS A | E35: EQUITY | F35: Information Technology | G35: Equity | H35: 68446.14 | I35: 0.46 | J35: 68446.14 | K35: 294 | L35: 232.81 | M35: United States | N35: NASDAQ | O35: USD
A36: AINF | B36: 45657 | C36: NTNX | D36: NUTANIX INC CLASS A | E36: EQUITY | F36: Information Technology | G36: Equity | H36: 65217.88 | I36: 0.43 | J36: 65217.88 | K36: 1066 | L36: 61.18 | M36: United States | N36: NASDAQ | O36: USD
A37: AINF | B37: 45657 | C37: JNPR | D37: JUNIPER NETWORKS INC | E37: EQUITY | F37: Information Technology | G37: Equity | H37: 49284.2 | I37: 0.33 | J37: 49284.2 | K37: 1316 | L37: 37.45 | M37: United States | N37: New York Stock Exchange Inc. | O37: USD
A38: AINF | B38: 45657 | C38: 992 | D38: LENOVO GROUP LTD | E38: EQUITY | F38: Information Technology | G38: Equity | H38: 44119.75 | I38: 0.29 | J38: 44119.75 | K38: 34000 | L38: 1.3 | M38: China | N38: Hong Kong Exchanges And Clearing Ltd | O38: HKD
A39: AINF | B39: 45657 | C39: CVLT | D39: COMMVAULT SYSTEMS INC | E39: EQUITY | F39: Information Technology | G39: Equity | H39: 25352.88 | I39: 0.17 | J39: 25352.88 | K39: 168 | L39: 150.91 | M39: United States | N39: NASDAQ | O39: USD
A40: AINF | B40: 45657 | C40: USD | D40: USD CASH | E40: CASH | F40: Cash and/or Derivatives | G40: Cash | H40: 6862.29 | I40: 0.05 | J40: 6862.29 | K40: 6862 | L40: 100 | M40: United States | N40: - | O40: USD
A41: AINF | B41: 45657 | C41: KRW | D41: KRW CASH | E41: CASH | F41: Cash and/or Derivatives | G41: Cash | H41: 6523.72 | I41: 0.04 | J41: 6523.72 | K41: 9603899 | L41: 0.07 | M41: Korea (South) | N41: - | O41: KRW
A42: AINF | B42: 45657 | C42: FSLY | D42: FASTLY INC CLASS A | E42: EQUITY | F42: Information Technology | G42: Equity | H42: 5003.2 | I42: 0.03 | J42: 5003.2 | K42: 530 | L42: 9.44 | M42: United States | N42: New York Stock Exchange Inc. | O42: USD
A43: AINF | B43: 45657 | C43: TWD | D43: TWD CASH | E43: CASH | F43: Cash and/or Derivatives | G43: Cash | H43: 3793.45 | I43: 0.03 | J43: 3793.45 | K43: 124366 | L43: 3.05 | M43: Taiwan | N43: - | O43: TWD
A44: AINF | B44: 45657 | C44: ICSUAGD | D44: BLK ICS USD LIQ AGENCY DIS | E44: FUND | F44: Cash and/or Derivatives | G44: Money Market | H44: 3579.92 | I44: 0.02 | J44: 3579.92 | K44: 3580 | L44: 1 | M44: Ireland | N44: - | O44: USD
A45: AINF | B45: 45657 | C45: EUR | D45: EUR CASH | E45: CASH | F45: Cash and/or Derivatives | G45: Cash | H45: 3239.24 | I45: 0.02 | J45: 3239.24 | K45: 3128 | L45: 103.55 | M45: European Union | N45: - | O45: EUR
A46: AINF | B46: 45657 | C46: 2388 | D46: VIA TECHNOLOGIES INC | E46: EQUITY | F46: Information Technology | G46: Equity | H46: 1014.67 | I46: 0.01 | J46: 1014.67 | K46: 331 | L46: 3.07 | M46: Taiwan | N46: Taiwan Stock Exchange | O46: TWD
A47: AINF | B47: 45657 | C47: HKD | D47: HKD CASH | E47: CASH | F47: Cash and/or Derivatives | G47: Cash | H47: 803.31 | I47: 0.01 | J47: 803.31 | K47: 6240 | L47: 12.87 | M47: Hong Kong | N47: - | O47: HKD
A48: AINF | B48: 45657 | C48: JPY | D48: JPY CASH | E48: CASH | F48: Cash and/or Derivatives | G48: Cash | H48: 450.46 | I48: 0 | J48: 450.46 | K48: 70794 | L48: 0.64 | M48: Japan | N48: - | O48: JPY
A49: AINF | B49: 45747 | C49: PLTR | D49: PALANTIR TECHNOLOGIES INC CLASS A | E49: EQUITY | F49: Information Technology | G49: Equity | H49: 3012826.8 | I49: 5.08 | J49: 3012826.8 | K49: 35697 | L49: 84.4 | M49: United States | N49: NASDAQ | O49: USD
A50: AINF | B50: 45747 | C50: AAPL | D50: APPLE INC | E50: EQUITY | F50: Information Technology | G50: Equity | H50: 3010972.1 | I50: 5.08 | J50: 3010972.1 | K50: 13555 | L50: 222.13 | M50: United States | N50: NASDAQ | O50: USD
A51: AINF | B51: 45747 | C51: AMD | D51: ADVANCED MICRO DEVICES INC | E51: EQUITY | F51: Information Technology | G51: Equity | H51: 2975555.9 | I51: 5.02 | J51: 2975555.9 | K51: 28962 | L51: 102.74 | M51: United States | N51: NASDAQ | O51: USD
A52: AINF | B52: 45747 | C52: CSCO | D52: CISCO SYSTEMS INC | E52: EQUITY | F52: Information Technology | G52: Equity | H52: 2939370.7 | I52: 4.96 | J52: 2939370.7 | K52: 47632 | L52: 61.71 | M52: United States | N52: NASDAQ | O52: USD
A53: AINF | B53: 45747 | C53: IBM | D53: INTERNATIONAL BUSINESS MACHINES CO | E53: EQUITY | F53: Information Technology | G53: Equity | H53: 2875255.6 | I53: 4.85 | J53: 2875255.6 | K53: 11563 | L53: 248.66 | M53: United States | N53: New York Stock Exchange Inc. | O53: USD
A54: AINF | B54: 45747 | C54: QCOM | D54: QUALCOMM INC | E54: EQUITY | F54: Information Technology | G54: Equity | H54: 2873428.7 | I54: 4.85 | J54: 2873428.7 | K54: 18706 | L54: 153.61 | M54: United States | N54: NASDAQ | O54: USD
A55: AINF | B55: 45747 | C55: MSFT | D55: MICROSOFT CORP | E55: EQUITY | F55: Information Technology | G55: Equity | H55: 2816926.6 | I55: 4.75 | J55: 2816926.6 | K55: 7504 | L55: 375.39 | M55: United States | N55: NASDAQ | O55: USD
A56: AINF | B56: 45747 | C56: AMZN | D56: AMAZON COM INC | E56: EQUITY | F56: Consumer Discretionary | G56: Equity | H56: 2789021.3 | I56: 4.71 | J56: 2789021.3 | K56: 14659 | L56: 190.26 | M56: United States | N56: NASDAQ | O56: USD
A57: AINF | B57: 45747 | C57: ORCL | D57: ORACLE CORP | E57: EQUITY | F57: Information Technology | G57: Equity | H57: 2691062.9 | I57: 4.54 | J57: 2691062.9 | K57: 19248 | L57: 139.81 | M57: United States | N57: New York Stock Exchange Inc. | O57: USD
A58: AINF | B58: 45747 | C58: ASML | D58: ASML HOLDING NV | E58: EQUITY | F58: Information Technology | G58: Equity | H58: 2667499.9 | I58: 4.5 | J58: 2667499.9 | K58: 4075 | L58: 654.6 | M58: Netherlands | N58: Euronext Amsterdam | O58: EUR
A59: AINF | B59: 45747 | C59: NVDA | D59: NVIDIA CORP | E59: EQUITY | F59: Information Technology | G59: Equity | H59: 2665172.6 | I59: 4.5 | J59: 2665172.6 | K59: 24591 | L59: 108.38 | M59: United States | N59: NASDAQ | O59: USD
A60: AINF | B60: 45747 | C60: 2330 | D60: TAIWAN SEMICONDUCTOR MANUFACTURING | E60: EQUITY | F60: Information Technology | G60: Equity | H60: 2654862.1 | I60: 4.48 | J60: 2654862.1 | K60: 96866 | L60: 27.41 | M60: Taiwan | N60: Taiwan Stock Exchange | O60: TWD
A61: AINF | B61: 45747 | C61: 5930 | D61: SAMSUNG ELECTRONICS LTD | E61: EQUITY | F61: Information Technology | G61: Equity | H61: 2618683.5 | I61: 4.42 | J61: 2618683.5 | K61: 66713 | L61: 39.25 | M61: Korea (South) | N61: Korea Exchange (Stock Market) | O61: KRW
A62: AINF | B62: 45747 | C62: AVGO | D62: BROADCOM INC | E62: EQUITY | F62: Information Technology | G62: Equity | H62: 2486837.8 | I62: 4.2 | J62: 2486837.8 | K62: 14853 | L62: 167.43 | M62: United States | N62: NASDAQ | O62: USD
A63: AINF | B63: 45747 | C63: PANW | D63: PALO ALTO NETWORKS INC | E63: EQUITY | F63: Information Technology | G63: Equity | H63: 2021742.7 | I63: 3.41 | J63: 2021742.7 | K63: 11848 | L63: 170.64 | M63: United States | N63: NASDAQ | O63: USD
A64: AINF | B64: 45747 | C64: INTC | D64: INTEL CORPORATION CORP | E64: EQUITY | F64: Information Technology | G64: Equity | H64: 1734044.8 | I64: 2.93 | J64: 1734044.8 | K64: 76356 | L64: 22.71 | M64: United States | N64: NASDAQ | O64: USD
A65: AINF | B65: 45747 | C65: MU | D65: MICRON TECHNOLOGY INC | E65: EQUITY | F65: Information Technology | G65: Equity | H65: 1724071.4 | I65: 2.91 | J65: 1724071.4 | K65: 19842 | L65: 86.89 | M65: United States | N65: NASDAQ | O65: USD
A66: AINF | B66: 45747 | C66: KLAC | D66: KLA CORP | E66: EQUITY | F66: Information Technology | G66: Equity | H66: 1634919 | I66: 2.76 | J66: 1634919 | K66: 2405 | L66: 679.8 | M66: United States | N66: NASDAQ | O66: USD
A67: AINF | B67: 45747 | C67: EQIX | D67: EQUINIX REIT INC | E67: EQUITY | F67: Real Estate | G67: Equity | H67: 1420339.7 | I67: 2.4 | J67: 1420339.7 | K67: 1742 | L67: 815.35 | M67: United States | N67: NASDAQ | O67: USD
A68: AINF | B68: 45747 | C68: GOOGL | D68: ALPHABET INC CLASS A | E68: EQUITY | F68: Communication | G68: Equity | H68: 1380625.9 | I68: 2.33 | J68: 1380625.9 | K68: 8928 | L68: 154.64 | M68: United States | N68: NASDAQ | O68: USD
A69: AINF | B69: 45747 | C69: GOOG | D69: ALPHABET INC CLASS C | E69: EQUITY | F69: Communication | G69: Equity | H69: 1317487.6 | I69: 2.22 | J69: 1317487.6 | K69: 8433 | L69: 156.23 | M69: United States | N69: NASDAQ | O69: USD
A70: AINF | B70: 45747 | C70: 2454 | D70: MEDIATEK INC | E70: EQUITY | F70: Information Technology | G70: Equity | H70: 1191123.6 | I70: 2.01 | J70: 1191123.6 | K70: 28452 | L70: 41.86 | M70: Taiwan | N70: Taiwan Stock Exchange | O70: TWD
A71: AINF | B71: 45747 | C71: 8035 | D71: TOKYO ELECTRON LTD | E71: EQUITY | F71: Information Technology | G71: Equity | H71: 1129624.2 | I71: 1.91 | J71: 1129624.2 | K71: 8400 | L71: 134.48 | M71: Japan | N71: Tokyo Stock Exchange | O71: JPY
A72: AINF | B72: 45747 | C72: 2317 | D72: HON HAI PRECISION INDUSTRY LTD | E72: EQUITY | F72: Information Technology | G72: Equity | H72: 955128.68 | I72: 1.61 | J72: 955128.68 | K72: 217210 | L72: 4.4 | M72: Taiwan | N72: Taiwan Stock Exchange | O72: TWD
A73: AINF | B73: 45747 | C73: MRVL | D73: MARVELL TECHNOLOGY INC | E73: EQUITY | F73: Information Technology | G73: Equity | H73: 954335 | I73: 1.61 | J73: 954335 | K73: 15500 | L73: 61.57 | M73: United States | N73: NASDAQ | O73: USD
A74: AINF | B74: 45747 | C74: SNOW | D74: SNOWFLAKE INC | E74: EQUITY | F74: Information Technology | G74: Equity | H74: 876667.68 | I74: 1.48 | J74: 876667.68 | K74: 5998 | L74: 146.16 | M74: United States | N74: New York Stock Exchange Inc. | O74: USD
A75: AINF | B75: 45747 | C75: DELL | D75: DELL TECHNOLOGIES INC CLASS C | E75: EQUITY | F75: Information Technology | G75: Equity | H75: 524021.35 | I75: 0.88 | J75: 524021.35 | K75: 5749 | L75: 91.15 | M75: United States | N75: New York Stock Exchange Inc. | O75: USD
A76: AINF | B76: 45747 | C76: MCHP | D76: MICROCHIP TECHNOLOGY INC | E76: EQUITY | F76: Information Technology | G76: Equity | H76: 464736 | I76: 0.78 | J76: 464736 | K76: 9600 | L76: 48.41 | M76: United States | N76: NASDAQ | O76: USD
A77: AINF | B77: 45747 | C77: HPE | D77: HEWLETT PACKARD ENTERPRISE | E77: EQUITY | F77: Information Technology | G77: Equity | H77: 358392.61 | I77: 0.6 | J77: 358392.61 | K77: 23227 | L77: 15.43 | M77: United States | N77: New York Stock Exchange Inc. | O77: USD
A78: AINF | B78: 45747 | C78: 5935 | D78: SAMSUNG ELECTRONICS NON VOTING PRE | E78: EQUITY | F78: Information Technology | G78: Equity | H78: 341250.39 | I78: 0.58 | J78: 341250.39 | K78: 10646 | L78: 32.05 | M78: Korea (South) | N78: Korea Exchange (Stock Market) | O78: KRW
A79: AINF | B79: 45747 | C79: NTNX | D79: NUTANIX INC CLASS A | E79: EQUITY | F79: Information Technology | G79: Equity | H79: 331318.26 | I79: 0.56 | J79: 331318.26 | K79: 4746 | L79: 69.81 | M79: United States | N79: NASDAQ | O79: USD
A80: AINF | B80: 45747 | C80: NTAP | D80: NETAPP INC | E80: EQUITY | F80: Information Technology | G80: Equity | H80: 321845.76 | I80: 0.54 | J80: 321845.76 | K80: 3664 | L80: 87.84 | M80: United States | N80: NASDAQ | O80: USD
A81: AINF | B81: 45747 | C81: ZBRA | D81: ZEBRA TECHNOLOGIES CORP CLASS A | E81: EQUITY | F81: Information Technology | G81: Equity | H81: 260802.88 | I81: 0.44 | J81: 260802.88 | K81: 923 | L81: 282.56 | M81: United States | N81: NASDAQ | O81: USD
A82: AINF | B82: 45747 | C82: PSTG | D82: PURE STORAGE INC CLASS A | E82: EQUITY | F82: Information Technology | G82: Equity | H82: 259599.28 | I82: 0.44 | J82: 259599.28 | K82: 5864 | L82: 44.27 | M82: United States | N82: New York Stock Exchange Inc. | O82: USD
A83: AINF | B83: 45747 | C83: MDB | D83: MONGODB INC CLASS A | E83: EQUITY | F83: Information Technology | G83: Equity | H83: 231878.8 | I83: 0.39 | J83: 231878.8 | K83: 1322 | L83: 175.4 | M83: United States | N83: NASDAQ | O83: USD
A84: AINF | B84: 45747 | C84: JNPR | D84: JUNIPER NETWORKS INC | E84: EQUITY | F84: Information Technology | G84: Equity | H84: 213159.1 | I84: 0.36 | J84: 213159.1 | K84: 5890 | L84: 36.19 | M84: United States | N84: New York Stock Exchange Inc. | O84: USD
A85: AINF | B85: 45747 | C85: 992 | D85: LENOVO GROUP LTD | E85: EQUITY | F85: Information Technology | G85: Equity | H85: 204742.75 | I85: 0.35 | J85: 204742.75 | K85: 152000 | L85: 1.35 | M85: China | N85: Hong Kong Exchanges And Clearing Ltd | O85: HKD
A86: AINF | B86: 45747 | C86: CVLT | D86: COMMVAULT SYSTEMS INC | E86: EQUITY | F86: Information Technology | G86: Equity | H86: 117846.72 | I86: 0.2 | J86: 117846.72 | K86: 747 | L86: 157.76 | M86: United States | N86: NASDAQ | O86: USD
A87: AINF | B87: 45747 | C87: USD | D87: USD CASH | E87: CASH | F87: Cash and/or Derivatives | G87: Cash | H87: 95002.04 | I87: 0.16 | J87: 95002.04 | K87: 95002 | L87: 100 | M87: United States | N87: - | O87: USD
A88: AINF | B88: 45747 | C88: KRW | D88: KRW CASH | E88: CASH | F88: Cash and/or Derivatives | G88: Cash | H88: 25706.63 | I88: 0.04 | J88: 25706.63 | K88: 37853017 | L88: 0.07 | M88: Korea (South) | N88: - | O88: KRW
A89: AINF | B89: 45747 | C89: JPY | D89: JPY CASH | E89: CASH | F89: Cash and/or Derivatives | G89: Cash | H89: 17260.47 | I89: 0.03 | J89: 17260.47 | K89: 2581131 | L89: 0.67 | M89: Japan | N89: - | O89: JPY
A90: AINF | B90: 45747 | C90: TWD | D90: TWD CASH | E90: CASH | F90: Cash and/or Derivatives | G90: Cash | H90: 17165.64 | I90: 0.03 | J90: 17165.64 | K90: 569942 | L90: 3.01 | M90: Taiwan | N90: - | O90: TWD
A91: AINF | B91: 45747 | C91: FSLY | D91: FASTLY INC CLASS A | E91: EQUITY | F91: Information Technology | G91: Equity | H91: 16420.02 | I91: 0.03 | J91: 16420.02 | K91: 2594 | L91: 6.33 | M91: United States | N91: New York Stock Exchange Inc. | O91: USD
A92: AINF | B92: 45747 | C92: 2388 | D92: VIA TECHNOLOGIES INC | E92: EQUITY | F92: Information Technology | G92: Equity | H92: 14377.15 | I92: 0.02 | J92: 14377.15 | K92: 6331 | L92: 2.27 | M92: Taiwan | N92: Taiwan Stock Exchange | O92: TWD
A93: AINF | B93: 45747 | C93: CITFT | D93: CASH COLLATERAL USD CITFT | E93: CASH | F93: Cash and/or Derivatives | G93: Cash Collateral and Margins | H93: 11000 | I93: 0.02 | J93: 11000 | K93: 11000 | L93: 100 | M93: United States | N93: - | O93: USD
A94: AINF | B94: 45747 | C94: ICSUAGD | D94: BLK ICS USD LIQ AGENCY DIS | E94: FUND | F94: Cash and/or Derivatives | G94: Money Market | H94: 10142.81 | I94: 0.02 | J94: 10142.81 | K94: 10143 | L94: 1 | M94: Ireland | N94: - | O94: USD
A95: AINF | B95: 45747 | C95: EUR | D95: EUR CASH | E95: CASH | F95: Cash and/or Derivatives | G95: Cash | H95: 3854.8 | I95: 0.01 | J95: 3854.8 | K95: 3569 | L95: 108.02 | M95: European Union | N95: - | O95: EUR
A96: AINF | B96: 45747 | C96: HKD | D96: HKD CASH | E96: CASH | F96: Cash and/or Derivatives | G96: Cash | H96: 1911.81 | I96: 0 | J96: 1911.81 | K96: 14874 | L96: 12.85 | M96: Hong Kong | N96: - | O96: HKD
A97: AINF | B97: 45747 | C97: HWBM5 | D97: MICRO E-MINI NASDAQ 100 JUN 25 | E97: FUTURE | F97: Cash and/or Derivatives | G97: Futures | H97: 0 | I97: 0 | J97: 155516 | K97: 4 | L97: 19439.5 | M97: - | N97: Chicago Mercantile Exchange | O97: USD
A98: AINF | B98: 45777 | C98: PLTR | D98: PALANTIR TECHNOLOGIES INC CLASS A | E98: EQUITY | F98: Information Technology | G98: Equity | H98: 4227952.7 | I98: 6.98 | J98: 4227952.7 | K98: 35697 | L98: 118.44 | M98: United States | N98: NASDAQ | O98: USD
A99: AINF | B99: 45777 | C99: MSFT | D99: MICROSOFT CORP | E99: EQUITY | F99: Information Technology | G99: Equity | H99: 2966031 | I99: 4.9 | J99: 2966031 | K99: 7504 | L99: 395.26 | M99: United States | N99: NASDAQ | O99: USD
A100: AINF | B100: 45777 | C100: AAPL | D100: APPLE INC | E100: EQUITY | F100: Information Technology | G100: Equity | H100: 2880437.5 | I100: 4.76 | J100: 2880437.5 | K100: 13555 | L100: 212.5 | M100: United States | N100: NASDAQ | O100: USD
...

Sheet Sheet2
A1: Row Labels | B1: Dec | C1: Mar | D1: Apr | E1: May | F1: Variance
A2: MRVL | B2: 2.51 | C2: 1.61 | D2: 1.49 | E2: 1.47 | F2: -1.04
A3: AVGO | B3: 6.29 | C3: 4.2 | D3: 4.72 | E3: 5.36 | F3: -0.93
A4: AAPL | B4: 4.95 | C4: 5.08 | D4: 4.76 | E4: 4.05 | F4: -0.9
A5: CSCO | B5: 4.93 | C5: 4.96 | D5: 4.54 | E5: 4.48 | F5: -0.45
A6: QCOM | B6: 4.48 | C6: 4.85 | D6: 4.59 | E6: 4.14 | F6: -0.34
A7: 2330 | B7: 4.93 | C7: 4.48 | D7: 4.54 | E7: 4.67 | F7: -0.26
A8: ASML | B8: 4.82 | C8: 4.5 | D8: 4.46 | E8: 4.59 | F8: -0.23
A9: AMZN | B9: 4.7 | C9: 4.71 | D9: 4.46 | E9: 4.5 | F9: -0.2
A10: GOOG | B10: 2.37 | C10: 2.22 | D10: 2.24 | E10: 2.18 | F10: -0.19
A11: GOOGL | B11: 2.47 | C11: 2.33 | D11: 2.34 | E11: 2.29 | F11: -0.18
A12: IBM | B12: 4.64 | C12: 4.85 | D12: 4.62 | E12: 4.46 | F12: -0.18
A13: ZBRA | B13: 0.53 | C13: 0.44 | D13: 0.38 | E13: 0.4 | F13: -0.13
A14: HPE | B14: 0.73 | C14: 0.6 | D14: 0.62 | E14: 0.61 | F14: -0.12
A15: 2317 | B15: 1.8 | C15: 1.61 | D15: 1.59 | E15: 1.69 | F15: -0.11
A16: MDB | B16: 0.46 | C16: 0.39 | D16: 0.38 | E16: 0.37 | F16: -0.09
A17: NTAP | B17: 0.63 | C17: 0.54 | D17: 0.54 | E17: 0.54 | F17: -0.09
A18: PSTG | B18: 0.53 | C18: 0.44 | D18: 0.44 | E18: 0.47 | F18: -0.06
A19: EQIX | B19: 2.35 | C19: 2.4 | D19: 2.48 | E19: 2.31 | F19: -0.04
A20: KRW | B20: 0.04 | C20: 0.04 | D20: 0.04 | E20: 0.01 | F20: -0.03
A21: 2454 | B21: 1.81 | C21: 2.01 | D21: 1.98 | E21: 1.79 | F21: -0.02
A22: 992 | B22: 0.29 | C22: 0.35 | D22: 0.29 | E22: 0.27 | F22: -0.02
A23: JNPR | B23: 0.33 | C23: 0.36 | D23: 0.35 | E23: 0.32 | F23: -0.01
A24: EUR | B24: 0.02 | C24: 0.01 | D24: 0.02 | E24: 0.01 | F24: -0.01
A25: HKD | B25: 0.01 | C25: 0 | D25: 0 | E25: 0 | F25: -0.01
A26: TWD | B26: 0.03 | C26: 0.03 | D26: 0.03 | E26: 0.03 | F26: 0
A27: FSLY | B27: 0.03 | C27: 0.03 | D27: 0.02 | E27: 0.03 | F27: 0
A28: ICSUAGD | B28: 0.02 | C28: 0.02 | D28: 0.02 | E28: 0.02 | F28: 0
A29: HWBM5 | C29: 0 | D29: 0 | E29: 0 | F29: 0
A30: ORCL | B30: 4.67 | C30: 4.54 | D30: 4.47 | E30: 4.68 | F30: 0.01
A31: 2388 | B31: 0.01 | C31: 0.02 | D31: 0.02 | E31: 0.02 | F31: 0.01
A32: 5935 | B32: 0.52 | C32: 0.58 | D32: 0.58 | E32: 0.53 | F32: 0.01
A33: MCHP | B33: 0.81 | C33: 0.78 | D33: 0.73 | E33: 0.83 | F33: 0.02
A34: CITFT | C34: 0.02 | D34: 0.02 | E34: 0.02 | F34: 0.02
A35: DELL | B35: 0.96 | C35: 0.88 | D35: 0.87 | E35: 0.98 | F35: 0.02
A36: CVLT | B36: 0.17 | C36: 0.2 | D36: 0.21 | E36: 0.2 | F36: 0.03
A37: JPY | B37: 0 | C37: 0.03 | D37: 0.03 | E37: 0.03 | F37: 0.03
A38: Grand Total | B38: 99.97 | C38: 100 | D38: 99.98 | E38: 100.02 | F38: 0.05
A39: 5930 | B39: 4.01 | C39: 4.42 | D39: 4.3 | E39: 4.06 | F39: 0.05
A40: INTC | B40: 2.25 | C40: 2.93 | D40: 2.53 | E40: 2.31 | F40: 0.06
A41: NTNX | B41: 0.43 | C41: 0.56 | D41: 0.54 | E41: 0.54 | F41: 0.11
A42: PANW | B42: 3.15 | C42: 3.41 | D42: 3.66 | E42: 3.29 | F42: 0.14
A43: 8035 | B43: 1.95 | C43: 1.91 | D43: 2.06 | E43: 2.1 | F43: 0.15
A44: USD | B44: 0.05 | C44: 0.16 | D44: 0.17 | E44: 0.25 | F44: 0.2
A45: NVDA | B45: 4.8 | C45: 4.5 | D45: 4.42 | E45: 5.11 | F45: 0.31
A46: AMD | B46: 4.54 | C46: 5.02 | D46: 4.66 | E46: 4.89 | F46: 0.35
A47: MU | B47: 2.45 | C47: 2.91 | D47: 2.52 | E47: 2.87 | F47: 0.42
A48: SNOW | B48: 1.36 | C48: 1.48 | D48: 1.58 | E48: 1.81 | F48: 0.45
A49: MSFT | B49: 4.59 | C49: 4.75 | D49: 4.9 | E49: 5.14 | F49: 0.55
A50: KLAC | B50: 2.21 | C50: 2.76 | D50: 2.79 | E50: 2.78 | F50: 0.57
A51: PLTR | B51: 4.34 | C51: 5.08 | D51: 6.98 | E51: 6.52 | F51: 2.18

Sheet WQTM
A1: Date | B1: Fund Name | C1: Fund Ticker Symbol | D1: Security Description | E1: Security Ticker | F1: Shares | G1: Mkt Value | H1: Weight %
A2: 2026-02-05T00:00:00 | B2: WisdomTree Quantum Computing UCITS ETF - USD Acc | C2: WQTM LN | D2: D-Wave Quantum Inc | E2: QBTS US | F2: 358772 | G2: 6174466.1 | H2: 0.0452234
A3: 2026-02-05T00:00:00 | B3: WisdomTree Quantum Computing UCITS ETF - USD Acc | C3: WQTM LN | D3: Intel Corp | E3: INTC UQ | F3: 125789 | G3: 6068061.4 | H3: 0.044444
A4: 2026-02-05T00:00:00 | B4: WisdomTree Quantum Computing UCITS ETF - USD Acc | C4: WQTM LN | D4: Ionq Inc | E4: IONQ US | F4: 184908 | G4: 5626750.4 | H4: 0.0412118
A5: 2026-02-05T00:00:00 | B5: WisdomTree Quantum Computing UCITS ETF - USD Acc | C5: WQTM LN | D5: Google Inc | E5: GOOGL UQ | F5: 16210 | G5: 5369562.5 | H5: 0.0393281
A6: 2026-02-05T00:00:00 | B6: WisdomTree Quantum Computing UCITS ETF - USD Acc | C6: WQTM LN | D6: Quantum Computing Inc | E6: QUBT US | F6: 642910 | G6: 5021127.1 | H6: 0.036776
A7: 2026-02-05T00:00:00 | B7: WisdomTree Quantum Computing UCITS ETF - USD Acc | C7: WQTM LN | D7: Rigetti Computing Inc | E7: RGTI US | F7: 332925 | G7: 4985551.9 | H7: 0.0365155
A8: 2026-02-05T00:00:00 | B8: WisdomTree Quantum Computing UCITS ETF - USD Acc | C8: WQTM LN | D8: SK Telecom Co Ltd | E8: 017670 KS | F8: 94349 | G8: 4979262.7 | H8: 0.0364694
A9: 2026-02-05T00:00:00 | B9: WisdomTree Quantum Computing UCITS ETF - USD Acc | C9: WQTM LN | D9: International Business Machines Corp | E9: IBM UN | F9: 14809 | G9: 4292981 | H9: 0.0314429
A10: 2026-02-05T00:00:00 | B10: WisdomTree Quantum Computing UCITS ETF - USD Acc | C10: WQTM LN | D10: Amazon.com Inc | E10: AMZN UQ | F10: 19063 | G10: 4245139.5 | H10: 0.0310925
A11: 2026-02-05T00:00:00 | B11: WisdomTree Quantum Computing UCITS ETF - USD Acc | C11: WQTM LN | D11: Fujitsu Ltd | E11: 6702 JT | F11: 167846 | G11: 4221167.4 | H11: 0.0309169
A12: 2026-02-05T00:00:00 | B12: WisdomTree Quantum Computing UCITS ETF - USD Acc | C12: WQTM LN | D12: Nvidia Corp | E12: NVDA UQ | F12: 24336 | G12: 4182871.7 | H12: 0.0306364
A13: 2026-02-05T00:00:00 | B13: WisdomTree Quantum Computing UCITS ETF - USD Acc | C13: WQTM LN | D13: Honeywell International Inc | E13: HON UN | F13: 17385 | G13: 4065482.2 | H13: 0.0297766
... A38: 2026-02-05T00:00:00 | B38: WisdomTree Quantum Computing UCITS ETF - USD Acc | C38: WQTM LN | D38: Cadence Design Systems Inc | E38: CDNS UQ | F38: 7719 | G38: 2085210.7 | H38: 0.0152726
A39: 2026-02-05T00:00:00 | B39: WisdomTree Quantum Computing UCITS ETF - USD Acc | C39: WQTM LN | D39: CASH W-O | F39: 0 | H39: 0.0024155
A40: 2026-02-05T00:00:00 | B40: WisdomTree Quantum Computing UCITS ETF - USD Acc | C40: WQTM LN | D40: EURO INCOME A/C | F40: 0 | H40: 0.0002176
A41: 2026-02-05T00:00:00 | B41: WisdomTree Quantum Computing UCITS ETF - USD Acc | C41: WQTM LN | D41: JAPANESE YEN | F41: 0 | H41: 3.81e-05
A42: 2026-02-06T00:00:00 | B42: WisdomTree Quantum Computing UCITS ETF - USD Acc | C42: WQTM LN | D42: D-Wave Quantum Inc | E42: QBTS US | F42: 355714 | G42: 7370394.1 | H42: 0.0517432
A43: 2026-02-06T00:00:00 | B43: WisdomTree Quantum Computing UCITS ETF - USD Acc | C43: WQTM LN | D43: Ionq Inc | E43: IONQ US | F43: 183332 | G43: 6414786.7 | H43: 0.0450344
A44: 2026-02-06T00:00:00 | B44: WisdomTree Quantum Computing UCITS ETF - USD Acc | C44: WQTM LN | D44: Intel Corp | E44: INTC UQ | F44: 124717 | G44: 6309433 | H44: 0.0442948
A45: 2026-02-06T00:00:00 | B45: WisdomTree Quantum Computing UCITS ETF - USD Acc | C45: WQTM LN | D45: Quantum Computing Inc | E45: QUBT US | F45: 637430 | G45: 6010964.9 | H45: 0.0421994
A46: 2026-02-06T00:00:00 | B46: WisdomTree Quantum Computing UCITS ETF - USD Acc | C46: WQTM LN | D46: Rigetti Computing Inc | E46: RGTI US | F46: 330087 | G46: 5845840.8 | H46: 0.0410402
A47: 2026-02-06T00:00:00 | B47: WisdomTree Quantum Computing UCITS ETF - USD Acc | C47: WQTM LN | D47: Google Inc | E47: GOOGL UQ | F47: 16072 | G47: 5189005.9 | H47: 0.0364289
A48: 2026-02-06T00:00:00 | B48: WisdomTree Quantum Computing UCITS ETF - USD Acc | C48: WQTM LN | D48: Nvidia Corp | E48: NVDA UQ | F48: 24128 | G48: 4473572.5 | H48: 0.0314063
A49: 2026-02-06T00:00:00 | B49: WisdomTree Quantum Computing UCITS ETF - USD Acc | C49: WQTM LN | D49: SK Telecom Co Ltd | E49: 017670 KS | F49: 93545 | G49: 4405263 | H49: 0.0309267
A50: 2026-02-06T00:00:00 | B50: WisdomTree Quantum Computing UCITS ETF - USD Acc | C50: WQTM LN | D50: International Business Machines Corp | E50: IBM UN | F50: 14683 | G50: 4389189.2 | H50: 0.0308139
A51: 2026-02-06T00:00:00 | B51: WisdomTree Quantum Computing UCITS ETF - USD Acc | C51: WQTM LN | D51: Formfactor Inc | E51: FORM | F51: 47520 | G51: 4290580.8 | H51: 0.0301216
A52: 2026-02-06T00:00:00 | B52: WisdomTree Quantum Computing UCITS ETF - USD Acc | C52: WQTM LN | D52: Fujitsu Ltd | E52: 6702 JT | F52: 166416 | G52: 4151514.5 | H52: 0.0291453
A53: 2026-02-06T00:00:00 | B53: WisdomTree Quantum Computing UCITS ETF - USD Acc | C53: WQTM LN | D53: Skywater Technology Inc | E53: SKYT US | F53: 136408 | G53: 4139982.8 | H53: 0.0290644
... A78: 2026-02-06T00:00:00 | B78: WisdomTree Quantum Computing UCITS ETF - USD Acc | C78: WQTM LN | D78: Cadence Design Systems Inc | E78: CDNS UQ | F78: 7653 | G78: 2169778.6 | H78: 0.0152327
A79: 2026-02-06T00:00:00 | B79: WisdomTree Quantum Computing UCITS ETF - USD Acc | C79: WQTM LN | D79: CASH W-O | F79: 0 | H79: 0.0082112
A80: 2026-02-06T00:00:00 | B80: WisdomTree Quantum Computing UCITS ETF - USD Acc | C80: WQTM LN | D80: EURO INCOME A/C | F80: 0 | H80: 0.000209
A81: 2026-02-06T00:00:00 | B81: WisdomTree Quantum Computing UCITS ETF - USD Acc | C81: WQTM LN | D81: JAPANESE YEN | F81: 0 | H81: 3.65e-05
A82: 2026-02-19T00:00:00 | B82: WisdomTree Quantum Computing UCITS ETF - USD Acc | C82: WQTM LN | D82: D-Wave Quantum Inc | E82: QBTS US | F82: 361830 | G82: 7012265.4 | H82: 0.0489311
A83: 2026-02-19T00:00:00 | B83: WisdomTree Quantum Computing UCITS ETF - USD Acc | C83: WQTM LN | D83: Ionq Inc | E83: IONQ US | F83: 186484 | G83: 6234160.1 | H83: 0.0435016
A84: 2026-02-19T00:00:00 | B84: WisdomTree Quantum Computing UCITS ETF - USD Acc | C84: WQTM LN | D84: Intel Corp | E84: INTC UQ | F84: 126861 | G84: 5660537.8 | H84: 0.0394989
A85: 2026-02-19T00:00:00 | B85: WisdomTree Quantum Computing UCITS ETF - USD Acc | C85: WQTM LN | D85: Rigetti Computing Inc | E85: RGTI US | F85: 335763 | G85: 5573665.8 | H85: 0.0388927
A86: 2026-02-19T00:00:00 | B86: WisdomTree Quantum Computing UCITS ETF - USD Acc | C86: WQTM LN | D86: Quantum Computing Inc | E86: QUBT US | F86: 648390 | G86: 5329765.8 | H86: 0.0371908
A87: 2026-02-19T00:00:00 | B87: WisdomTree Quantum Computing UCITS ETF - USD Acc | C87: WQTM LN | D87: SK Telecom Co Ltd | E87: 017670 KS | F87: 93545 | G87: 5273330.3 | H87: 0.036797
A88: 2026-02-19T00:00:00 | B88: WisdomTree Quantum Computing UCITS ETF - USD Acc | C88: WQTM LN | D88: Google Inc | E88: GOOGL UQ | F88: 16348 | G88: 4950991.8 | H88: 0.0345477
A89: 2026-02-19T00:00:00 | B89: WisdomTree Quantum Computing UCITS ETF - USD Acc | C89: WQTM LN | D89: Nvidia Corp | E89: NVDA UQ | F89: 24544 | G89: 4611817.6 | H89: 0.032181
A90: 2026-02-19T00:00:00 | B90: WisdomTree Quantum Computing UCITS ETF - USD Acc | C90: WQTM LN | D90: Formfactor Inc | E90: FORM | F90: 48336 | G90: 4460446.1 | H90: 0.0311247
A91: 2026-02-19T00:00:00 | B91: WisdomTree Quantum Computing UCITS ETF - USD Acc | C91: WQTM LN | D91: Deutsche Telekom AG | E91: DTE GY | F91: 110458 | G91: 4239481.4 | H91: 0.0295828
A92: 2026-02-19T00:00:00 | B92: WisdomTree Quantum Computing UCITS ETF - USD Acc | C92: WQTM LN | D92: Honeywell International Inc | E92: HON UN | F92: 17533 | G92: 4221420.4 | H92: 0.0294568
A93: 2026-02-19T00:00:00 | B93: WisdomTree Quantum Computing UCITS ETF - USD Acc | C93: WQTM LN | D93: Applied Materials Inc | E93: AMAT UQ | F93: 11058 | G93: 4089580.1 | H93: 0.0285368
... A118: 2026-02-19T00:00:00 | B118: WisdomTree Quantum Computing UCITS ETF - USD Acc | C118: WQTM LN | D118: Dell Technologies -C | E118: DELL US | F118: 18285 | G118: 2177012.1 | H118: 0.015191
A119: 2026-02-19T00:00:00 | B119: WisdomTree Quantum Computing UCITS ETF - USD Acc | C119: WQTM LN | D119: CASH W-O | F119: 0 | H119: 0.0033303
A120: 2026-02-19T00:00:00 | B120: WisdomTree Quantum Computing UCITS ETF - USD Acc | C120: WQTM LN | D120: EURO INCOME A/C | F120: 0 | H120: 0.0003045
A121: 2026-02-19T00:00:00 | B121: WisdomTree Quantum Computing UCITS ETF - USD Acc | C121: WQTM LN | D121: JAPANESE YEN | F121: 0 | H121: 5.89e-05

Sheet NATP
A1: FUND | B1: Date | C1: Security Description | D1: Shares | E1: Market Value (Base) | F1: Trading Currency | G1: SEDOL/CUSIP | H1: Exposure Country | I1: Region | J1: ISIN | K1: Weight
A2: NATP | B2: 46030 | C2: BAE SYSTEMS PLC | D2: 5957482 | E2: 1.6199677e+08 | F2: GBP | G2: 0263494 | H2: United Kingdom | I2: Europe | J2: GB0002634946 | K2: 0.0524
A3: NATP | B3: 46030 | C3: RHEINMETALL AG COMMON | D3: 72130 | E3: 1.5585088e+08 | F3: EUR | G3: 5334588 | H3: Germany | I3: Europe | J3: DE0007030009 | K3: 0.0504 | P3: Column Labels
A4: NATP | B4: 46030 | C4: SAFRAN SA COMMON STOCK | D4: 416860 | E4: 1.5543098e+08 | F4: EUR | G4: B058TZ6 | H4: France | I4: Europe | J4: FR0000073272 | K4: 0.0503 | P4: Sum of Shares | X4: Sum of Weight
A5: NATP | B5: 46030 | C5: RTX CORP | D5: 753100 | E5: 140957727 | F5: USD | G5: BM5M5Y3 | H5: United States | I5: North America | J5: US75513E1010 | K5: 0.0456 | O5: Row Labels | P5: 46030 | Q5: 46031 | R5: 46049 | S5: 46055 | T5: 46058 | U5: 46059 | V5: 46063 | W5: (blank) | X5: 46030 | Y5: 46031 | Z5: 46049 | AA5: 46055 | AB5: 46058 | AC5: 46059 | AD5: 46063 | AE5: (blank)
A6: NATP | B6: 46030 | C6: LOCKHEED MARTIN CORP | D6: 266213 | E6: 1.3801547e+08 | F6: USD | G6: 2522096 | H6: United States | I6: North America | J6: US5398301094 | K6: 0.0447 | O6: CISCO SYSTEMS INC COMMON | P6: 1842989 | Q6: 1842989 | R6: 1836765 | S6: 1912860 | T6: 1916102 | U6: 1914481 | V6: 1945280 | X6: 0.0443 | Y6: 0.0434 | Z6: 0.0448 | AA6: 0.0498 | AB6: 0.0533 | AC6: 0.0535 | AD6: 0.0539
A7: NATP | B7: 46030 | C7: CISCO SYSTEMS INC COMMON | D7: 1842989 | E7: 1.3695137e+08 | F7: USD | G7: 2198163 | H7: United States | I7: North America | J7: US17275R1023 | K7: 0.0443 | O7: SAFRAN SA COMMON STOCK | P7: 416860 | Q7: 416860 | R7: 417214 | S7: 428028 | T7: 428754 | U7: 428391 | V7: 435288 | X7: 0.0503 | Y7: 0.0489 | Z7: 0.0477 | AA7: 0.0492 | AB7: 0.0516 | AC7: 0.0514 | AD7: 0.0504
A8: NATP | B8: 46030 | C8: GENERAL DYNAMICS CORP | D8: 382507 | E8: 1.3442826e+08 | F8: USD | G8: 2365161 | H8: United States | I8: North America | J8: US3695501086 | K8: 0.0435 | O8: LOCKHEED MARTIN CORP | P8: 266213 | Q8: 266213 | R8: 265313 | S8: 243566 | T8: 243978 | U8: 243772 | V8: 247686 | X8: 0.0447 | Y8: 0.0459 | Z8: 0.0489 | AA8: 0.05 | AB8: 0.0502 | AC8: 0.0501 | AD8: 0.05
A9: NATP | B9: 46030 | C9: NORTHROP GRUMMAN CORP | D9: 217408 | E9: 1.2844247e+08 | F9: USD | G9: 2648806 | H9: United States | I9: North America | J9: US6668071029 | K9: 0.0416 | O9: BAE SYSTEMS PLC | P9: 5957482 | Q9: 5957482 | R9: 5937362 | S9: 5710841 | T9: 5720517 | U9: 5715679 | V9: 5807601 | X9: 0.0524 | Y9: 0.0521 | Z9: 0.0509 | AA9: 0.0483 | AB9: 0.0485 | AC9: 0.0482 | AD9: 0.0482
A10: NATP | B10: 46030 | C10: PALANTIR TECHNOLOGIES INC | D10: 717975 | E10: 1.2698106e+08 | F10: USD | G10: BN78DQ4 | H10: United States | I10: North America | J10: US69608A1088 | K10: 0.0411 | O10: NORTHROP GRUMMAN CORP | P10: 217408 | Q10: 217408 | R10: 216672 | S10: 213462 | T10: 213824 | U10: 213643 | V10: 217082 | X10: 0.0416 | Y10: 0.0427 | Z10: 0.0456 | AA10: 0.0472 | AB10: 0.0503 | AC10: 0.0499 | AD10: 0.0477
A11: NATP | B11: 46030 | C11: CROWDSTRIKE HOLDINGS INC | D11: 258612 | E11: 1.1996235e+08 | F11: USD | G11: BJJP138 | H11: United States | I11: North America | J11: US22788C1053 | K11: 0.0388 | O11: GENERAL DYNAMICS CORP | P11: 382507 | Q11: 382507 | R11: 381215 | S11: 390645 | T11: 391307 | U11: 390976 | V11: 397265 | X11: 0.0435 | Y11: 0.043 | Z11: 0.0435 | AA11: 0.0438 | AB11: 0.0467 | AC11: 0.0464 | AD11: 0.0457
A12: NATP | B12: 46030 | C12: PALO ALTO NETWORKS INC | D12: 607839 | E12: 1.1597568e+08 | F12: USD | G12: B87ZMX0 | H12: United States | I12: North America | J12: US6974351057 | K12: 0.0375 | O12: RTX CORP | P12: 753100 | Q12: 753100 | R12: 750556 | S12: 714547 | T12: 715757 | U12: 715152 | V12: 726647 | X12: 0.0456 | Y12: 0.0451 | Z12: 0.0468 | AA12: 0.0464 | AB12: 0.0474 | AC12: 0.0468 | AD12: 0.0455
A13: NATP | B13: 46030 | C13: L3HARRIS TECHNOLOGIES INC | D13: 354078 | E13: 1.1533737e+08 | F13: USD | G13: BK9DTN5 | H13: United States | I13: North America | J13: US5024311095 | K13: 0.0373 | O13: RHEINMETALL AG COMMON | P13: 72130 | Q13: 72130 | R13: 71886 | S13: 70920 | T13: 71040 | U13: 70980 | V13: 72120 | X13: 0.0504 | Y13: 0.0507 | Z13: 0.0493 | AA13: 0.0467 | AB13: 0.0445 | AC13: 0.0444 | AD13: 0.0442
A14: NATP | B14: 46030 | C14: THALES SA COMMON STOCK | D14: 362783 | E14: 1.124974e+08 | F14: EUR | G14: 4162791 | H14: France | I14: Europe | J14: FR0000121329 | K14: 0.0364 | O14: CROWDSTRIKE HOLDINGS INC | P14: 258612 | Q14: 258612 | R14: 259140 | S14: 316916 | T14: 317452 | U14: 317184 | V14: 322276 | X14: 0.0388 | Y14: 0.0387 | Z14: 0.0383 | AA14: 0.0449 | AB14: 0.0405 | AC14: 0.0413 | AD14: 0.0428
A15: NATP | B15: 46030 | C15: FORTINET INC COMMON STOCK | D15: 1211505 | E15: 94557965 | F15: USD | G15: B5B2106 | H15: United States | I15: North America | J15: US34959E1091 | K15: 0.0306 | O15: PALO ALTO NETWORKS INC | P15: 607839 | Q15: 607839 | R15: 609259 | S15: 762296 | T15: 763588 | U15: 762942 | V15: 775216 | X15: 0.0375 | Y15: 0.0365 | Z15: 0.0346 | AA15: 0.0432 | AB15: 0.0399 | AC15: 0.04 | AD15: 0.0412
A16: NATP | B16: 46030 | C16: LEONARDO SPA COMMON STOCK | D16: 1113326 | E16: 76009391 | F16: EUR | G16: B0DJNG0 | H16: Italy | I16: Europe | J16: IT0003856405 | K16: 0.0246 | O16: L3HARRIS TECHNOLOGIES INC | P16: 354078 | Q16: 354078 | R16: 352882 | S16: 345070 | T16: 345654 | U16: 345362 | V16: 350910 | X16: 0.0373 | Y16: 0.0378 | Z16: 0.0394 | AA16: 0.0379 | AB16: 0.04 | AC16: 0.0398 | AD16: 0.0389
A17: NATP | B17: 46030 | C17: SAAB AB COMMON STOCK SEK | D17: 1016770 | E17: 70941632 | F17: SEK | G17: BPXZH27 | H17: Sweden | I17: Europe | J17: SE0021921269 | K17: 0.023 | O17: PALANTIR TECHNOLOGIES INC | P17: 717975 | Q17: 717975 | R17: 715551 | S17: 832514 | T17: 833924 | U17: 833219 | V17: 846614 | X17: 0.0411 | Y17: 0.0405 | Z17: 0.0367 | AA17: 0.0397 | AB17: 0.0366 | AC17: 0.0373 | AD17: 0.0379
... A55: NATP | B55: 46030 | C55: SENTINELONE INC COMMON | D55: 574085 | E55: 8800723.1 | F55: USD | G55: BP7L1B8 | H55: United States | I55: North America | J55: US81730H1095 | K55: 0.0028 | O55: LIG NEX1 CO LTD COMMON | P55: 34038 | Q55: 34038 | R55: 33922 | S55: 32202 | T55: 32256 | U55: 32229 | V55: 32742 | X55: 0.004 | Y55: 0.004 | Z55: 0.0037 | AA55: 0.0032 | AB55: 0.0032 | AC55: 0.0031 | AD55: 0.0033
A56: NATP | B56: 46030 | C56: HANWHA SYSTEMS CO LTD | D56: 202069 | E56: 8400386.6 | F56: KRW | G56: BJN3H96 | H56: South Korea | I56: Asia | J56: KR7272210006 | K56: 0.0027 | O56: BIGBEAR.AI HOLDINGS INC | S56: 2138610 | T56: 2142234 | U56: 2140422 | V56: 2174850 | AA56: 0.0032 | AB56: 0.003 | AC56: 0.0034 | AD56: 0.0032
A57: NATP | B57: 46030 | C57: VARONIS SYSTEMS INC | D57: 202718 | E57: 7247168.5 | F57: USD | G57: BJZ2ZR5 | H57: United States | I57: North America | J57: US9222801022 | K57: 0.0023 | O57: MERCURY SYSTEMS INC | P57: 110565 | Q57: 110565 | R57: 110193 | S57: 109307 | T57: 109493 | U57: 109400 | V57: 111167 | X57: 0.0032 | Y57: 0.0033 | Z57: 0.0034 | AA57: 0.0033 | AB57: 0.0029 | AC57: 0.003 | AD57: 0.003
A58: NATP | B58: 46030 | C58: BLACKBERRY LTD COMMON | D58: 1612604 | E58: 6224651.4 | F58: USD | G58: BCBHZ42 | H58: Canada | I58: North America | J58: CA09228F1036 | K58: 0.002 | O58: SCIENCE APPLICATIONS | P58: 86663 | Q58: 86663 | R58: 86371 | S58: 82748 | T58: 82888 | U58: 82818 | V58: 84148 | X58: 0.0031 | Y58: 0.0031 | Z58: 0.0028 | AA58: 0.0027 | AB58: 0.0027 | AC58: 0.0027 | AD58: 0.0026
A59: NATP | B59: 46030 | C59: DRONESHIELD LTD COMMON | D59: 2408606 | E59: 6211608.2 | F59: AUD | G59: BYV1JW4 | H59: Australia | I59: Asia | J59: AU000000DRO2 | K59: 0.002 | O59: SENTINELONE INC COMMON | P59: 574085 | Q59: 574085 | R59: 572145 | S59: 583277 | T59: 584265 | U59: 583771 | V59: 593157 | X59: 0.0028 | Y59: 0.0028 | Z59: 0.0027 | AA59: 0.0027 | AB59: 0.0026 | AC59: 0.0025 | AD59: 0.0026
A60: NATP | B60: 46030 | C60: LEONARDO DRS INC COMMON | D60: 147732 | E60: 5737910.9 | F60: USD | G60: BNSNZQ2 | H60: United States | I60: North America | J60: US52661A1088 | K60: 0.0019 | O60: QUALYS INC COMMON STOCK | P60: 67795 | Q60: 67795 | R60: 67567 | S60: 65496 | T60: 65606 | U60: 65551 | V60: 66596 | X60: 0.0029 | Y60: 0.0029 | Z60: 0.0028 | AA60: 0.0029 | AB60: 0.0028 | AC60: 0.0024 | AD60: 0.0024
A61: NATP | B61: 46030 | C61: TENABLE HOLDINGS INC | D61: 225508 | E61: 5312968.5 | F61: USD | G61: BF7J7N6 | H61: United States | I61: North America | J61: US88025T1025 | K61: 0.0017 | O61: TENABLE HOLDINGS INC | P61: 225508 | Q61: 225508 | R61: 252398 | S61: 290561 | T61: 291053 | U61: 290807 | V61: 295481 | X61: 0.0017 | Y61: 0.0017 | Z61: 0.0018 | AA61: 0.0021 | AB61: 0.0019 | AC61: 0.002 | AD61: 0.0022
A62: NATP | B62: 46030 | C62: CASH | D62: 3.9337081e+08 | E62: 5527736.7 | F62: USD | G62: CASH | H62: Cash | I62: Cash | J62: NONE | K62: 0.0017 | O62: LEONARDO DRS INC COMMON | P62: 147732 | Q62: 147732 | R62: 147232 | S62: 150978 | T62: 151234 | U62: 151106 | V62: 153538 | X62: 0.0019 | Y62: 0.0019 | Z62: 0.0019 | AA62: 0.002 | AB62: 0.0019 | AC62: 0.0019 | AD62: 0.0019
A63: NATP | B63: 46030 | C63: KONGSBERG GRUPPEN ASA | D63: 0 | E63: 69959.96 | F63: NOK | G63: 5208241 | H63: Norway | I63: Europe | J63: NO0003043309 | K63: 0 | O63: DRONESHIELD LTD COMMON | P63: 2408606 | Q63: 2408606 | R63: 2400470 | S63: 2477036 | T63: 2481234 | U63: 2479135 | V63: 2519016 | X63: 0.002 | Y63: 0.0021 | Z63: 0.0022 | AA63: 0.0019 | AB63: 0.0019 | AC63: 0.0017 | AD63: 0.0019
A64: NATP | B64: 46030 | C64: INVISIO AB COMMON STOCK | D64: 0 | E64: 4505.35 | F64: SEK | G64: B06G108 | H64: Sweden | I64: Europe | J64: SE0001200015 | K64: 0 | O64: VARONIS SYSTEMS INC | P64: 202718 | Q64: 202718 | R64: 202034 | S64: 208367 | T64: 208721 | U64: 208544 | V64: 211907 | X64: 0.0023 | Y64: 0.0023 | Z64: 0.0021 | AA64: 0.002 | AB64: 0.0016 | AC64: 0.0016 | AD64: 0.0018
A65: NATP | B65: 46030 | C65: SAAB AB COMMON STOCK SEK | D65: 0 | E65: 3114.03 | F65: SEK | G65: 5469554 | H65: Sweden | I65: Europe | J65: SE0021921269 | K65: 0 | O65: FIREFLY AEROSPACE INC | R65: 20432 | S65: 209349 | T65: 209703 | U65: 209526 | V65: 212889 | Z65: 0.0002 | AA65: 0.0015 | AB65: 0.0016 | AC65: 0.0016 | AD65: 0.0016
A66: NATP | B66: 46031 | C66: BAE SYSTEMS PLC | D66: 5957482 | E66: 1.6411779e+08 | F66: GBP | G66: 0263494 | H66: United Kingdom | I66: Europe | J66: GB0002634946 | K66: 0.0521 | O66: KYNDRYL HOLDINGS INC | P66: 430049 | Q66: 430049 | R66: 428597 | S66: 414510 | T66: 415212 | U66: 414861 | V66: 421530 | X66: 0.0038 | Y66: 0.0037 | Z66: 0.0032 | AA66: 0.0031 | AB66: 0.0031 | AC66: 0.0032 | AD66: 0.0015
A67: NATP | B67: 46031 | C67: RHEINMETALL AG COMMON | D67: 72130 | E67: 1.5962459e+08 | F67: EUR | G67: 5334588 | H67: Germany | I67: Europe | J67: DE0007030009 | K67: 0.0507 | O67: SOFTCAT PLC COMMON STOCK | P67: 776159 | Q67: 776159 | R67: 606729 | X67: 0.0049 | Y67: 0.0049 | Z67: 0.0042
A68: NATP | B68: 46031 | C68: SAFRAN SA COMMON STOCK | D68: 416860 | E68: 1.5397513e+08 | F68: EUR | G68: B058TZ6 | H68: France | I68: Europe | J68: FR0000073272 | K68: 0.0489 | O68: (blank)
A69: NATP | B69: 46031 | C69: LOCKHEED MARTIN CORP | D69: 266213 | E69: 1.4453236e+08 | F69: USD | G69: 2522096 | H69: United States | I69: North America | J69: US5398301094 | K69: 0.0459 | O69: BLACKBERRY LTD COMMON | P69: 1612604 | Q69: 1612604 | R69: 1607156 | X69: 0.002 | Y69: 0.002 | Z69: 0.0019
A70: NATP | B70: 46031 | C70: RTX CORP | D70: 753100 | E70: 141959350 | F70: USD | G70: BM5M5Y3 | H70: United States | I70: North America | J70: US75513E1010 | K70: 0.0451 | O70: INVISIO AB COMMON STOCK | P70: 0 | Q70: 0 | R70: 0 | S70: 0 | T70: 0 | U70: 0 | V70: 0 | X70: 0 | Y70: 0 | Z70: 0 | AA70: 0 | AB70: 0 | AC70: 0 | AD70: 0
A71: NATP | B71: 46031 | C71: CISCO SYSTEMS INC COMMON | D71: 1842989 | E71: 1.3680394e+08 | F71: USD | G71: 2198163 | H71: United States | I71: North America | J71: US17275R1023 | K71: 0.0434 | O71: Grand Total | P71: 4.3133086e+08 | Q71: 4.2522973e+08 | R71: 4.2228223e+08 | S71: 4.2169753e+08 | T71: 4.2444565e+08 | U71: 4.2254209e+08 | V71: 4.7197714e+08 | X71: 0.9993 | Y71: 1.0002 | Z71: 0.9996 | AA71: 1.0014 | AB71: 1.0015 | AC71: 1.0018 | AD71: 1.0011
A72: NATP | B72: 46031 | C72: GENERAL DYNAMICS CORP | D72: 382507 | E72: 1.353654e+08 | F72: USD | G72: 2365161 | H72: United States | I72: North America | J72: US3695501086 | K72: 0.043
A73: NATP | B73: 46031 | C73: NORTHROP GRUMMAN CORP | D73: 217408 | E73: 1.3453642e+08 | F73: USD | G73: 2648806 | H73: United States | I73: North America | J73: US6668071029 | K73: 0.0427
A74: NATP | B74: 46031 | C74: PALANTIR TECHNOLOGIES INC | D74: 717975 | E74: 1.2743338e+08 | F74: USD | G74: BN78DQ4 | H74: United States | I74: North America | J74: US69608A1088 | K74: 0.0405
A75: NATP | B75: 46031 | C75: CROWDSTRIKE HOLDINGS INC | D75: 258612 | E75: 1.2170539e+08 | F75: USD | G75: BJJP138 | H75: United States | I75: North America | J75: US22788C1053 | K75: 0.0387
A76: NATP | B76: 46031 | C76: L3HARRIS TECHNOLOGIES INC | D76: 354078 | E76: 1.1888877e+08 | F76: USD | G76: BK9DTN5 | H76: United States | I76: North America | J76: US5024311095 | K76: 0.0378
A77: NATP | B77: 46031 | C77: PALO ALTO NETWORKS INC | D77: 607839 | E77: 1.1489373e+08 | F77: USD | G77: B87ZMX0 | H77: United States | I77: North America | J77: US6974351057 | K77: 0.0365
A78: NATP | B78: 46031 | C78: THALES SA COMMON STOCK | D78: 362783 | E78: 1.1233597e+08 | F78: EUR | G78: 4162791 | H78: France | I78: Europe | J78: FR0000121329 | K78: 0.0357
A79: NATP | B79: 46031 | C79: FORTINET INC COMMON STOCK | D79: 1211505 | E79: 95975426 | F79: USD | G79: B5B2106 | H79: United States | I79: North America | J79: US34959E1091 | K79: 0.0305
A80: NATP | B80: 46031 | C80: LEONARDO SPA COMMON STOCK | D80: 1113326 | E80: 75791413 | F80: EUR | G80: B0DJNG0 | H80: Italy | I80: Europe | J80: IT0003856405 | K80: 0.0241
A81: NATP | B81: 46031 | C81: SAAB AB COMMON STOCK SEK | D81: 1016770 | E81: 75322817 | F81: SEK | G81: BPXZH27 | H81: Sweden | I81: Europe | J81: SE0021921269 | K81: 0.0239
A82: NATP | B82: 46031 | C82: HANWHA AEROSPACE CO LTD | D82: 85046 | E82: 70965682 | F82: KRW | G82: 6772671 | H82: South Korea | I82: Asia | J82: KR7012450003 | K82: 0.0225
A83: NATP | B83: 46031 | C83: ROCKET LAB CORP COMMON | D83: 802097 | E83: 68057930 | F83: USD | G83: BT6C8Z3 | H83: United States | I83: North America | J83: US7731211089 | K83: 0.0216
... A580: NATP | B580: 46077 | C580: SAAB AB COMMON STOCK SEK | D580: 0 | E580: 3169.35 | F580: SEK | G580: 5469554 | H580: Sweden | I580: Europe | J580: SE0021921269 | K580: 0

Sheet FCBR
A1: ETF | B1: Date | C1: Security Name | D1: Identifier | E1: CUSIP | F1: Classification | G1: Shares or Quantity | H1: Market Value | I1: Weighting
A2: FCBR | B2: 46072 | C2: Cisco Systems, Inc. | D2: CSCO | E2: 17275R102 | F2: Telecommunications Equipment | G2: 11527970 | H2: 9.0563732e+08 | I2: 0.0905
A3: FCBR | B3: 46072 | C3: Infosys Limited (ADR) | D3: INFY | E3: 456788108 | F3: Software and Computer Services | G3: 50741475 | H3: 7.3828846e+08 | I3: 0.0737
A4: FCBR | B4: 46072 | C4: Broadcom Inc. | D4: AVGO | E4: 11135F101 | F4: Technology Hardware and Equipment | G4: 2201131 | H4: 7.3515574e+08 | I4: 0.0734
A5: FCBR | B5: 46072 | C5: CrowdStrike Holdings, Inc. (Class A) | D5: CRWD | E5: 22788C105 | F5: Software and Computer Services | G5: 1741994 | H5: 7.3536535e+08 | I5: 0.0734
A6: FCBR | B6: 46072 | C6: Palo Alto Networks, Inc. | D6: PANW | E6: 697435105 | F6: Software and Computer Services | G6: 4665039 | H6: 7.0437424e+08 | I6: 0.0704
A7: FCBR | B7: 46072 | C7: Thales S.A. | D7: HO.FP | E7: F9156M108 | F7: Aerospace and Defense | G7: 1695338 | H7: 5.2532256e+08 | I7: 0.0525
A8: FCBR | B8: 46072 | C8: Akamai Technologies, Inc. | D8: AKAM | E8: 00971T101 | F8: Software and Computer Services | G8: 4564948 | H8: 5.0027265e+08 | I8: 0.05
A9: FCBR | B9: 46072 | C9: F5, Inc. | D9: FFIV | E9: 315616102 | F9: Software and Computer Services | G9: 1638407 | H9: 4.5742685e+08 | I9: 0.0457
A10: FCBR | B10: 46072 | C10: Fortinet, Inc. | D10: FTNT | E10: 34959E109 | F10: Software and Computer Services | G10: 5466283 | H10: 4.4643133e+08 | I10: 0.0446
A11: FCBR | B11: 46072 | C11: Cloudflare, Inc. (Class A) | D11: NET | E11: 18915M107 | F11: Software and Computer Services | G11: 2215072 | H11: 4.2671147e+08 | I11: 0.0426
A12: FCBR | B12: 46072 | C12: Leidos Holdings, Inc. | D12: LDOS | E12: 525327102 | F12: Software and Computer Services | G12: 2320676 | H12: 4.0906556e+08 | I12: 0.0409
A13: FCBR | B13: 46072 | C13: Okta, Inc. | D13: OKTA | E13: 679295105 | F13: Software and Computer Services | G13: 4912366 | H13: 4.0183154e+08 | I13: 0.0401
... A30: FCBR | B30: 46072 | C30: Radware Ltd. | D30: RDWR | E30: M81873107 | F30: Software and Computer Services | G30: 1361183 | H30: 34084022 | I30: 0.0034
A31: FCBR | B31: 46072 | C31: US Dollar | D31: $USD | F31: Other | G31: 19980827 | H31: 19980827 | I31: 0.002
A32: FCBR | B32: 46072 | C32: Rapid7, Inc. | D32: RPD | E32: 753422104 | F32: Software and Computer Services | G32: 2026443 | H32: 14367481 | I32: 0.0014
A33: FCBR | B33: 46072 | C33: OneSpan Inc. | D33: OSPN | E33: 68287N100 | F33: Software and Computer Services | G33: 1161918 | H33: 13222627 | I33: 0.0013
A34: FCBR | B34: 46072 | C34: NCC Group Plc | D34: NCC.LN | E34: G64319109 | F34: Software and Computer Services | G34: 6663320 | H34: 11818721 | I34: 0.0012
A35: FCBR | B35: 46072 | C35: Japanese Yen | D35: $JPY | F35: Other | G35: 815712305 | H35: 5263339.2 | I35: 0.0005
A36: FCBR | B36: 46072 | C36: Canadian Dollar | D36: $CAD | F36: Other | G36: 1 | H36: 0.38 | I36: 0
A37: FCBR | B37: 46077 | C37: Cisco Systems, Inc. | D37: CSCO | E37: 17275R102 | F37: Telecommunications Equipment | G37: 11459660 | H37: 8.9545783e+08 | I37: 0.0964
A38: FCBR | B38: 46077 | C38: Broadcom Inc. | D38: AVGO | E38: 11135F101 | F38: Technology Hardware and Equipment | G38: 2188081 | H38: 7.1219848e+08 | I38: 0.0767
A39: FCBR | B39: 46077 | C39: Infosys Limited (ADR) | D39: INFY | E39: 456788108 | F39: Software and Computer Services | G39: 50440839 | H39: 6.9810121e+08 | I39: 0.0751
A40: FCBR | B40: 46077 | C40: Palo Alto Networks, Inc. | D40: PANW | E40: 697435105 | F40: Software and Computer Services | G40: 4637391 | H40: 6.5697918e+08 | I40: 0.0707
A41: FCBR | B41: 46077 | C41: CrowdStrike Holdings, Inc. (Class A) | D41: CRWD | E41: 22788C105 | F41: Software and Computer Services | G41: 1731680 | H41: 606520920 | I41: 0.0653
A42: FCBR | B42: 46077 | C42: Thales S.A. | D42: HO.FP | E42: F9156M108 | F42: Aerospace and Defense | G42: 1685294 | H42: 498552397 | I42: 0.0537
A43: FCBR | B43: 46077 | C43: Akamai Technologies, Inc. | D43: AKAM | E43: 00971T101 | F43: Software and Computer Services | G43: 4537894 | H43: 4.5437933e+08 | I43: 0.0489
A44: FCBR | B44: 46077 | C44: F5, Inc. | D44: FFIV | E44: 315616102 | F44: Software and Computer Services | G44: 1628705 | H44: 4.4305662e+08 | I44: 0.0477
A45: FCBR | B45: 46077 | C45: Fortinet, Inc. | D45: FTNT | E45: 34959E109 | F45: Software and Computer Services | G45: 5433901 | H45: 4.0879237e+08 | I45: 0.044
A46: FCBR | B46: 46077 | C46: Leidos Holdings, Inc. | D46: LDOS | E46: 525327102 | F46: Software and Computer Services | G46: 2306924 | H46: 4.0170468e+08 | I46: 0.0432
A47: FCBR | B47: 46077 | C47: Gen Digital Inc. | D47: GEN | E47: 668771108 | F47: Software and Computer Services | G47: 16717977 | H47: 3.6729395e+08 | I47: 0.0395
A48: FCBR | B48: 46077 | C48: Cloudflare, Inc. (Class A) | D48: NET | E48: 18915M107 | F48: Software and Computer Services | G48: 2201950 | H48: 3.6070143e+08 | I48: 0.0388
... A65: FCBR | B65: 46077 | C65: Radware Ltd. | D65: RDWR | E65: M81873107 | F65: Software and Computer Services | G65: 1353119 | H65: 30235444 | I65: 0.0033
A66: FCBR | B66: 46077 | C66: US Dollar | D66: $USD | F66: Other | G66: 20390272 | H66: 20390272 | I66: 0.0022
A67: FCBR | B67: 46077 | C67: OneSpan Inc. | D67: OSPN | E67: 68287N100 | F67: Software and Computer Services | G67: 1155042 | H67: 12520655 | I67: 0.0013
A68: FCBR | B68: 46077 | C68: Rapid7, Inc. | D68: RPD | E68: 753422104 | F68: Software and Computer Services | G68: 2014437 | H68: 12328354 | I68: 0.0013
A69: FCBR | B69: 46077 | C69: NCC Group Plc | D69: NCC.LN | E69: G64319109 | F69: Software and Computer Services | G69: 6623846 | H69: 11552388 | I69: 0.0012
A70: FCBR | B70: 46077 | C70: Japanese Yen | D70: $JPY | F70: Other | G70: 815712305 | H70: 5232279 | I70: 0.0006
A71: FCBR | B71: 46077 | C71: Canadian Dollar | D71: $CAD | F71: Other | G71: -127240 | H71: -92875.77 | I71: 0

Sheet AINF
A1: As Of | B1: Currency | C1: NAV | D1: Securities In Issue | E1: Net Assets | F1: Fund Return Series | G1: Benchmark Return Series
A2: 45631 | B2: USD | C2: 5.104953 | D2: 1000000 | E2: 5104953.8 | F2: 100 | G2: 100
A3: 45632 | B3: USD | C3: 5.149099 | D3: 1000000 | E3: 5149099.2 | F3: 100.86477 | G3: --
A4: 45635 | B4: USD | C4: 5.089238 | D4: 1000000 | E4: 5089238.4 | F4: 99.692162 | G4: 99.698046
A5: 45636 | B5: USD | C5: 5.019961 | D5: 1000000 | E5: 5019961.1 | F5: 98.335107 | G5: 98.334664
A6: 45637 | B6: USD | C6: 5.093328 | D6: 1000000 | E6: 5093328.6 | F6: 99.77228 | G6: 99.779436
A7: 45638 | B7: USD | C7: 5.090522 | D7: 2000000 | E7: 10181046 | F7: 99.717314 | G7: 99.726666
A8: 45639 | B8: USD | C8: 5.14664 | D8: 2000000 | E8: 10293281 | F8: 100.8166 | G8: 100.82887
A9: 45642 | B9: USD | C9: 5.215882 | D9: 2000000 | E9: 10431765 | F9: 102.17297 | G9: 102.1904
A10: 45643 | B10: USD | C10: 5.169691 | D10: 2000000 | E10: 10339383 | F10: 101.26814 | G10: 101.28601
A11: 45644 | B11: USD | C11: 5.017739 | D11: 2000000 | E11: 10035479 | F11: 98.291581 | G11: 98.310358
A12: 45645 | B12: USD | C12: 4.975434 | D12: 2000000 | E12: 9950868.9 | F12: 97.462876 | G12: 97.479071
A13: 45646 | B13: USD | C13: 5.029401 | D13: 2000000 | E13: 10058803 | F13: 98.520026 | G13: 98.535717
A14: 45649 | B14: USD | C14: 5.10432 | D14: 3000000 | E14: 15312961 | F14: 99.9876 | G14: 100.00936
A15: 45650 | B15: USD | C15: 5.158891 | D15: 3000000 | E15: 15476674 | F15: -- | G15: 101.08076
A16: 45653 | B16: USD | C16: 5.106835 | D16: 3000000 | E16: 15320506 | F16: -- | G16: 100.0357
A17: 45656 | B17: USD | C17: 5.035062 | D17: 3000000 | E17: 15105188 | F17: 98.630918 | G17: 98.63017
A18: 45657 | B18: USD | C18: 4.999048 | D18: 3000000 | E18: 14997145 | F18: 97.925446 | G18: 97.924306
A19: 45659 | B19: USD | C19: 5.006017 | D19: 3000000 | E19: 15018052 | F19: 98.061961 | G19: 98.06143
A20: 45660 | B20: USD | C20: 5.091241 | D20: 3000000 | E20: 15273725 | F20: 99.731398 | G20: 99.729729
A21: 45663 | B21: USD | C21: 5.182584 | D21: 3000000 | E21: 15547752 | F21: 101.5207 | G21: 101.52741
A22: 45664 | B22: USD | C22: 5.125954 | D22: 5000000 | E22: 25629772 | F22: 100.41138 | G22: 100.41783
A23: 45665 | B23: USD | C23: 5.099735 | D23: 5000000 | E23: 25498677 | F23: 99.897786 | G23: 99.903589
A24: 45666 | B24: USD | C24: 5.089847 | D24: 5000000 | E24: 25449238 | F24: 99.704091 | G24: 99.709439
A25: 45667 | B25: USD | C25: 4.999266 | D25: 5000000 | E25: 24996331 | F25: 97.929716 | G25: 97.931471
A26: 45670 | B26: USD | C26: 4.941926 | D26: 5000000 | E26: 24709634 | F26: 96.806494 | G26: 96.809066
A27: 45671 | B27: USD | C27: 4.960522 | D27: 5000000 | E27: 24802612 | F27: 97.170767 | G27: 97.174915
A28: 45672 | B28: USD | C28: 5.042492 | D28: 5000000 | E28: 25212465 | F28: 98.776463 | G28: 98.781415
... A120: 45806 | B120: USD | C120: 5.152362 | D120: 13000000 | E120: 66980714 | F120: 100.92869 | G120: 100.9898
A121: 45807 | B121: USD | C121: 5.14747 | D121: 13000000 | E121: 66917112 | F121: -- | G121: --
A122: 45810 | B122: USD | C122: 5.188353 | D122: 13000000 | E122: 67448600 | F122: 101.63371 | G122: 101.69773
A123: 45811 | B123: USD | C123: 5.245902 | D123: 14000000 | E123: 73442634 | F123: 102.76102 | G123: 102.82748
A124: 45812 | B124: USD | C124: 5.277068 | D124: 14000000 | E124: 73878954 | F124: -- | G124: --
A125: 45813 | B125: USD | C125: 5.268026 | D125: 14000000 | E125: 73752372 | F125: 103.19441 | G125: 103.26037
A126: 45814 | B126: USD | C126: 5.329753 | D126: 14000000 | E126: 74616554 | F126: 104.40357 | G126: 104.47282
A127: 45817 | B127: USD | C127: 5.395965 | D127: 14000000 | E127: 75543518 | F127: 105.70058 | G127: 105.77606
A128: 45818 | B128: USD | C128: 5.444568 | D128: 14000000 | E128: 76223966 | F128: 106.65266 | G128: 106.73153
A129: 45819 | B129: USD | C129: 5.452358 | D129: 14000000 | E129: 76333013 | F129: 106.80525 | G129: 106.88639
A130: 45820 | B130: USD | C130: 5.494308 | D130: 14000000 | E130: 76920323 | F130: 107.627 | G130: 107.71069
A131: 45821 | B131: USD | C131: 5.437612 | D131: 16000000 | E131: 87001795 | F131: 106.5164 | G131: 106.60336
A132: 45824 | B132: USD | C132: 5.525485 | D132: 16000000 | E132: 88407772 | F132: 108.23772 | G132: 108.32845
A133: 45825 | B133: USD | C133: 5.515625 | D133: 16000000 | E133: 88250003 | F133: 108.04458 | G133: 108.13757
A134: 45826 | B134: USD | C134: 5.541375 | D134: 16000000 | E134: 88662004 | F134: 108.54899 | G134: 108.64471
A135: 45827 | B135: USD | C135: 5.518272 | D135: 16000000 | E135: 88292366 | F135: 108.09643 | G135: 108.19174
A136: 45828 | B136: USD | C136: 5.493417 | D136: 16000000 | E136: 87894682 | F136: 107.60955 | G136: 107.70336
... A264: 46009 | B264: USD | C264: 7.033003 | D264: 50000000 | E264: 3.5165019e+08 | F264: 137.76822 | G264: 138.05822
A265: 46010 | B265: USD | C265: 7.17338 | D265: 50000000 | E265: 3.5866905e+08 | F265: -- | G265: 140.81611
A266: 46013 | B266: USD | C266: 7.248638 | D266: 53000000 | E266: 3.8417783e+08 | F266: 141.99226 | G266: 142.30115
A267: 46014 | B267: USD | C267: 7.278831 | D267: 54000000 | E267: 3.9305691e+08 | F267: 142.5837 | G267: 142.8959
A268: 46015 | B268: USD | C268: 7.303325 | D268: 54000000 | E268: 3.9437956e+08 | F268: 143.06351 | G268: 143.37716
A269: 46020 | B269: USD | C269: 7.342781 | D269: 54000000 | E269: 3.9651019e+08 | F269: 143.83641 | G269: 144.14267
A270: 46021 | B270: USD | C270: 7.326538 | D270: 54000000 | E270: 3.9563309e+08 | F270: 143.51823 | G270: 143.82431
A271: 46022 | B271: USD | C271: 7.26831 | D271: 54000000 | E271: 3.9248877e+08 | F271: 142.37761 | G271: 142.68293
A272: 46024 | B272: USD | C272: 7.379061 | D272: 54000000 | E272: 3.9846932e+08 | F272: 144.54709 | G272: 144.86391
A273: 46027 | B273: USD | C273: 7.510148 | D273: 54000000 | E273: 4.05548e+08 | F273: 147.11493 | G273: 147.44476
A274: 46028 | B274: USD | C274: 7.635713 | D274: 55000000 | E274: 4.1996422e+08 | F274: 149.5746 | G274: 149.91555
A275: 46029 | B275: USD | C275: 7.639863 | D275: 55000000 | E275: 4.2019247e+08 | F275: 149.65589 | G275: 149.99809
A276: 46030 | B276: USD | C276: 7.511811 | D276: 56000000 | E276: 4.2066146e+08 | F276: 147.14751 | G276: 147.47919
A277: 46031 | B277: USD | C277: 7.646686 | D277: 56000000 | E277: 4.2821445e+08 | F277: -- | G277: --
A278: 46034 | B278: USD | C278: 7.676485 | D278: 56000000 | E278: 4.2988317e+08 | F278: 150.37328 | G278: 150.72457
A279: 46035 | B279: USD | C279: 7.701077 | D279: 56000000 | E279: 4.3126033e+08 | F279: 150.855 | G279: 151.20947
A280: 46036 | B280: USD | C280: 7.653508 | D280: 56000000 | E280: 4.2859646e+08 | F280: 149.92318 | G280: 150.27807
A281: 46037 | B281: USD | C281: 7.708544 | D281: 56000000 | E281: 4.3167847e+08 | F281: 151.00127 | G281: 151.36268
A282: 46038 | B282: USD | C282: 7.774337 | D282: 56000000 | E282: 4.3536288e+08 | F282: 152.29008 | G282: 152.6599
A283: 46041 | B283: USD | C283: 7.763035 | D283: 56000000 | E283: 4.3472998e+08 | F283: 152.06869 | G283: 152.44098
A284: 46042 | B284: USD | C284: 7.595693 | D284: 56000000 | E284: 4.2535884e+08 | F284: 148.79065 | G284: 149.15516
A285: 46043 | B285: USD | C285: 7.723892 | D285: 57000000 | E285: 4.4026185e+08 | F285: 151.30192 | G285: 151.6769
A286: 46044 | B286: USD | C286: 7.796816 | D286: 57000000 | E286: 4.4441852e+08 | F286: 152.73042 | G286: 153.11072
A287: 46045 | B287: USD | C287: 7.766 | D287: 57000000 | E287: 4.4266205e+08 | F287: 152.12677 | G287: 152.50624
A288: 46048 | B288: USD | C288: 7.791457 | D288: 59000000 | E288: 4.5969602e+08 | F288: 152.62544 | G288: 153.01009
A289: 46049 | B289: USD | C289: 7.915383 | D289: 59000000 | E289: 4.6700763e+08 | F289: 155.053 | G289: 155.44881

Sheet DFEU
A1: As Of | B1: Currency | C1: NAV | D1: Securities In Issue | E1: Net Assets | F1: Fund Return Series | G1: Benchmark Return Series
A2: 45800 | B2: EUR | C2: 4.997688 | D2: 1000000 | E2: 4997688 | F2: 100 | G2: 100
A3: 45804 | B3: EUR | C3: 5.200417 | D3: 1000000 | E3: 5200418 | F3: 104.05646 | G3: 104.06211
A4: 45805 | B4: EUR | C4: 5.278065 | D4: 1000000 | E4: 5278065.7 | F4: -- | G4: --
A5: 45806 | B5: EUR | C5: 5.229013 | D5: 1000000 | E5: 5229013 | F5: 100 | G5: --
A6: 45807 | B6: EUR | C6: 5.238507 | D6: 1000000 | E6: 5238508 | F6: 104.81861 | G6: 104.82883
A7: 45810 | B7: EUR | C7: 5.249557 | D7: 1000000 | E7: 5249557.4 | F7: 105.03971 | G7: 105.05248
A8: 45811 | B8: EUR | C8: 5.338457 | D8: 1000000 | E8: 5338457.4 | F8: 106.81853 | G8: 106.83721
A9: 45812 | B9: EUR | C9: 5.309253 | D9: 1000000 | E9: 5309253.3 | F9: -- | G9: --
A10: 45813 | B10: EUR | C10: 5.42492 | D10: 1000000 | E10: 5424920.3 | F10: 108.54859 | G10: 108.5731
A11: 45814 | B11: EUR | C11: 5.283128 | D11: 1000000 | E11: 5283128.6 | F11: 105.71144 | G11: 105.73178
A12: 45817 | B12: EUR | C12: 5.21695 | D12: 3000000 | E12: 15650852 | F12: 104.38727 | G12: 104.0822
A13: 45818 | B13: EUR | C13: 4.943732 | D13: 3000000 | E13: 14831198 | F13: 98.920381 | G13: 98.915245
A14: 45819 | B14: EUR | C14: 5.004662 | D14: 3000000 | E14: 15013987 | F14: 100.13954 | G14: 100.1496
A15: 45820 | B15: EUR | C15: 5.023171 | D15: 3000000 | E15: 15069515 | F15: 100.5099 | G15: 100.52208
A16: 45821 | B16: EUR | C16: 5.083784 | D16: 3000000 | E16: 15251354 | F16: 101.72272 | G16: 101.73903
A17: 45824 | B17: EUR | C17: 5.079014 | D17: 4000000 | E17: 20316057 | F17: 101.62727 | G17: 101.64613
A18: 45825 | B18: EUR | C18: 5.070118 | D18: 4000000 | E18: 20280472 | F18: 101.44927 | G18: 101.47018
A19: 45826 | B19: EUR | C19: 5.081187 | D19: 4000000 | E19: 20324751 | F19: 101.67075 | G19: 101.69371
A20: 45827 | B20: EUR | C20: 5.026417 | D20: 4000000 | E20: 20105671 | F20: 100.57485 | G20: 100.59828
A21: 45828 | B21: EUR | C21: 5.058063 | D21: 4000000 | E21: 20232253 | F21: 101.20806 | G21: 101.23362
... A66: 45891 | B66: EUR | C66: 4.946638 | D66: 12000000 | E66: 59359667 | F66: 98.978528 | G66: 99.085674
A67: 45895 | B67: EUR | C67: 4.991731 | D67: -- | E67: -- | F67: 99.880805 | G67: 99.997571
A68: 45896 | B68: EUR | C68: 4.988731 | D68: 12000000 | E68: 59864775 | F68: 99.820777 | G68: 99.939058
A69: 45897 | B69: EUR | C69: 4.987553 | D69: 12000000 | E69: 59850639 | F69: 99.797206 | G69: 99.914641
A70: 45898 | B70: EUR | C70: 5.013645 | D70: 12000000 | E70: 60163749 | F70: 100.31929 | G70: 100.44227
A71: 45901 | B71: EUR | C71: 5.129651 | D71: 12000000 | E71: 61555823 | F71: 102.64048 | G71: 102.77325
A72: 45902 | B72: EUR | C72: 5.028534 | D72: 12000000 | E72: 60342412 | F72: 100.6172 | G72: 100.74896
A73: 45903 | B73: EUR | C73: 5.079878 | D73: 12000000 | E73: 60958542 | F73: 101.64456 | G73: 101.77885
A74: 45904 | B74: EUR | C74: 5.001845 | D74: 12000000 | E74: 60022145 | F74: 100.08318 | G74: 100.211
A75: 45905 | B75: EUR | C75: 5.022353 | D75: 12000000 | E75: 60268248 | F75: 100.49353 | G75: 100.62336
A76: 45908 | B76: EUR | C76: 5.09434 | D76: 13000000 | E76: 66226423 | F76: 101.93393 | G76: 102.07074
A77: 45909 | B77: EUR | C77: 5.077488 | D77: 14000000 | E77: 71084833 | F77: 101.59674 | G77: 101.73346
A78: 45910 | B78: EUR | C78: 5.191861 | D78: 14000000 | E78: 72686054 | F78: 103.88526 | G78: 104.03065
A79: 45911 | B79: EUR | C79: 5.349187 | D79: 14000000 | E79: 74888622 | F79: 107.03323 | G79: 107.1884
... A149: 46009 | B149: EUR | C149: 4.949497 | D149: 26000000 | E149: 1.2868693e+08 | F149: 99.035734 | G149: 99.241365
A150: 46010 | B150: EUR | C150: 4.994457 | D150: 26000000 | E150: 129855902 | F150: -- | G150: 100.14283
A151: 46013 | B151: EUR | C151: 4.988333 | D151: 26000000 | E151: 1.2969668e+08 | F151: 99.812813 | G151: 100.0237
A152: 46014 | B152: EUR | C152: 5.005782 | D152: 26000000 | E152: 1.3015036e+08 | F152: 100.16196 | G152: 100.37407
A153: 46015 | B153: EUR | C153: 5.00429 | D153: 26000000 | E153: 1.3011155e+08 | F153: 100.1321 | G153: 100.34453
A154: 46020 | B154: EUR | C154: 4.946901 | D154: 26000000 | E154: 128619448 | F154: 98.98379 | G154: 99.196472
A155: 46021 | B155: EUR | C155: 5.024462 | D155: 26000000 | E155: 1.3063602e+08 | F155: 100.53573 | G155: 100.75626
A156: 46022 | B156: EUR | C156: 5.022987 | D156: 26000000 | E156: 1.3059767e+08 | F156: 100.50621 | G156: 100.72688
A157: 46024 | B157: EUR | C157: 5.177995 | D157: 26000000 | E157: 1.3462789e+08 | F157: 103.60781 | G157: 103.84357
A158: 46027 | B158: EUR | C158: 5.474465 | D158: 26000000 | E158: 1.4233609e+08 | F158: 109.53995 | G158: 109.79832
A159: 46028 | B159: EUR | C159: 5.52047 | D159: 26000000 | E159: 1.4353224e+08 | F159: 110.46048 | G159: 110.72143
A160: 46029 | B160: EUR | C160: 5.746078 | D160: 27000000 | E160: 1.5514411e+08 | F160: 114.97472 | G160: 115.27217
A161: 46030 | B161: EUR | C161: 5.827066 | D161: 27000000 | E161: 1.573308e+08 | F161: 116.59523 | G161: 116.88279
A162: 46031 | B162: EUR | C162: 5.946783 | D162: 27000000 | E162: 1.6056315e+08 | F162: -- | G162: --
A163: 46034 | B163: EUR | C163: 6.002991 | D163: 27000000 | E163: 1.6208077e+08 | F163: 120.11536 | G163: 120.42028
A164: 46035 | B164: EUR | C164: 6.014587 | D164: 31000000 | E164: 1.864522e+08 | F164: 120.34739 | G164: 120.65197
A165: 46036 | B165: EUR | C165: 5.935945 | D165: 33000000 | E165: 1.9588621e+08 | F165: 118.77382 | G165: 119.07451
A166: 46037 | B166: EUR | C166: 5.925727 | D166: 36000000 | E166: 2.1332619e+08 | F166: 118.56937 | G166: 118.86828
A167: 46038 | B167: EUR | C167: 6.02066 | D167: 36000000 | E167: 2.1674376e+08 | F167: 120.46891 | G167: 120.77644
A168: 46041 | B168: EUR | C168: 6.049454 | D168: 36000000 | E168: 2.1778034e+08 | F168: 121.04505 | G168: 121.36154
A169: 46042 | B169: EUR | C169: 6.040418 | D169: 36000000 | E169: 2.1745507e+08 | F169: 120.86425 | G169: 121.18141
A170: 46043 | B170: EUR | C170: 5.944514 | D170: 38000000 | E170: 2.2589153e+08 | F170: 118.94528 | G170: 119.25592
A171: 46044 | B171: EUR | C171: 5.776732 | D171: 38000000 | E171: 2.1951584e+08 | F171: 115.58809 | G171: 115.88471
A172: 46045 | B172: EUR | C172: 5.9055 | D172: 41000000 | E172: 2.4212554e+08 | F172: 118.16464 | G172: 118.47068
A173: 46048 | B173: EUR | C173: 5.804501 | D173: 41000000 | E173: 2.3798457e+08 | F173: 116.14373 | G173: 116.44622
A174: 46049 | B174: EUR | C174: 5.896998 | D174: 41000000 | E174: 2.4177693e+08 | F174: 117.99452 | G174: 118.30548

Sheet MINE
A1: As Of | B1: Currency | C1: NAV | D1: Securities In Issue | E1: Net Assets | F1: Fund Return Series | G1: Benchmark Return Series
A2: 45098 | B2: USD | C2: 4.913997 | D2: 1000000 | E2: 4913997.9 | F2: 100 | G2: 100
A3: 45099 | B3: USD | C3: 4.884557 | D3: 1000000 | E3: 4884557.8 | F3: 99.400895 | G3: --
A4: 45100 | B4: USD | C4: 4.761274 | D4: 1000000 | E4: 4761274.8 | F4: 96.892082 | G4: 96.910707
A5: 45103 | B5: USD | C5: 4.814387 | D5: 1000000 | E5: 4814388 | F5: 97.972933 | G5: 97.999065
A6: 45104 | B6: USD | C6: 4.841511 | D6: 1000000 | E6: 4841511.1 | F6: 98.524908 | G6: 98.565022
A7: 45105 | B7: USD | C7: 4.747385 | D7: 1000000 | E7: 4747385.1 | F7: 96.60944 | G7: 96.659486
A8: 45106 | B8: USD | C8: 4.731446 | D8: 1000000 | E8: 4731446.4 | F8: 96.285081 | G8: 96.334738
A9: 45107 | B9: USD | C9: 4.790157 | D9: 1000000 | E9: 4790157.9 | F9: 97.479852 | G9: 97.50049
A10: 45110 | B10: USD | C10: 4.873975 | D10: 1000000 | E10: 4873975.3 | F10: 99.185551 | G10: 99.201815
A11: 45111 | B11: USD | C11: 4.901299 | D11: 1000000 | E11: 4901299.8 | F11: 99.741595 | G11: 99.785007
A12: 45112 | B12: USD | C12: 4.828275 | D12: 1000000 | E12: 4828275.9 | F12: -- | G12: --
A13: 45113 | B13: USD | C13: 4.665591 | D13: 1000000 | E13: 4665591.1 | F13: 94.94493 | G13: 94.991744
A14: 45114 | B14: USD | C14: 4.757057 | D14: 1000000 | E14: 4757057.5 | F14: 96.806266 | G14: 96.847423
A15: 45117 | B15: USD | C15: 4.779246 | D15: 1000000 | E15: 4779246.9 | F15: 97.257813 | G15: 97.309999
A16: 45118 | B16: USD | C16: 4.841777 | D16: 1000000 | E16: 4841777.1 | F16: 98.530321 | G16: 98.599476
A17: 45119 | B17: USD | C17: 5.028853 | D17: 1000000 | E17: 5028853.9 | F17: 102.33732 | G17: 102.40136
A18: 45120 | B18: USD | C18: 5.163453 | D18: 1000000 | E18: 5163453.6 | F18: 105.07644 | G18: 105.09998
A19: 45121 | B19: USD | C19: 5.125496 | D19: 1000000 | E19: 5125496.6 | F19: 104.30401 | G19: 104.33016
A20: 45124 | B20: USD | C20: 5.045572 | D20: 1000000 | E20: 5045572.6 | F20: 102.67756 | G20: 102.75108
A21: 45125 | B21: USD | C21: 5.070778 | D21: 1000000 | E21: 5070778.3 | F21: 103.1905 | G21: 103.24135
A22: 45126 | B22: USD | C22: 5.046604 | D22: 1000000 | E22: 5046604.7 | F22: 102.69856 | G22: 102.76656
A23: 45127 | B23: USD | C23: 5.078823 | D23: 1000000 | E23: 5078823.4 | F23: 103.35421 | G23: 103.41926
A24: 45128 | B24: USD | C24: 5.044092 | D24: 1000000 | E24: 5044092.6 | F24: 102.64744 | G24: 102.70797
... A48: 45162 | B48: USD | C48: 4.687502 | D48: 1000000 | E48: 4687502.1 | F48: 95.390819 | G48: 95.480554
A49: 45163 | B49: USD | C49: 4.649617 | D49: 1000000 | E49: 4649617.9 | F49: -- | G49: 94.705728
A50: 45167 | B50: USD | C50: 4.830676 | D50: 1000000 | E50: 4830676.5 | F50: 98.304415 | G50: 98.408466
A51: 45168 | B51: USD | C51: 4.865361 | D51: 1000000 | E51: 4865361.6 | F51: 99.010256 | G51: 99.096857
A52: 45169 | B52: USD | C52: 4.857079 | D52: 1000000 | E52: 4857079.8 | F52: 98.841717 | G52: 98.968413
A53: 45170 | B53: USD | C53: 4.940651 | D53: 1000000 | E53: 4940651.8 | F53: 100.54241 | G53: 100.62714
A54: 45173 | B54: USD | C54: 4.959923 | D54: 1000000 | E54: 4959923.4 | F54: 100.9346 | G54: 101.06542
A55: 45174 | B55: USD | C55: 4.855839 | D55: 1000000 | E55: 4855839.7 | F55: 98.816483 | G55: 98.886269
A56: 45175 | B56: USD | C56: 4.831749 | D56: 1000000 | E56: 4831749.1 | F56: 98.326251 | G56: 98.413578
A57: 45176 | B57: USD | C57: 4.743716 | D57: 1500000 | E57: 7115574.1 | F57: 96.534776 | G57: 96.597109
A58: 45177 | B58: USD | C58: 4.719343 | D58: 1500000 | E58: 7079014.9 | F58: 96.038785 | G58: 96.143118
A59: 45180 | B59: USD | C59: 4.829203 | D59: 1500000 | E59: 7243805.8 | F59: 98.274439 | G59: 98.365747
A60: 45181 | B60: USD | C60: 4.77693 | D60: 1500000 | E60: 7165396 | F60: 97.210682 | G60: 97.335337
A61: 45182 | B61: USD | C61: 4.769383 | D61: 1500000 | E61: 7154074.8 | F61: 97.0571 | G61: 97.191015
... A132: 45281 | B132: USD | C132: 5.016007 | D132: 2000000 | E132: 10032015 | F132: 102.07591 | G132: 102.23084
A133: 45282 | B133: USD | C133: 5.057804 | D133: 2000000 | E133: 10115608 | F133: -- | G133: 103.12812
A134: 45287 | B134: USD | C134: 5.138323 | D134: 2000000 | E134: 10276647 | F134: 104.56504 | G134: 104.75702
A135: 45288 | B135: USD | C135: 5.118477 | D135: 2000000 | E135: 10236955 | F135: 104.16118 | G135: 104.3641
A136: 45289 | B136: USD | C136: 5.071878 | D136: 2000000 | E136: 10143757 | F136: 103.21288 | G136: 103.43392
A137: 45293 | B137: USD | C137: 5.029773 | D137: 2000000 | E137: 10059548 | F137: 102.35604 | G137: 102.59771
A138: 45294 | B138: USD | C138: 4.972913 | D138: 2000000 | E138: 9945826.4 | F138: 101.19894 | G138: 101.43781
A139: 45295 | B139: USD | C139: 4.969248 | D139: 2000000 | E139: 9938496.3 | F139: 101.12436 | G139: 101.34309
A140: 45296 | B140: USD | C140: 4.983728 | D140: 2000000 | E140: 9967456.6 | F140: 101.41903 | G140: 101.64728
A141: 45299 | B141: USD | C141: 4.994826 | D141: 2000000 | E141: 9989652.7 | F141: 101.64487 | G141: 101.88414
A142: 45300 | B142: USD | C142: 4.900152 | D142: 2000000 | E142: 9800304 | F142: 99.718254 | G142: 99.95565
A143: 45301 | B143: USD | C143: 4.866882 | D143: 2000000 | E143: 9733765.3 | F143: 99.041208 | G143: 99.266149
A144: 45302 | B144: USD | C144: 4.849195 | D144: 2000000 | E144: 9698391.9 | F144: 98.681277 | G144: 98.909317
A145: 45303 | B145: USD | C145: 4.90936 | D145: 2000000 | E145: 9818721.3 | F145: 99.905637 | G145: 100.10088
... A222: 45414 | B222: USD | C222: 5.964638 | D222: 4500000 | E222: 26840874 | F222: 121.38058 | G222: 121.87808
A223: 45415 | B223: USD | C223: 6.088659 | D223: 4500000 | E223: 27398968 | F223: -- | G223: 124.42811
A224: 45419 | B224: USD | C224: 6.206055 | D224: 4500000 | E224: 27927250 | F224: 126.29342 | G224: 126.87149
A225: 45420 | B225: USD | C225: 6.122904 | D225: 4500000 | E225: 27553068 | F225: 124.6013 | G225: 125.15263
A226: 45421 | B226: USD | C226: 6.218888 | D226: 5000000 | E226: 31094441 | F226: 126.55457 | G226: 127.13659
A227: 45422 | B227: USD | C227: 6.259037 | D227: 5000000 | E227: 31295185 | F227: 127.37161 | G227: 127.94455
A228: 45425 | B228: USD | C228: 6.272912 | D228: 5000000 | E228: 31364563 | F228: 127.65396 | G228: 128.20782
A229: 45426 | B229: USD | C229: 6.419298 | D229: 5000000 | E229: 32096492 | F229: 130.63293 | G229: 131.2036
A230: 45427 | B230: USD | C230: 6.411234 | D230: 5000000 | E230: 32056172 | F230: 130.46882 | G230: 131.11371
A231: 45428 | B231: USD | C231: 6.403025 | D231: 5000000 | E231: 32015128 | F231: 130.30177 | G231: 130.88022
A232: 45429 | B232: USD | C232: 6.659701 | D232: 5000000 | E232: 33298507 | F232: 135.52513 | G232: 136.20497
A233: 45432 | B233: USD | C233: 6.748659 | D233: 5000000 | E233: 33743296 | F233: 137.33543 | G233: 138.04656
A234: 45433 | B234: USD | C234: 6.736376 | D234: 5000000 | E234: 33681881 | F234: 137.08547 | G234: 137.76795
A235: 45434 | B235: USD | C235: 6.395132 | D235: 5500000 | E235: 35173231 | F235: 130.14115 | G235: 130.71758
A236: 45435 | B236: USD | C236: 6.273369 | D236: 5500000 | E236: 34503533 | F236: 127.66326 | G236: 128.29128
A237: 45436 | B237: USD | C237: 6.321289 | D237: 5500000 | E237: 34767091 | F237: -- | G237: 129.23019
A238: 45440 | B238: USD | C238: 6.456118 | D238: 5500000 | E238: 35508652 | F238: 131.38221 | G238: 132.00149
A239: 45441 | B239: USD | C239: 6.314717 | D239: 5500000 | E239: 34730948 | F239: 128.5047 | G239: 129.15364
A240: 45442 | B240: USD | C240: 6.262759 | D240: 5500000 | E240: 34445176 | F240: 127.44735 | G240: 128.08404
A241: 45443 | B241: USD | C241: 6.243379 | D241: 6000000 | E241: 37460276 | F241: 127.05297 | G241: 127.64893
A242: 45446 | B242: USD | C242: 6.144907 | D242: 6000000 | E242: 36869442 | F242: 125.04906 | G242: 125.70442
A243: 45447 | B243: USD | C243: 5.899236 | D243: 6500000 | E243: 38345039 | F243: 120.04965 | G243: 120.60842
A244: 45448 | B244: USD | C244: 5.956765 | D244: 6500000 | E244: 38718974 | F244: 121.22036 | G244: 121.82049
A245: 45449 | B245: USD | C245: 6.064801 | D245: 6500000 | E245: 39421208 | F245: 123.4189 | G245: 124.05235
A246: 45450 | B246: USD | C246: 5.879867 | D246: 6500000 | E246: 38219142 | F246: 119.65549 | G246: 120.25335
A247: 45453 | B247: USD | C247: 5.928881 | D247: 6500000 | E247: 38537730 | F247: 120.65292 | G247: 121.26257
A248: 45454 | B248: USD | C248: 5.816831 | D248: 6500000 | E248: 37809404 | F248: 118.3727 | G248: 118.99445
A249: 45455 | B249: USD | C249: 5.813947 | D249: 6500000 | E249: 37790660 | F249: 118.31401 | G249: 118.86273
... A495: 45811 | B495: USD | C495: 5.612368 | D495: 11700595 | E495: 65668055 | F495: 114.21187 | G495: 115.26679
A496: 45812 | B496: USD | C496: 5.70035 | D496: 11700595 | E496: 66697494 | F496: -- | G496: --
A497: 45813 | B497: USD | C497: 5.81736 | D497: 11700595 | E497: 68066578 | F497: 118.38347 | G497: 119.46911
A498: 45814 | B498: USD | C498: 5.762169 | D498: 11700595 | E498: 67420809 | F498: 117.26033 | G498: 118.34605
A499: 45817 | B499: USD | C499: 5.802588 | D499: 11700595 | E499: 67893739 | F499: 118.08286 | G499: 119.17934
A500: 45818 | B500: USD | C500: 5.774857 | D500: 11700595 | E500: 67569271 | F500: 117.51853 | G500: 118.61267
A501: 45819 | B501: USD | C501: 5.735351 | D501: 11700595 | E501: 67107026 | F501: 116.71458 | G501: 117.80501
A502: 45820 | B502: USD | C502: 5.737975 | D502: 11700595 | E502: 67137730 | F502: 116.76798 | G502: 117.86298
A503: 45821 | B503: USD | C503: 5.724437 | D503: 11700595 | E503: 66979327 | F503: 116.49248 | G503: 117.58485
A504: 45824 | B504: USD | C504: 5.757016 | D504: 11700595 | E504: 67360513 | F504: 117.15546 | G504: 118.2596
A505: 45825 | B505: USD | C505: 5.709469 | D505: 11700595 | E505: 66804188 | F505: 116.18788 | G505: 117.29117
A506: 45826 | B506: USD | C506: 5.679831 | D506: 11700595 | E506: 66457411 | F506: 115.58475 | G506: 116.68356
A507: 45827 | B507: USD | C507: 5.574903 | D507: 11700595 | E507: 65229690 | F507: 113.44946 | G507: 114.53066
A508: 45828 | B508: USD | C508: 5.53753 | D508: 11700595 | E508: 64792396 | F508: 112.68892 | G508: 113.75497
... A636: 46009 | B636: USD | C636: 8.757085 | D636: 28211595 | E636: 2.4705135e+08 | F636: 178.20697 | G636: 180.53224
A637: 46010 | B637: USD | C637: 8.847941 | D637: 28211595 | E637: 2.4961453e+08 | F637: -- | G637: 182.20464
A638: 46013 | B638: USD | C638: 9.082104 | D638: 28211595 | E638: 2.5622066e+08 | F638: 184.82111 | G638: 187.11365
A639: 46014 | B639: USD | C639: 9.220018 | D639: 28211595 | E639: 2.6011142e+08 | F639: 187.62767 | G639: 189.97045
A640: 46015 | B640: USD | C640: 9.208264 | D640: 34211595 | E640: 3.1502941e+08 | F640: 187.38847 | G640: 189.73048
A641: 46020 | B641: USD | C641: 9.134625 | D641: 34211595 | E641: 3.1251012e+08 | F641: 185.88992 | G641: 188.21809
...

Sheet SL Macquarie Global Infr
A1: Date | B1: Open | C1: High | D1: Low | E1: Close | F1: Volume | J1: https://markets.ft.com/data/funds/tearsheet/historical?s=GB00B3K5WJ87:GBP
A2: 46097 | B2: 3.5 | C2: 3.5 | D2: 3.5 | E2: 3.5 | F2: 0 | J2: SL Macquarie Global Infrastructure Secs
A3: 46094 | B3: 3.45 | C3: 3.45 | D3: 3.45 | E3: 3.45 | F3: 0 | J3: GB00B3K5WJ87:GBP
A4: 46093 | B4: 3.46 | C4: 3.46 | D4: 3.46 | E4: 3.46 | F4: 0 | J4: Formula to convert Date: "=DATE(RIGHT(A2, 4), MONTH(1 & MID(A2, FIND(" ", A2) + 1, FIND(" ", A2, FIND(" ", A2) + 1) - FIND(" ", A2) - 1)), MID(A2, FIND(" ", A2, FIND(" ", A2) + 1) + 1, FIND(",", A2, FIND(",", A2) + 1) - FIND(" ", A2, FIND(" ", A2) + 1) - 1))"
A5: 46092 | B5: 3.48 | C5: 3.48 | D5: 3.48 | E5: 3.48 | F5: 0
A6: 46091 | B6: 3.46 | C6: 3.46 | D6: 3.46 | E6: 3.46 | F6: 0
A7: 46090 | B7: 3.49 | C7: 3.49 | D7: 3.49 | E7: 3.49 | F7: 0
A8: 46087 | B8: 3.54 | C8: 3.54 | D8: 3.54 | E8: 3.54 | F8: 0
A9: 46086 | B9: 3.51 | C9: 3.51 | D9: 3.51 | E9: 3.51 | F9: 0
A10: 46085 | B10: 3.52 | C10: 3.52 | D10: 3.52 | E10: 3.52 | F10: 0
A11: 46084 | B11: 3.56 | C11: 3.56 | D11: 3.56 | E11: 3.56 | F11: 0
A12: 46083 | B12: 3.54 | C12: 3.54 | D12: 3.54 | E12: 3.54 | F12: 0
A13: 46080 | B13: 3.52 | C13: 3.52 | D13: 3.52 | E13: 3.52 | F13: 0
A14: 46079 | B14: 3.52 | C14: 3.52 | D14: 3.52 | E14: 3.52 | F14: 0
A15: 46078 | B15: 3.53 | C15: 3.53 | D15: 3.53 | E15: 3.53 | F15: 0
A16: 46077 | B16: 3.5 | C16: 3.5 | D16: 3.5 | E16: 3.5 | F16: 0
... A258: 45733 | B258: 2.8 | C258: 2.8 | D258: 2.8 | E258: 2.8 | F258: 0

Sheet Burcu Dashboard
A1: Fund Name | B1: Lastest Price | C1: 1D% | D1: 1W% | E1: 1M% | F1: 3M% | H1: Since Portfolio change | T1: Portfolio update date | U1: 46080 | X1: Date | Y1: =A2 -> SL Asia | Z1: =A3 -> SL Gold | AA1: =A4 -> SL China | AB1: =A5 -> SL JPM NatRes | AC1: SL Ishares Pacific | AD1: SL Infrastructure
A2: SL Asia | B2: {=_xlfn.LET( _xlpm.Dates, INDIRECT("'"&$A2&"'!A:A"), _xlpm.Prices, INDIRECT("'"&$A2&"'!E:E"), _xlpm.LatestDate, MAX(_xlpm.Dates), _xlpm.LatestPrice, _xlfn.XLOOKUP(_xlpm.LatestDate, _xlpm.Dates, _xlpm.Prices, , 0, -1), _xlpm.PrevPrice, _xlfn.XLOOKUP(WORKDAY(_xlpm.LatestDate, -1), _xlpm.Dates, _xlpm.Prices, _xlpm.LatestPrice, -1, -1), _xlpm.LatestPrice )} -> #REF! | C2: {=_xlfn.LET( _xlpm.Dates, INDIRECT("'"&$A2&"'!A:A"), _xlpm.Prices, INDIRECT("'"&$A2&"'!E:E"), _xlpm.LatestDate, MAX(_xlpm.Dates), _xlpm.LatestPrice, _xlfn.XLOOKUP(_xlpm.LatestDate, _xlpm.Dates, _xlpm.Prices, , 0, -1), _xlpm.PrevPrice, _xlfn.XLOOKUP(WORKDAY(_xlpm.LatestDate, -1), _xlpm.Dates, _xlpm.Prices, _xlpm.LatestPrice, -1, -1), (_xlpm.LatestPrice / _xlpm.PrevPrice) - 1 )} -> #REF! | D2: {=_xlfn.LET( _xlpm.Dates, INDIRECT("'"&$A2&"'!A:A"), _xlpm.Prices, INDIRECT("'"&$A2&"'!E:E"), _xlpm.LatestDate, MAX(_xlpm.Dates), _xlpm.LatestPrice, _xlfn.XLOOKUP(_xlpm.LatestDate, _xlpm.Dates, _xlpm.Prices, , 0, -1), _xlpm.PrevPrice, _xlfn.XLOOKUP(_xlpm.LatestDate - 7, _xlpm.Dates, _xlpm.Prices, _xlpm.LatestPrice, -1, -1), (_xlpm.LatestPrice / _xlpm.PrevPrice) - 1 )} -> #REF! | E2: {=_xlfn.LET( _xlpm.Dates, INDIRECT("'"&$A2&"'!A:A"), _xlpm.Prices, INDIRECT("'"&$A2&"'!E:E"), _xlpm.LatestDate, MAX(_xlpm.Dates), _xlpm.LatestPrice, _xlfn.XLOOKUP(_xlpm.LatestDate, _xlpm.Dates, _xlpm.Prices, , 0, -1), _xlpm.PrevPrice, _xlfn.XLOOKUP(EDATE(_xlpm.LatestDate, -1), _xlpm.Dates, _xlpm.Prices, _xlpm.LatestPrice, -1, -1), (_xlpm.LatestPrice / _xlpm.PrevPrice) - 1 )} -> #REF! | F2: {=_xlfn.LET( _xlpm.Dates, INDIRECT("'"&$A2&"'!A:A"), _xlpm.Prices, INDIRECT("'"&$A2&"'!E:E"), _xlpm.LatestDate, MAX(_xlpm.Dates), _xlpm.LatestPrice, _xlfn.XLOOKUP(_xlpm.LatestDate, _xlpm.Dates, _xlpm.Prices, , 0, -1), _xlpm.PrevPrice, _xlfn.XLOOKUP(EDATE(_xlpm.LatestDate, -3), _xlpm.Dates, _xlpm.Prices, _xlpm.LatestPrice, -1, -1), (_xlpm.LatestPrice / _xlpm.PrevPrice) - 1 )} -> #REF! | H2: {=_xlfn.LET( _xlpm.Dates, INDIRECT("'"&$A2&"'!A:A"), _xlpm.Prices, INDIRECT("'"&$A2&"'!E:E"), _xlpm.LatestDate, MAX(_xlpm.Dates), _xlpm.TargetDate, $U$1, _xlpm.LatestPrice, _xlfn.XLOOKUP(_xlpm.LatestDate, _xlpm.Dates, _xlpm.Prices, , 0, -1), _xlpm.StartPrice, _xlfn.XLOOKUP(_xlpm.TargetDate, _xlpm.Dates, _xlpm.Prices, _xlpm.LatestPrice, -1, 1), (_xlpm.LatestPrice / _xlpm.StartPrice) - 1 )} -> #REF! | X2: =U1 -> 46080 | Y2: {=IF($X2="", "", _xlfn.LET( _xlpm.SheetName, Y$1, _xlpm.CurrentDate, $X2, _xlpm.StartDate, $X$2, _xlpm.Dates, INDIRECT("'"&_xlpm.SheetName&"'!A:A"), _xlpm.Prices, INDIRECT("'"&_xlpm.SheetName&"'!E:E"), _xlpm.StartPrice, _xlfn.XLOOKUP(_xlpm.StartDate, _xlpm.Dates, _xlpm.Prices, , 0, 1), _xlpm.CurrentPrice, _xlfn.XLOOKUP(_xlpm.CurrentDate, _xlpm.Dates, _xlpm.Prices, _xlpm.StartPrice, -1, 1), (_xlpm.CurrentPrice / _xlpm.StartPrice)-1 ))} -> #REF! | Z2: {=IF($X2="", "", _xlfn.LET( _xlpm.SheetName, Z$1, _xlpm.CurrentDate, $X2, _xlpm.StartDate, $X$2, _xlpm.Dates, INDIRECT("'"&_xlpm.SheetName&"'!A:A"), _xlpm.Prices, INDIRECT("'"&_xlpm.SheetName&"'!E:E"), _xlpm.StartPrice, _xlfn.XLOOKUP(_xlpm.StartDate, _xlpm.Dates, _xlpm.Prices, , 0, 1), _xlpm.CurrentPrice, _xlfn.XLOOKUP(_xlpm.CurrentDate, _xlpm.Dates, _xlpm.Prices, _xlpm.StartPrice, -1, 1), (_xlpm.CurrentPrice / _xlpm.StartPrice)-1 ))} -> #REF! | AA2: {=IF($X2="", "", _xlfn.LET( _xlpm.SheetName, AA$1, _xlpm.CurrentDate, $X2, _xlpm.StartDate, $X$2, _xlpm.Dates, INDIRECT("'"&_xlpm.SheetName&"'!A:A"), _xlpm.Prices, INDIRECT("'"&_xlpm.SheetName&"'!E:E"), _xlpm.StartPrice, _xlfn.XLOOKUP(_xlpm.StartDate, _xlpm.Dates, _xlpm.Prices, , 0, 1), _xlpm.CurrentPrice, _xlfn.XLOOKUP(_xlpm.CurrentDate, _xlpm.Dates, _xlpm.Prices, _xlpm.StartPrice, -1, 1), (_xlpm.CurrentPrice / _xlpm.StartPrice)-1 ))} -> #REF! | AB2: {=IF($X2="", "", _xlfn.LET( _xlpm.SheetName, AB$1, _xlpm.CurrentDate, $X2, _xlpm.StartDate, $X$2, _xlpm.Dates, INDIRECT("'"&_xlpm.SheetName&"'!A:A"), _xlpm.Prices, INDIRECT("'"&_xlpm.SheetName&"'!E:E"), _xlpm.StartPrice, _xlfn.XLOOKUP(_xlpm.StartDate, _xlpm.Dates, _xlpm.Prices, , 0, 1), _xlpm.CurrentPrice, _xlfn.XLOOKUP(_xlpm.CurrentDate, _xlpm.Dates, _xlpm.Prices, _xlpm.StartPrice, -1, 1), (_xlpm.CurrentPrice / _xlpm.StartPrice)-1 ))} -> #REF! | AC2: {=IF($X2="", "", _xlfn.LET( _xlpm.SheetName, AC$1, _xlpm.CurrentDate, $X2, _xlpm.StartDate, $X$2, _xlpm.Dates, INDIRECT("'"&_xlpm.SheetName&"'!A:A"), _xlpm.Prices, INDIRECT("'"&_xlpm.SheetName&"'!E:E"), _xlpm.StartPrice, _xlfn.XLOOKUP(_xlpm.StartDate, _xlpm.Dates, _xlpm.Prices, , 0, 1), _xlpm.CurrentPrice, _xlfn.XLOOKUP(_xlpm.CurrentDate, _xlpm.Dates, _xlpm.Prices, _xlpm.StartPrice, -1, 1), (_xlpm.CurrentPrice / _xlpm.StartPrice)-1 ))} -> #REF! | AD2: {=IF($X2="", "", _xlfn.LET( _xlpm.SheetName, AD$1, _xlpm.CurrentDate, $X2, _xlpm.StartDate, $X$2, _xlpm.Dates, INDIRECT("'"&_xlpm.SheetName&"'!A:A"), _xlpm.Prices, INDIRECT("'"&_xlpm.SheetName&"'!E:E"), _xlpm.StartPrice, _xlfn.XLOOKUP(_xlpm.StartDate, _xlpm.Dates, _xlpm.Prices, , 0, 1), _xlpm.CurrentPrice, _xlfn.XLOOKUP(_xlpm.CurrentDate, _xlpm.Dates, _xlpm.Prices, _xlpm.StartPrice, -1, 1), (_xlpm.CurrentPrice / _xlpm.StartPrice)-1 ))} -> #REF!
A3: SL Gold | B3: {=_xlfn.LET( _xlpm.Dates, INDIRECT("'"&$A3&"'!A:A"), _xlpm.Prices, INDIRECT("'"&$A3&"'!E:E"), _xlpm.LatestDate, MAX(_xlpm.Dates), _xlpm.LatestPrice, _xlfn.XLOOKUP(_xlpm.LatestDate, _xlpm.Dates, _xlpm.Prices, , 0, -1), _xlpm.PrevPrice, _xlfn.XLOOKUP(WORKDAY(_xlpm.LatestDate, -1), _xlpm.Dates, _xlpm.Prices, _xlpm.LatestPrice, -1, -1), _xlpm.LatestPrice )} -> #REF! | C3: {=_xlfn.LET( _xlpm.Dates, INDIRECT("'"&$A3&"'!A:A"), _xlpm.Prices, INDIRECT("'"&$A3&"'!E:E"), _xlpm.LatestDate, MAX(_xlpm.Dates), _xlpm.LatestPrice, _xlfn.XLOOKUP(_xlpm.LatestDate, _xlpm.Dates, _xlpm.Prices, , 0, -1), _xlpm.PrevPrice, _xlfn.XLOOKUP(WORKDAY(_xlpm.LatestDate, -1), _xlpm.Dates, _xlpm.Prices, _xlpm.LatestPrice, -1, -1), (_xlpm.LatestPrice / _xlpm.PrevPrice) - 1 )} -> #REF! | D3: {=_xlfn.LET( _xlpm.Dates, INDIRECT("'"&$A3&"'!A:A"), _xlpm.Prices, INDIRECT("'"&$A3&"'!E:E"), _xlpm.LatestDate, MAX(_xlpm.Dates), _xlpm.LatestPrice, _xlfn.XLOOKUP(_xlpm.LatestDate, _xlpm.Dates, _xlpm.Prices, , 0, -1), _xlpm.PrevPrice, _xlfn.XLOOKUP(_xlpm.LatestDate - 7, _xlpm.Dates, _xlpm.Prices, _xlpm.LatestPrice, -1, -1), (_xlpm.LatestPrice / _xlpm.PrevPrice) - 1 )} -> #REF! | E3: {=_xlfn.LET( _xlpm.Dates, INDIRECT("'"&$A3&"'!A:A"), _xlpm.Prices, INDIRECT("'"&$A3&"'!E:E"), _xlpm.LatestDate, MAX(_xlpm.Dates), _xlpm.LatestPrice, _xlfn.XLOOKUP(_xlpm.LatestDate, _xlpm.Dates, _xlpm.Prices, , 0, -1), _xlpm.PrevPrice, _xlfn.XLOOKUP(EDATE(_xlpm.LatestDate, -1), _xlpm.Dates, _xlpm.Prices, _xlpm.LatestPrice, -1, -1), (_xlpm.LatestPrice / _xlpm.PrevPrice) - 1 )} -> #REF! | F3: {=_xlfn.LET( _xlpm.Dates, INDIRECT("'"&$A3&"'!A:A"), _xlpm.Prices, INDIRECT("'"&$A3&"'!E:E"), _xlpm.LatestDate, MAX(_xlpm.Dates), _xlpm.LatestPrice, _xlfn.XLOOKUP(_xlpm.LatestDate, _xlpm.Dates, _xlpm.Prices, , 0, -1), _xlpm.PrevPrice, _xlfn.XLOOKUP(EDATE(_xlpm.LatestDate, -3), _xlpm.Dates, _xlpm.Prices, _xlpm.LatestPrice, -1, -1), (_xlpm.LatestPrice / _xlpm.PrevPrice) - 1 )} -> #REF! | H3: {=_xlfn.LET( _xlpm.Dates, INDIRECT("'"&$A3&"'!A:A"), _xlpm.Prices, INDIRECT("'"&$A3&"'!E:E"), _xlpm.LatestDate, MAX(_xlpm.Dates), _xlpm.TargetDate, $U$1, _xlpm.LatestPrice, _xlfn.XLOOKUP(_xlpm.LatestDate, _xlpm.Dates, _xlpm.Prices, , 0, -1), _xlpm.StartPrice, _xlfn.XLOOKUP(_xlpm.TargetDate, _xlpm.Dates, _xlpm.Prices, _xlpm.LatestPrice, -1, 1), (_xlpm.LatestPrice / _xlpm.StartPrice) - 1 )} -> #REF! | X3: =IF(X2="", "", IF(X2 >= TODAY(), "", X2+1)) -> 46081 | Y3: {=IF($X3="", "", _xlfn.LET( _xlpm.SheetName, Y$1, _xlpm.CurrentDate, $X3, _xlpm.StartDate, $X$2, _xlpm.Dates, INDIRECT("'"&_xlpm.SheetName&"'!A:A"), _xlpm.Prices, INDIRECT("'"&_xlpm.SheetName&"'!E:E"), _xlpm.StartPrice, _xlfn.XLOOKUP(_xlpm.StartDate, _xlpm.Dates, _xlpm.Prices, , 0, 1), _xlpm.CurrentPrice, _xlfn.XLOOKUP(_xlpm.CurrentDate, _xlpm.Dates, _xlpm.Prices, _xlpm.StartPrice, -1, 1), (_xlpm.CurrentPrice / _xlpm.StartPrice)-1 ))} -> #REF! | Z3: {=IF($X3="", "", _xlfn.LET( _xlpm.SheetName, Z$1, _xlpm.CurrentDate, $X3, _xlpm.StartDate, $X$2, _xlpm.Dates, INDIRECT("'"&_xlpm.SheetName&"'!A:A"), _xlpm.Prices, INDIRECT("'"&_xlpm.SheetName&"'!E:E"), _xlpm.StartPrice, _xlfn.XLOOKUP(_xlpm.StartDate, _xlpm.Dates, _xlpm.Prices, , 0, 1), _xlpm.CurrentPrice, _xlfn.XLOOKUP(_xlpm.CurrentDate, _xlpm.Dates, _xlpm.Prices, _xlpm.StartPrice, -1, 1), (_xlpm.CurrentPrice / _xlpm.StartPrice)-1 ))} -> #REF! | AA3: {=IF($X3="", "", _xlfn.LET( _xlpm.SheetName, AA$1, _xlpm.CurrentDate, $X3, _xlpm.StartDate, $X$2, _xlpm.Dates, INDIRECT("'"&_xlpm.SheetName&"'!A:A"), _xlpm.Prices, INDIRECT("'"&_xlpm.SheetName&"'!E:E"), _xlpm.StartPrice, _xlfn.XLOOKUP(_xlpm.StartDate, _xlpm.Dates, _xlpm.Prices, , 0, 1), _xlpm.CurrentPrice, _xlfn.XLOOKUP(_xlpm.CurrentDate, _xlpm.Dates, _xlpm.Prices, _xlpm.StartPrice, -1, 1), (_xlpm.CurrentPrice / _xlpm.StartPrice)-1 ))} -> #REF! | AB3: {=IF($X3="", "", _xlfn.LET( _xlpm.SheetName, AB$1, _xlpm.CurrentDate, $X3, _xlpm.StartDate, $X$2, _xlpm.Dates, INDIRECT("'"&_xlpm.SheetName&"'!A:A"), _xlpm.Prices, INDIRECT("'"&_xlpm.SheetName&"'!E:E"), _xlpm.StartPrice, _xlfn.XLOOKUP(_xlpm.StartDate, _xlpm.Dates, _xlpm.Prices, , 0, 1), _xlpm.CurrentPrice, _xlfn.XLOOKUP(_xlpm.CurrentDate, _xlpm.Dates, _xlpm.Prices, _xlpm.StartPrice, -1, 1), (_xlpm.CurrentPrice / _xlpm.StartPrice)-1 ))} -> #REF! | AC3: {=IF($X3="", "", _xlfn.LET( _xlpm.SheetName, AC$1, _xlpm.CurrentDate, $X3, _xlpm.StartDate, $X$2, _xlpm.Dates, INDIRECT("'"&_xlpm.SheetName&"'!A:A"), _xlpm.Prices, INDIRECT("'"&_xlpm.SheetName&"'!E:E"), _xlpm.StartPrice, _xlfn.XLOOKUP(_xlpm.StartDate, _xlpm.Dates, _xlpm.Prices, , 0, 1), _xlpm.CurrentPrice, _xlfn.XLOOKUP(_xlpm.CurrentDate, _xlpm.Dates, _xlpm.Prices, _xlpm.StartPrice, -1, 1), (_xlpm.CurrentPrice / _xlpm.StartPrice)-1 ))} -> #REF! | AD3: {=IF($X3="", "", _xlfn.LET( _xlpm.SheetName, AD$1, _xlpm.CurrentDate, $X3, _xlpm.StartDate, $X$2, _xlpm.Dates, INDIRECT("'"&_xlpm.SheetName&"'!A:A"), _xlpm.Prices, INDIRECT("'"&_xlpm.SheetName&"'!E:E"), _xlpm.StartPrice, _xlfn.XLOOKUP(_xlpm.StartDate, _xlpm.Dates, _xlpm.Prices, , 0, 1), _xlpm.CurrentPrice, _xlfn.XLOOKUP(_xlpm.CurrentDate, _xlpm.Dates, _xlpm.Prices, _xlpm.StartPrice, -1, 1), (_xlpm.CurrentPrice / _xlpm.StartPrice)-1 ))} -> #REF!
A4: SL China | B4: {=_xlfn.LET( _xlpm.Dates, INDIRECT("'"&$A4&"'!A:A"), _xlpm.Prices, INDIRECT("'"&$A4&"'!E:E"), _xlpm.LatestDate, MAX(_xlpm.Dates), _xlpm.LatestPrice, _xlfn.XLOOKUP(_xlpm.LatestDate, _xlpm.Dates, _xlpm.Prices, , 0, -1), _xlpm.PrevPrice, _xlfn.XLOOKUP(WORKDAY(_xlpm.LatestDate, -1), _xlpm.Dates, _xlpm.Prices, _xlpm.LatestPrice, -1, -1), _xlpm.LatestPrice )} -> #REF! | C4: {=_xlfn.LET( _xlpm.Dates, INDIRECT("'"&$A4&"'!A:A"), _xlpm.Prices, INDIRECT("'"&$A4&"'!E:E"), _xlpm.LatestDate, MAX(_xlpm.Dates), _xlpm.LatestPrice, _xlfn.XLOOKUP(_xlpm.LatestDate, _xlpm.Dates, _xlpm.Prices, , 0, -1), _xlpm.PrevPrice, _xlfn.XLOOKUP(WORKDAY(_xlpm.LatestDate, -1), _xlpm.Dates, _xlpm.Prices, _xlpm.LatestPrice, -1, -1), (_xlpm.LatestPrice / _xlpm.PrevPrice) - 1 )} -> #REF! | D4: {=_xlfn.LET( _xlpm.Dates, INDIRECT("'"&$A4&"'!A:A"), _xlpm.Prices, INDIRECT("'"&$A4&"'!E:E"), _xlpm.LatestDate, MAX(_xlpm.Dates), _xlpm.LatestPrice, _xlfn.XLOOKUP(_xlpm.LatestDate, _xlpm.Dates, _xlpm.Prices, , 0, -1), _xlpm.PrevPrice, _xlfn.XLOOKUP(_xlpm.LatestDate - 7, _xlpm.Dates, _xlpm.Prices, _xlpm.LatestPrice, -1, -1), (_xlpm.LatestPrice / _xlpm.PrevPrice) - 1 )} -> #REF! | E4: {=_xlfn.LET( _xlpm.Dates, INDIRECT("'"&$A4&"'!A:A"), _xlpm.Prices, INDIRECT("'"&$A4&"'!E:E"), _xlpm.LatestDate, MAX(_xlpm.Dates), _xlpm.LatestPrice, _xlfn.XLOOKUP(_xlpm.LatestDate, _xlpm.Dates, _xlpm.Prices, , 0, -1), _xlpm.PrevPrice, _xlfn.XLOOKUP(EDATE(_xlpm.LatestDate, -1), _xlpm.Dates, _xlpm.Prices, _xlpm.LatestPrice, -1, -1), (_xlpm.LatestPrice / _xlpm.PrevPrice) - 1 )} -> #REF! | F4: {=_xlfn.LET( _xlpm.Dates, INDIRECT("'"&$A4&"'!A:A"), _xlpm.Prices, INDIRECT("'"&$A4&"'!E:E"), _xlpm.LatestDate, MAX(_xlpm.Dates), _xlpm.LatestPrice, _xlfn.XLOOKUP(_xlpm.LatestDate, _xlpm.Dates, _xlpm.Prices, , 0, -1), _xlpm.PrevPrice, _xlfn.XLOOKUP(EDATE(_xlpm.LatestDate, -3), _xlpm.Dates, _xlpm.Prices, _xlpm.LatestPrice, -1, -1), (_xlpm.LatestPrice / _xlpm.PrevPrice) - 1 )} -> #REF! | H4: {=_xlfn.LET( _xlpm.Dates, INDIRECT("'"&$A4&"'!A:A"), _xlpm.Prices, INDIRECT("'"&$A4&"'!E:E"), _xlpm.LatestDate, MAX(_xlpm.Dates), _xlpm.TargetDate, $U$1, _xlpm.LatestPrice, _xlfn.XLOOKUP(_xlpm.LatestDate, _xlpm.Dates, _xlpm.Prices, , 0, -1), _xlpm.StartPrice, _xlfn.XLOOKUP(_xlpm.TargetDate, _xlpm.Dates, _xlpm.Prices, _xlpm.LatestPrice, -1, 1), (_xlpm.LatestPrice / _xlpm.StartPrice) - 1 )} -> #REF! | X4: =IF(X3="", "", IF(X3 >= TODAY(), "", X3+1)) -> 46082 | Y4: {=IF($X4="", "", _xlfn.LET( _xlpm.SheetName, Y$1, _xlpm.CurrentDate, $X4, _xlpm.StartDate, $X$2, _xlpm.Dates, INDIRECT("'"&_xlpm.SheetName&"'!A:A"), _xlpm.Prices, INDIRECT("'"&_xlpm.SheetName&"'!E:E"), _xlpm.StartPrice, _xlfn.XLOOKUP(_xlpm.StartDate, _xlpm.Dates, _xlpm.Prices, , 0, 1), _xlpm.CurrentPrice, _xlfn.XLOOKUP(_xlpm.CurrentDate, _xlpm.Dates, _xlpm.Prices, _xlpm.StartPrice, -1, 1), (_xlpm.CurrentPrice / _xlpm.StartPrice)-1 ))} -> #REF! | Z4: {=IF($X4="", "", _xlfn.LET( _xlpm.SheetName, Z$1, _xlpm.CurrentDate, $X4, _xlpm.StartDate, $X$2, _xlpm.Dates, INDIRECT("'"&_xlpm.SheetName&"'!A:A"), _xlpm.Prices, INDIRECT("'"&_xlpm.SheetName&"'!E:E"), _xlpm.StartPrice, _xlfn.XLOOKUP(_xlpm.StartDate, _xlpm.Dates, _xlpm.Prices, , 0, 1), _xlpm.CurrentPrice, _xlfn.XLOOKUP(_xlpm.CurrentDate, _xlpm.Dates, _xlpm.Prices, _xlpm.StartPrice, -1, 1), (_xlpm.CurrentPrice / _xlpm.StartPrice)-1 ))} -> #REF! | AA4: {=IF($X4="", "", _xlfn.LET( _xlpm.SheetName, AA$1, _xlpm.CurrentDate, $X4, _xlpm.StartDate, $X$2, _xlpm.Dates, INDIRECT("'"&_xlpm.SheetName&"'!A:A"), _xlpm.Prices, INDIRECT("'"&_xlpm.SheetName&"'!E:E"), _xlpm.StartPrice, _xlfn.XLOOKUP(_xlpm.StartDate, _xlpm.Dates, _xlpm.Prices, , 0, 1), _xlpm.CurrentPrice, _xlfn.XLOOKUP(_xlpm.CurrentDate, _xlpm.Dates, _xlpm.Prices, _xlpm.StartPrice, -1, 1), (_xlpm.CurrentPrice / _xlpm.StartPrice)-1 ))} -> #REF! | AB4: {=IF($X4="", "", _xlfn.LET( _xlpm.SheetName, AB$1, _xlpm.CurrentDate, $X4, _xlpm.StartDate, $X$2, _xlpm.Dates, INDIRECT("'"&_xlpm.SheetName&"'!A:A"), _xlpm.Prices, INDIRECT("'"&_xlpm.SheetName&"'!E:E"), _xlpm.StartPrice, _xlfn.XLOOKUP(_xlpm.StartDate, _xlpm.Dates, _xlpm.Prices, , 0, 1), _xlpm.CurrentPrice, _xlfn.XLOOKUP(_xlpm.CurrentDate, _xlpm.Dates, _xlpm.Prices, _xlpm.StartPrice, -1, 1), (_xlpm.CurrentPrice / _xlpm.StartPrice)-1 ))} -> #REF! | AC4: {=IF($X4="", "", _xlfn.LET( _xlpm.SheetName, AC$1, _xlpm.CurrentDate, $X4, _xlpm.StartDate, $X$2, _xlpm.Dates, INDIRECT("'"&_xlpm.SheetName&"'!A:A"), _xlpm.Prices, INDIRECT("'"&_xlpm.SheetName&"'!E:E"), _xlpm.StartPrice, _xlfn.XLOOKUP(_xlpm.StartDate, _xlpm.Dates, _xlpm.Prices, , 0, 1), _xlpm.CurrentPrice, _xlfn.XLOOKUP(_xlpm.CurrentDate, _xlpm.Dates, _xlpm.Prices, _xlpm.StartPrice, -1, 1), (_xlpm.CurrentPrice / _xlpm.StartPrice)-1 ))} -> #REF! | AD4: {=IF($X4="", "", _xlfn.LET( _xlpm.SheetName, AD$1, _xlpm.CurrentDate, $X4, _xlpm.StartDate, $X$2, _xlpm.Dates, INDIRECT("'"&_xlpm.SheetName&"'!A:A"), _xlpm.Prices, INDIRECT("'"&_xlpm.SheetName&"'!E:E"), _xlpm.StartPrice, _xlfn.XLOOKUP(_xlpm.StartDate, _xlpm.Dates, _xlpm.Prices, , 0, 1), _xlpm.CurrentPrice, _xlfn.XLOOKUP(_xlpm.CurrentDate, _xlpm.Dates, _xlpm.Prices, _xlpm.StartPrice, -1, 1), (_xlpm.CurrentPrice / _xlpm.StartPrice)-1 ))} -> #REF!
A5: SL JPM NatRes | B5: {=_xlfn.LET( _xlpm.Dates, INDIRECT("'"&$A5&"'!A:A"), _xlpm.Prices, INDIRECT("'"&$A5&"'!E:E"), _xlpm.LatestDate, MAX(_xlpm.Dates), _xlpm.LatestPrice, _xlfn.XLOOKUP(_xlpm.LatestDate, _xlpm.Dates, _xlpm.Prices, , 0, -1), _xlpm.PrevPrice, _xlfn.XLOOKUP(WORKDAY(_xlpm.LatestDate, -1), _xlpm.Dates, _xlpm.Prices, _xlpm.LatestPrice, -1, -1), _xlpm.LatestPrice )} -> #REF! | C5: {=_xlfn.LET( _xlpm.Dates, INDIRECT("'"&$A5&"'!A:A"), _xlpm.Prices, INDIRECT("'"&$A5&"'!E:E"), _xlpm.LatestDate, MAX(_xlpm.Dates), _xlpm.LatestPrice, _xlfn.XLOOKUP(_xlpm.LatestDate, _xlpm.Dates, _xlpm.Prices, , 0, -1), _xlpm.PrevPrice, _xlfn.XLOOKUP(WORKDAY(_xlpm.LatestDate, -1), _xlpm.Dates, _xlpm.Prices, _xlpm.LatestPrice, -1, -1), (_xlpm.LatestPrice / _xlpm.PrevPrice) - 1 )} -> #REF! | D5: {=_xlfn.LET( _xlpm.Dates, INDIRECT("'"&$A5&"'!A:A"), _xlpm.Prices, INDIRECT("'"&$A5&"'!E:E"), _xlpm.LatestDate, MAX(_xlpm.Dates), _xlpm.LatestPrice, _xlfn.XLOOKUP(_xlpm.LatestDate, _xlpm.Dates, _xlpm.Prices, , 0, -1), _xlpm.PrevPrice, _xlfn.XLOOKUP(_xlpm.LatestDate - 7, _xlpm.Dates, _xlpm.Prices, _xlpm.LatestPrice, -1, -1), (_xlpm.LatestPrice / _xlpm.PrevPrice) - 1 )} -> #REF! | E5: {=_xlfn.LET( _xlpm.Dates, INDIRECT("'"&$A5&"'!A:A"), _xlpm.Prices, INDIRECT("'"&$A5&"'!E:E"), _xlpm.LatestDate, MAX(_xlpm.Dates), _xlpm.LatestPrice, _xlfn.XLOOKUP(_xlpm.LatestDate, _xlpm.Dates, _xlpm.Prices, , 0, -1), _xlpm.PrevPrice, _xlfn.XLOOKUP(EDATE(_xlpm.LatestDate, -1), _xlpm.Dates, _xlpm.Prices, _xlpm.LatestPrice, -1, -1), (_xlpm.LatestPrice / _xlpm.PrevPrice) - 1 )} -> #REF! | F5: {=_xlfn.LET( _xlpm.Dates, INDIRECT("'"&$A5&"'!A:A"), _xlpm.Prices, INDIRECT("'"&$A5&"'!E:E"), _xlpm.LatestDate, MAX(_xlpm.Dates), _xlpm.LatestPrice, _xlfn.XLOOKUP(_xlpm.LatestDate, _xlpm.Dates, _xlpm.Prices, , 0, -1), _xlpm.PrevPrice, _xlfn.XLOOKUP(EDATE(_xlpm.LatestDate, -3), _xlpm.Dates, _xlpm.Prices, _xlpm.LatestPrice, -1, -1), (_xlpm.LatestPrice / _xlpm.PrevPrice) - 1 )} -> #REF! | H5: {=_xlfn.LET( _xlpm.Dates, INDIRECT("'"&$A5&"'!A:A"), _xlpm.Prices, INDIRECT("'"&$A5&"'!E:E"), _xlpm.LatestDate, MAX(_xlpm.Dates), _xlpm.TargetDate, $U$1, _xlpm.LatestPrice, _xlfn.XLOOKUP(_xlpm.LatestDate, _xlpm.Dates, _xlpm.Prices, , 0, -1), _xlpm.StartPrice, _xlfn.XLOOKUP(_xlpm.TargetDate, _xlpm.Dates, _xlpm.Prices, _xlpm.LatestPrice, -1, 1), (_xlpm.LatestPrice / _xlpm.StartPrice) - 1 )} -> #REF! | X5: =IF(X4="", "", IF(X4 >= TODAY(), "", X4+1)) -> 46083 | Y5: {=IF($X5="", "", _xlfn.LET( _xlpm.SheetName, Y$1, _xlpm.CurrentDate, $X5, _xlpm.StartDate, $X$2, _xlpm.Dates, INDIRECT("'"&_xlpm.SheetName&"'!A:A"), _xlpm.Prices, INDIRECT("'"&_xlpm.SheetName&"'!E:E"), _xlpm.StartPrice, _xlfn.XLOOKUP(_xlpm.StartDate, _xlpm.Dates, _xlpm.Prices, , 0, 1), _xlpm.CurrentPrice, _xlfn.XLOOKUP(_xlpm.CurrentDate, _xlpm.Dates, _xlpm.Prices, _xlpm.StartPrice, -1, 1), (_xlpm.CurrentPrice / _xlpm.StartPrice)-1 ))} -> #REF! | Z5: {=IF($X5="", "", _xlfn.LET( _xlpm.SheetName, Z$1, _xlpm.CurrentDate, $X5, _xlpm.StartDate, $X$2, _xlpm.Dates, INDIRECT("'"&_xlpm.SheetName&"'!A:A"), _xlpm.Prices, INDIRECT("'"&_xlpm.SheetName&"'!E:E"), _xlpm.StartPrice, _xlfn.XLOOKUP(_xlpm.StartDate, _xlpm.Dates, _xlpm.Prices, , 0, 1), _xlpm.CurrentPrice, _xlfn.XLOOKUP(_xlpm.CurrentDate, _xlpm.Dates, _xlpm.Prices, _xlpm.StartPrice, -1, 1), (_xlpm.CurrentPrice / _xlpm.StartPrice)-1 ))} -> #REF! | AA5: {=IF($X5="", "", _xlfn.LET( _xlpm.SheetName, AA$1, _xlpm.CurrentDate, $X5, _xlpm.StartDate, $X$2, _xlpm.Dates, INDIRECT("'"&_xlpm.SheetName&"'!A:A"), _xlpm.Prices, INDIRECT("'"&_xlpm.SheetName&"'!E:E"), _xlpm.StartPrice, _xlfn.XLOOKUP(_xlpm.StartDate, _xlpm.Dates, _xlpm.Prices, , 0, 1), _xlpm.CurrentPrice, _xlfn.XLOOKUP(_xlpm.CurrentDate, _xlpm.Dates, _xlpm.Prices, _xlpm.StartPrice, -1, 1), (_xlpm.CurrentPrice / _xlpm.StartPrice)-1 ))} -> #REF! | AB5: {=IF($X5="", "", _xlfn.LET( _xlpm.SheetName, AB$1, _xlpm.CurrentDate, $X5, _xlpm.StartDate, $X$2, _xlpm.Dates, INDIRECT("'"&_xlpm.SheetName&"'!A:A"), _xlpm.Prices, INDIRECT("'"&_xlpm.SheetName&"'!E:E"), _xlpm.StartPrice, _xlfn.XLOOKUP(_xlpm.StartDate, _xlpm.Dates, _xlpm.Prices, , 0, 1), _xlpm.CurrentPrice, _xlfn.XLOOKUP(_xlpm.CurrentDate, _xlpm.Dates, _xlpm.Prices, _xlpm.StartPrice, -1, 1), (_xlpm.CurrentPrice / _xlpm.StartPrice)-1 ))} -> #REF! | AC5: {=IF($X5="", "", _xlfn.LET( _xlpm.SheetName, AC$1, _xlpm.CurrentDate, $X5, _xlpm.StartDate, $X$2, _xlpm.Dates, INDIRECT("'"&_xlpm.SheetName&"'!A:A"), _xlpm.Prices, INDIRECT("'"&_xlpm.SheetName&"'!E:E"), _xlpm.StartPrice, _xlfn.XLOOKUP(_xlpm.StartDate, _xlpm.Dates, _xlpm.Prices, , 0, 1), _xlpm.CurrentPrice, _xlfn.XLOOKUP(_xlpm.CurrentDate, _xlpm.Dates, _xlpm.Prices, _xlpm.StartPrice, -1, 1), (_xlpm.CurrentPrice / _xlpm.StartPrice)-1 ))} -> #REF! | AD5: {=IF($X5="", "", _xlfn.LET( _xlpm.SheetName, AD$1, _xlpm.CurrentDate, $X5, _xlpm.StartDate, $X$2, _xlpm.Dates, INDIRECT("'"&_xlpm.SheetName&"'!A:A"), _xlpm.Prices, INDIRECT("'"&_xlpm.SheetName&"'!E:E"), _xlpm.StartPrice, _xlfn.XLOOKUP(_xlpm.StartDate, _xlpm.Dates, _xlpm.Prices, , 0, 1), _xlpm.CurrentPrice, _xlfn.XLOOKUP(_xlpm.CurrentDate, _xlpm.Dates, _xlpm.Prices, _xlpm.StartPrice, -1, 1), (_xlpm.CurrentPrice / _xlpm.StartPrice)-1 ))} -> #REF!
A6: SL Ishares Pacific | B6: {=_xlfn.LET( _xlpm.Dates, INDIRECT("'"&$A6&"'!A:A"), _xlpm.Prices, INDIRECT("'"&$A6&"'!E:E"), _xlpm.LatestDate, MAX(_xlpm.Dates), _xlpm.LatestPrice, _xlfn.XLOOKUP(_xlpm.LatestDate, _xlpm.Dates, _xlpm.Prices, , 0, -1), _xlpm.PrevPrice, _xlfn.XLOOKUP(WORKDAY(_xlpm.LatestDate, -1), _xlpm.Dates, _xlpm.Prices, _xlpm.LatestPrice, -1, -1), _xlpm.LatestPrice )} -> #REF! | C6: {=_xlfn.LET( _xlpm.Dates, INDIRECT("'"&$A6&"'!A:A"), _xlpm.Prices, INDIRECT("'"&$A6&"'!E:E"), _xlpm.LatestDate, MAX(_xlpm.Dates), _xlpm.LatestPrice, _xlfn.XLOOKUP(_xlpm.LatestDate, _xlpm.Dates, _xlpm.Prices, , 0, -1), _xlpm.PrevPrice, _xlfn.XLOOKUP(WORKDAY(_xlpm.LatestDate, -1), _xlpm.Dates, _xlpm.Prices, _xlpm.LatestPrice, -1, -1), (_xlpm.LatestPrice / _xlpm.PrevPrice) - 1 )} -> #REF! | D6: {=_xlfn.LET( _xlpm.Dates, INDIRECT("'"&$A6&"'!A:A"), _xlpm.Prices, INDIRECT("'"&$A6&"'!E:E"), _xlpm.LatestDate, MAX(_xlpm.Dates), _xlpm.LatestPrice, _xlfn.XLOOKUP(_xlpm.LatestDate, _xlpm.Dates, _xlpm.Prices, , 0, -1), _xlpm.PrevPrice, _xlfn.XLOOKUP(_xlpm.LatestDate - 7, _xlpm.Dates, _xlpm.Prices, _xlpm.LatestPrice, -1, -1), (_xlpm.LatestPrice / _xlpm.PrevPrice) - 1 )} -> #REF! | E6: {=_xlfn.LET( _xlpm.Dates, INDIRECT("'"&$A6&"'!A:A"), _xlpm.Prices, INDIRECT("'"&$A6&"'!E:E"), _xlpm.LatestDate, MAX(_xlpm.Dates), _xlpm.LatestPrice, _xlfn.XLOOKUP(_xlpm.LatestDate, _xlpm.Dates, _xlpm.Prices, , 0, -1), _xlpm.PrevPrice, _xlfn.XLOOKUP(EDATE(_xlpm.LatestDate, -1), _xlpm.Dates, _xlpm.Prices, _xlpm.LatestPrice, -1, -1), (_xlpm.LatestPrice / _xlpm.PrevPrice) - 1 )} -> #REF! | F6: {=_xlfn.LET( _xlpm.Dates, INDIRECT("'"&$A6&"'!A:A"), _xlpm.Prices, INDIRECT("'"&$A6&"'!E:E"), _xlpm.LatestDate, MAX(_xlpm.Dates), _xlpm.LatestPrice, _xlfn.XLOOKUP(_xlpm.LatestDate, _xlpm.Dates, _xlpm.Prices, , 0, -1), _xlpm.PrevPrice, _xlfn.XLOOKUP(EDATE(_xlpm.LatestDate, -3), _xlpm.Dates, _xlpm.Prices, _xlpm.LatestPrice, -1, -1), (_xlpm.LatestPrice / _xlpm.PrevPrice) - 1 )} -> #REF! | H6: {=_xlfn.LET( _xlpm.Dates, INDIRECT("'"&$A6&"'!A:A"), _xlpm.Prices, INDIRECT("'"&$A6&"'!E:E"), _xlpm.LatestDate, MAX(_xlpm.Dates), _xlpm.TargetDate, $U$1, _xlpm.LatestPrice, _xlfn.XLOOKUP(_xlpm.LatestDate, _xlpm.Dates, _xlpm.Prices, , 0, -1), _xlpm.StartPrice, _xlfn.XLOOKUP(_xlpm.TargetDate, _xlpm.Dates, _xlpm.Prices, _xlpm.LatestPrice, -1, 1), (_xlpm.LatestPrice / _xlpm.StartPrice) - 1 )} -> #REF! | X6: =IF(X5="", "", IF(X5 >= TODAY(), "", X5+1)) -> 46084 | Y6: {=IF($X6="", "", _xlfn.LET( _xlpm.SheetName, Y$1, _xlpm.CurrentDate, $X6, _xlpm.StartDate, $X$2, _xlpm.Dates, INDIRECT("'"&_xlpm.SheetName&"'!A:A"), _xlpm.Prices, INDIRECT("'"&_xlpm.SheetName&"'!E:E"), _xlpm.StartPrice, _xlfn.XLOOKUP(_xlpm.StartDate, _xlpm.Dates, _xlpm.Prices, , 0, 1), _xlpm.CurrentPrice, _xlfn.XLOOKUP(_xlpm.CurrentDate, _xlpm.Dates, _xlpm.Prices, _xlpm.StartPrice, -1, 1), (_xlpm.CurrentPrice / _xlpm.StartPrice)-1 ))} -> #REF! | Z6: {=IF($X6="", "", _xlfn.LET( _xlpm.SheetName, Z$1, _xlpm.CurrentDate, $X6, _xlpm.StartDate, $X$2, _xlpm.Dates, INDIRECT("'"&_xlpm.SheetName&"'!A:A"), _xlpm.Prices, INDIRECT("'"&_xlpm.SheetName&"'!E:E"), _xlpm.StartPrice, _xlfn.XLOOKUP(_xlpm.StartDate, _xlpm.Dates, _xlpm.Prices, , 0, 1), _xlpm.CurrentPrice, _xlfn.XLOOKUP(_xlpm.CurrentDate, _xlpm.Dates, _xlpm.Prices, _xlpm.StartPrice, -1, 1), (_xlpm.CurrentPrice / _xlpm.StartPrice)-1 ))} -> #REF! | AA6: {=IF($X6="", "", _xlfn.LET( _xlpm.SheetName, AA$1, _xlpm.CurrentDate, $X6, _xlpm.StartDate, $X$2, _xlpm.Dates, INDIRECT("'"&_xlpm.SheetName&"'!A:A"), _xlpm.Prices, INDIRECT("'"&_xlpm.SheetName&"'!E:E"), _xlpm.StartPrice, _xlfn.XLOOKUP(_xlpm.StartDate, _xlpm.Dates, _xlpm.Prices, , 0, 1), _xlpm.CurrentPrice, _xlfn.XLOOKUP(_xlpm.CurrentDate, _xlpm.Dates, _xlpm.Prices, _xlpm.StartPrice, -1, 1), (_xlpm.CurrentPrice / _xlpm.StartPrice)-1 ))} -> #REF! | AB6: {=IF($X6="", "", _xlfn.LET( _xlpm.SheetName, AB$1, _xlpm.CurrentDate, $X6, _xlpm.StartDate, $X$2, _xlpm.Dates, INDIRECT("'"&_xlpm.SheetName&"'!A:A"), _xlpm.Prices, INDIRECT("'"&_xlpm.SheetName&"'!E:E"), _xlpm.StartPrice, _xlfn.XLOOKUP(_xlpm.StartDate, _xlpm.Dates, _xlpm.Prices, , 0, 1), _xlpm.CurrentPrice, _xlfn.XLOOKUP(_xlpm.CurrentDate, _xlpm.Dates, _xlpm.Prices, _xlpm.StartPrice, -1, 1), (_xlpm.CurrentPrice / _xlpm.StartPrice)-1 ))} -> #REF! | AC6: {=IF($X6="", "", _xlfn.LET( _xlpm.SheetName, AC$1, _xlpm.CurrentDate, $X6, _xlpm.StartDate, $X$2, _xlpm.Dates, INDIRECT("'"&_xlpm.SheetName&"'!A:A"), _xlpm.Prices, INDIRECT("'"&_xlpm.SheetName&"'!E:E"), _xlpm.StartPrice, _xlfn.XLOOKUP(_xlpm.StartDate, _xlpm.Dates, _xlpm.Prices, , 0, 1), _xlpm.CurrentPrice, _xlfn.XLOOKUP(_xlpm.CurrentDate, _xlpm.Dates, _xlpm.Prices, _xlpm.StartPrice, -1, 1), (_xlpm.CurrentPrice / _xlpm.StartPrice)-1 ))} -> #REF! | AD6: {=IF($X6="", "", _xlfn.LET( _xlpm.SheetName, AD$1, _xlpm.CurrentDate, $X6, _xlpm.StartDate, $X$2, _xlpm.Dates, INDIRECT("'"&_xlpm.SheetName&"'!A:A"), _xlpm.Prices, INDIRECT("'"&_xlpm.SheetName&"'!E:E"), _xlpm.StartPrice, _xlfn.XLOOKUP(_xlpm.StartDate, _xlpm.Dates, _xlpm.Prices, , 0, 1), _xlpm.CurrentPrice, _xlfn.XLOOKUP(_xlpm.CurrentDate, _xlpm.Dates, _xlpm.Prices, _xlpm.StartPrice, -1, 1), (_xlpm.CurrentPrice / _xlpm.StartPrice)-1 ))} -> #REF!
A7: SL Infrastructure | B7: {=_xlfn.LET( _xlpm.Dates, INDIRECT("'"&$A7&"'!A:A"), _xlpm.Prices, INDIRECT("'"&$A7&"'!E:E"), _xlpm.LatestDate, MAX(_xlpm.Dates), _xlpm.LatestPrice, _xlfn.XLOOKUP(_xlpm.LatestDate, _xlpm.Dates, _xlpm.Prices, , 0, -1), _xlpm.PrevPrice, _xlfn.XLOOKUP(WORKDAY(_xlpm.LatestDate, -1), _xlpm.Dates, _xlpm.Prices, _xlpm.LatestPrice, -1, -1), _xlpm.LatestPrice )} -> #REF! | C7: {=_xlfn.LET( _xlpm.Dates, INDIRECT("'"&$A7&"'!A:A"), _xlpm.Prices, INDIRECT("'"&$A7&"'!E:E"), _xlpm.LatestDate, MAX(_xlpm.Dates), _xlpm.LatestPrice, _xlfn.XLOOKUP(_xlpm.LatestDate, _xlpm.Dates, _xlpm.Prices, , 0, -1), _xlpm.PrevPrice, _xlfn.XLOOKUP(WORKDAY(_xlpm.LatestDate, -1), _xlpm.Dates, _xlpm.Prices, _xlpm.LatestPrice, -1, -1), (_xlpm.LatestPrice / _xlpm.PrevPrice) - 1 )} -> #REF! | D7: {=_xlfn.LET( _xlpm.Dates, INDIRECT("'"&$A7&"'!A:A"), _xlpm.Prices, INDIRECT("'"&$A7&"'!E:E"), _xlpm.LatestDate, MAX(_xlpm.Dates), _xlpm.LatestPrice, _xlfn.XLOOKUP(_xlpm.LatestDate, _xlpm.Dates, _xlpm.Prices, , 0, -1), _xlpm.PrevPrice, _xlfn.XLOOKUP(_xlpm.LatestDate - 7, _xlpm.Dates, _xlpm.Prices, _xlpm.LatestPrice, -1, -1), (_xlpm.LatestPrice / _xlpm.PrevPrice) - 1 )} -> #REF! | E7: {=_xlfn.LET( _xlpm.Dates, INDIRECT("'"&$A7&"'!A:A"), _xlpm.Prices, INDIRECT("'"&$A7&"'!E:E"), _xlpm.LatestDate, MAX(_xlpm.Dates), _xlpm.LatestPrice, _xlfn.XLOOKUP(_xlpm.LatestDate, _xlpm.Dates, _xlpm.Prices, , 0, -1), _xlpm.PrevPrice, _xlfn.XLOOKUP(EDATE(_xlpm.LatestDate, -1), _xlpm.Dates, _xlpm.Prices, _xlpm.LatestPrice, -1, -1), (_xlpm.LatestPrice / _xlpm.PrevPrice) - 1 )} -> #REF! | F7: {=_xlfn.LET( _xlpm.Dates, INDIRECT("'"&$A7&"'!A:A"), _xlpm.Prices, INDIRECT("'"&$A7&"'!E:E"), _xlpm.LatestDate, MAX(_xlpm.Dates), _xlpm.LatestPrice, _xlfn.XLOOKUP(_xlpm.LatestDate, _xlpm.Dates, _xlpm.Prices, , 0, -1), _xlpm.PrevPrice, _xlfn.XLOOKUP(EDATE(_xlpm.LatestDate, -3), _xlpm.Dates, _xlpm.Prices, _xlpm.LatestPrice, -1, -1), (_xlpm.LatestPrice / _xlpm.PrevPrice) - 1 )} -> #REF! | H7: {=_xlfn.LET( _xlpm.Dates, INDIRECT("'"&$A7&"'!A:A"), _xlpm.Prices, INDIRECT("'"&$A7&"'!E:E"), _xlpm.LatestDate, MAX(_xlpm.Dates), _xlpm.TargetDate, $U$1, _xlpm.LatestPrice, _xlfn.XLOOKUP(_xlpm.LatestDate, _xlpm.Dates, _xlpm.Prices, , 0, -1), _xlpm.StartPrice, _xlfn.XLOOKUP(_xlpm.TargetDate, _xlpm.Dates, _xlpm.Prices, _xlpm.LatestPrice, -1, 1), (_xlpm.LatestPrice / _xlpm.StartPrice) - 1 )} -> #REF! | X7: =IF(X6="", "", IF(X6 >= TODAY(), "", X6+1)) -> 46085 | Y7: {=IF($X7="", "", _xlfn.LET( _xlpm.SheetName, Y$1, _xlpm.CurrentDate, $X7, _xlpm.StartDate, $X$2, _xlpm.Dates, INDIRECT("'"&_xlpm.SheetName&"'!A:A"), _xlpm.Prices, INDIRECT("'"&_xlpm.SheetName&"'!E:E"), _xlpm.StartPrice, _xlfn.XLOOKUP(_xlpm.StartDate, _xlpm.Dates, _xlpm.Prices, , 0, 1), _xlpm.CurrentPrice, _xlfn.XLOOKUP(_xlpm.CurrentDate, _xlpm.Dates, _xlpm.Prices, _xlpm.StartPrice, -1, 1), (_xlpm.CurrentPrice / _xlpm.StartPrice)-1 ))} -> #REF! | Z7: {=IF($X7="", "", _xlfn.LET( _xlpm.SheetName, Z$1, _xlpm.CurrentDate, $X7, _xlpm.StartDate, $X$2, _xlpm.Dates, INDIRECT("'"&_xlpm.SheetName&"'!A:A"), _xlpm.Prices, INDIRECT("'"&_xlpm.SheetName&"'!E:E"), _xlpm.StartPrice, _xlfn.XLOOKUP(_xlpm.StartDate, _xlpm.Dates, _xlpm.Prices, , 0, 1), _xlpm.CurrentPrice, _xlfn.XLOOKUP(_xlpm.CurrentDate, _xlpm.Dates, _xlpm.Prices, _xlpm.StartPrice, -1, 1), (_xlpm.CurrentPrice / _xlpm.StartPrice)-1 ))} -> #REF! | AA7: {=IF($X7="", "", _xlfn.LET( _xlpm.SheetName, AA$1, _xlpm.CurrentDate, $X7, _xlpm.StartDate, $X$2, _xlpm.Dates, INDIRECT("'"&_xlpm.SheetName&"'!A:A"), _xlpm.Prices, INDIRECT("'"&_xlpm.SheetName&"'!E:E"), _xlpm.StartPrice, _xlfn.XLOOKUP(_xlpm.StartDate, _xlpm.Dates, _xlpm.Prices, , 0, 1), _xlpm.CurrentPrice, _xlfn.XLOOKUP(_xlpm.CurrentDate, _xlpm.Dates, _xlpm.Prices, _xlpm.StartPrice, -1, 1), (_xlpm.CurrentPrice / _xlpm.StartPrice)-1 ))} -> #REF! | AB7: {=IF($X7="", "", _xlfn.LET( _xlpm.SheetName, AB$1, _xlpm.CurrentDate, $X7, _xlpm.StartDate, $X$2, _xlpm.Dates, INDIRECT("'"&_xlpm.SheetName&"'!A:A"), _xlpm.Prices, INDIRECT("'"&_xlpm.SheetName&"'!E:E"), _xlpm.StartPrice, _xlfn.XLOOKUP(_xlpm.StartDate, _xlpm.Dates, _xlpm.Prices, , 0, 1), _xlpm.CurrentPrice, _xlfn.XLOOKUP(_xlpm.CurrentDate, _xlpm.Dates, _xlpm.Prices, _xlpm.StartPrice, -1, 1), (_xlpm.CurrentPrice / _xlpm.StartPrice)-1 ))} -> #REF! | AC7: {=IF($X7="", "", _xlfn.LET( _xlpm.SheetName, AC$1, _xlpm.CurrentDate, $X7, _xlpm.StartDate, $X$2, _xlpm.Dates, INDIRECT("'"&_xlpm.SheetName&"'!A:A"), _xlpm.Prices, INDIRECT("'"&_xlpm.SheetName&"'!E:E"), _xlpm.StartPrice, _xlfn.XLOOKUP(_xlpm.StartDate, _xlpm.Dates, _xlpm.Prices, , 0, 1), _xlpm.CurrentPrice, _xlfn.XLOOKUP(_xlpm.CurrentDate, _xlpm.Dates, _xlpm.Prices, _xlpm.StartPrice, -1, 1), (_xlpm.CurrentPrice / _xlpm.StartPrice)-1 ))} -> #REF! | AD7: {=IF($X7="", "", _xlfn.LET( _xlpm.SheetName, AD$1, _xlpm.CurrentDate, $X7, _xlpm.StartDate, $X$2, _xlpm.Dates, INDIRECT("'"&_xlpm.SheetName&"'!A:A"), _xlpm.Prices, INDIRECT("'"&_xlpm.SheetName&"'!E:E"), _xlpm.StartPrice, _xlfn.XLOOKUP(_xlpm.StartDate, _xlpm.Dates, _xlpm.Prices, , 0, 1), _xlpm.CurrentPrice, _xlfn.XLOOKUP(_xlpm.CurrentDate, _xlpm.Dates, _xlpm.Prices, _xlpm.StartPrice, -1, 1), (_xlpm.CurrentPrice / _xlpm.StartPrice)-1 ))} -> #REF!
X8: =IF(X7="", "", IF(X7 >= TODAY(), "", X7+1)) -> 46086 | Y8: {=IF($X8="", "", _xlfn.LET( _xlpm.SheetName, Y$1, _xlpm.CurrentDate, $X8, _xlpm.StartDate, $X$2, _xlpm.Dates, INDIRECT("'"&_xlpm.SheetName&"'!A:A"), _xlpm.Prices, INDIRECT("'"&_xlpm.SheetName&"'!E:E"), _xlpm.StartPrice, _xlfn.XLOOKUP(_xlpm.StartDate, _xlpm.Dates, _xlpm.Prices, , 0, 1), _xlpm.CurrentPrice, _xlfn.XLOOKUP(_xlpm.CurrentDate, _xlpm.Dates, _xlpm.Prices, _xlpm.StartPrice, -1, 1), (_xlpm.CurrentPrice / _xlpm.StartPrice)-1 ))} -> #REF! | Z8: {=IF($X8="", "", _xlfn.LET( _xlpm.SheetName, Z$1, _xlpm.CurrentDate, $X8, _xlpm.StartDate, $X$2, _xlpm.Dates, INDIRECT("'"&_xlpm.SheetName&"'!A:A"), _xlpm.Prices, INDIRECT("'"&_xlpm.SheetName&"'!E:E"), _xlpm.StartPrice, _xlfn.XLOOKUP(_xlpm.StartDate, _xlpm.Dates, _xlpm.Prices, , 0, 1), _xlpm.CurrentPrice, _xlfn.XLOOKUP(_xlpm.CurrentDate, _xlpm.Dates, _xlpm.Prices, _xlpm.StartPrice, -1, 1), (_xlpm.CurrentPrice / _xlpm.StartPrice)-1 ))} -> #REF! | AA8: {=IF($X8="", "", _xlfn.LET( _xlpm.SheetName, AA$1, _xlpm.CurrentDate, $X8, _xlpm.StartDate, $X$2, _xlpm.Dates, INDIRECT("'"&_xlpm.SheetName&"'!A:A"), _xlpm.Prices, INDIRECT("'"&_xlpm.SheetName&"'!E:E"), _xlpm.StartPrice, _xlfn.XLOOKUP(_xlpm.StartDate, _xlpm.Dates, _xlpm.Prices, , 0, 1), _xlpm.CurrentPrice, _xlfn.XLOOKUP(_xlpm.CurrentDate, _xlpm.Dates, _xlpm.Prices, _xlpm.StartPrice, -1, 1), (_xlpm.CurrentPrice / _xlpm.StartPrice)-1 ))} -> #REF! | AB8: {=IF($X8="", "", _xlfn.LET( _xlpm.SheetName, AB$1, _xlpm.CurrentDate, $X8, _xlpm.StartDate, $X$2, _xlpm.Dates, INDIRECT("'"&_xlpm.SheetName&"'!A:A"), _xlpm.Prices, INDIRECT("'"&_xlpm.SheetName&"'!E:E"), _xlpm.StartPrice, _xlfn.XLOOKUP(_xlpm.StartDate, _xlpm.Dates, _xlpm.Prices, , 0, 1), _xlpm.CurrentPrice, _xlfn.XLOOKUP(_xlpm.CurrentDate, _xlpm.Dates, _xlpm.Prices, _xlpm.StartPrice, -1, 1), (_xlpm.CurrentPrice / _xlpm.StartPrice)-1 ))} -> #REF! | AC8: {=IF($X8="", "", _xlfn.LET( _xlpm.SheetName, AC$1, _xlpm.CurrentDate, $X8, _xlpm.StartDate, $X$2, _xlpm.Dates, INDIRECT("'"&_xlpm.SheetName&"'!A:A"), _xlpm.Prices, INDIRECT("'"&_xlpm.SheetName&"'!E:E"), _xlpm.StartPrice, _xlfn.XLOOKUP(_xlpm.StartDate, _xlpm.Dates, _xlpm.Prices, , 0, 1), _xlpm.CurrentPrice, _xlfn.XLOOKUP(_xlpm.CurrentDate, _xlpm.Dates, _xlpm.Prices, _xlpm.StartPrice, -1, 1), (_xlpm.CurrentPrice / _xlpm.StartPrice)-1 ))} -> #REF! | AD8: {=IF($X8="", "", _xlfn.LET( _xlpm.SheetName, AD$1, _xlpm.CurrentDate, $X8, _xlpm.StartDate, $X$2, _xlpm.Dates, INDIRECT("'"&_xlpm.SheetName&"'!A:A"), _xlpm.Prices, INDIRECT("'"&_xlpm.SheetName&"'!E:E"), _xlpm.StartPrice, _xlfn.XLOOKUP(_xlpm.StartDate, _xlpm.Dates, _xlpm.Prices, , 0, 1), _xlpm.CurrentPrice, _xlfn.XLOOKUP(_xlpm.CurrentDate, _xlpm.Dates, _xlpm.Prices, _xlpm.StartPrice, -1, 1), (_xlpm.CurrentPrice / _xlpm.StartPrice)-1 ))} -> #REF!
X9: =IF(X8="", "", IF(X8 >= TODAY(), "", X8+1)) -> 46087 | Y9: {=IF($X9="", "", _xlfn.LET( _xlpm.SheetName, Y$1, _xlpm.CurrentDate, $X9, _xlpm.StartDate, $X$2, _xlpm.Dates, INDIRECT("'"&_xlpm.SheetName&"'!A:A"), _xlpm.Prices, INDIRECT("'"&_xlpm.SheetName&"'!E:E"), _xlpm.StartPrice, _xlfn.XLOOKUP(_xlpm.StartDate, _xlpm.Dates, _xlpm.Prices, , 0, 1), _xlpm.CurrentPrice, _xlfn.XLOOKUP(_xlpm.CurrentDate, _xlpm.Dates, _xlpm.Prices, _xlpm.StartPrice, -1, 1), (_xlpm.CurrentPrice / _xlpm.StartPrice)-1 ))} -> #REF! | Z9: {=IF($X9="", "", _xlfn.LET( _xlpm.SheetName, Z$1, _xlpm.CurrentDate, $X9, _xlpm.StartDate, $X$2, _xlpm.Dates, INDIRECT("'"&_xlpm.SheetName&"'!A:A"), _xlpm.Prices, INDIRECT("'"&_xlpm.SheetName&"'!E:E"), _xlpm.StartPrice, _xlfn.XLOOKUP(_xlpm.StartDate, _xlpm.Dates, _xlpm.Prices, , 0, 1), _xlpm.CurrentPrice, _xlfn.XLOOKUP(_xlpm.CurrentDate, _xlpm.Dates, _xlpm.Prices, _xlpm.StartPrice, -1, 1), (_xlpm.CurrentPrice / _xlpm.StartPrice)-1 ))} -> #REF! | AA9: {=IF($X9="", "", _xlfn.LET( _xlpm.SheetName, AA$1, _xlpm.CurrentDate, $X9, _xlpm.StartDate, $X$2, _xlpm.Dates, INDIRECT("'"&_xlpm.SheetName&"'!A:A"), _xlpm.Prices, INDIRECT("'"&_xlpm.SheetName&"'!E:E"), _xlpm.StartPrice, _xlfn.XLOOKUP(_xlpm.StartDate, _xlpm.Dates, _xlpm.Prices, , 0, 1), _xlpm.CurrentPrice, _xlfn.XLOOKUP(_xlpm.CurrentDate, _xlpm.Dates, _xlpm.Prices, _xlpm.StartPrice, -1, 1), (_xlpm.CurrentPrice / _xlpm.StartPrice)-1 ))} -> #REF! | AB9: {=IF($X9="", "", _xlfn.LET( _xlpm.SheetName, AB$1, _xlpm.CurrentDate, $X9, _xlpm.StartDate, $X$2, _xlpm.Dates, INDIRECT("'"&_xlpm.SheetName&"'!A:A"), _xlpm.Prices, INDIRECT("'"&_xlpm.SheetName&"'!E:E"), _xlpm.StartPrice, _xlfn.XLOOKUP(_xlpm.StartDate, _xlpm.Dates, _xlpm.Prices, , 0, 1), _xlpm.CurrentPrice, _xlfn.XLOOKUP(_xlpm.CurrentDate, _xlpm.Dates, _xlpm.Prices, _xlpm.StartPrice, -1, 1), (_xlpm.CurrentPrice / _xlpm.StartPrice)-1 ))} -> #REF! | AC9: {=IF($X9="", "", _xlfn.LET( _xlpm.SheetName, AC$1, _xlpm.CurrentDate, $X9, _xlpm.StartDate, $X$2, _xlpm.Dates, INDIRECT("'"&_xlpm.SheetName&"'!A:A"), _xlpm.Prices, INDIRECT("'"&_xlpm.SheetName&"'!E:E"), _xlpm.StartPrice, _xlfn.XLOOKUP(_xlpm.StartDate, _xlpm.Dates, _xlpm.Prices, , 0, 1), _xlpm.CurrentPrice, _xlfn.XLOOKUP(_xlpm.CurrentDate, _xlpm.Dates, _xlpm.Prices, _xlpm.StartPrice, -1, 1), (_xlpm.CurrentPrice / _xlpm.StartPrice)-1 ))} -> #REF! | AD9: {=IF($X9="", "", _xlfn.LET( _xlpm.SheetName, AD$1, _xlpm.CurrentDate, $X9, _xlpm.StartDate, $X$2, _xlpm.Dates, INDIRECT("'"&_xlpm.SheetName&"'!A:A"), _xlpm.Prices, INDIRECT("'"&_xlpm.SheetName&"'!E:E"), _xlpm.StartPrice, _xlfn.XLOOKUP(_xlpm.StartDate, _xlpm.Dates, _xlpm.Prices, , 0, 1), _xlpm.CurrentPrice, _xlfn.XLOOKUP(_xlpm.CurrentDate, _xlpm.Dates, _xlpm.Prices, _xlpm.StartPrice, -1, 1), (_xlpm.CurrentPrice / _xlpm.StartPrice)-1 ))} -> #REF!
X10: =IF(X9="", "", IF(X9 >= TODAY(), "", X9+1)) -> 46088 | Y10: {=IF($X10="", "", _xlfn.LET( _xlpm.SheetName, Y$1, _xlpm.CurrentDate, $X10, _xlpm.StartDate, $X$2, _xlpm.Dates, INDIRECT("'"&_xlpm.SheetName&"'!A:A"), _xlpm.Prices, INDIRECT("'"&_xlpm.SheetName&"'!E:E"), _xlpm.StartPrice, _xlfn.XLOOKUP(_xlpm.StartDate, _xlpm.Dates, _xlpm.Prices, , 0, 1), _xlpm.CurrentPrice, _xlfn.XLOOKUP(_xlpm.CurrentDate, _xlpm.Dates, _xlpm.Prices, _xlpm.StartPrice, -1, 1), (_xlpm.CurrentPrice / _xlpm.StartPrice)-1 ))} -> #REF! | Z10: {=IF($X10="", "", _xlfn.LET( _xlpm.SheetName, Z$1, _xlpm.CurrentDate, $X10, _xlpm.StartDate, $X$2, _xlpm.Dates, INDIRECT("'"&_xlpm.SheetName&"'!A:A"), _xlpm.Prices, INDIRECT("'"&_xlpm.SheetName&"'!E:E"), _xlpm.StartPrice, _xlfn.XLOOKUP(_xlpm.StartDate, _xlpm.Dates, _xlpm.Prices, , 0, 1), _xlpm.CurrentPrice, _xlfn.XLOOKUP(_xlpm.CurrentDate, _xlpm.Dates, _xlpm.Prices, _xlpm.StartPrice, -1, 1), (_xlpm.CurrentPrice / _xlpm.StartPrice)-1 ))} -> #REF! | AA10: {=IF($X10="", "", _xlfn.LET( _xlpm.SheetName, AA$1, _xlpm.CurrentDate, $X10, _xlpm.StartDate, $X$2, _xlpm.Dates, INDIRECT("'"&_xlpm.SheetName&"'!A:A"), _xlpm.Prices, INDIRECT("'"&_xlpm.SheetName&"'!E:E"), _xlpm.StartPrice, _xlfn.XLOOKUP(_xlpm.StartDate, _xlpm.Dates, _xlpm.Prices, , 0, 1), _xlpm.CurrentPrice, _xlfn.XLOOKUP(_xlpm.CurrentDate, _xlpm.Dates, _xlpm.Prices, _xlpm.StartPrice, -1, 1), (_xlpm.CurrentPrice / _xlpm.StartPrice)-1 ))} -> #REF! | AB10: {=IF($X10="", "", _xlfn.LET( _xlpm.SheetName, AB$1, _xlpm.CurrentDate, $X10, _xlpm.StartDate, $X$2, _xlpm.Dates, INDIRECT("'"&_xlpm.SheetName&"'!A:A"), _xlpm.Prices, INDIRECT("'"&_xlpm.SheetName&"'!E:E"), _xlpm.StartPrice, _xlfn.XLOOKUP(_xlpm.StartDate, _xlpm.Dates, _xlpm.Prices, , 0, 1), _xlpm.CurrentPrice, _xlfn.XLOOKUP(_xlpm.CurrentDate, _xlpm.Dates, _xlpm.Prices, _xlpm.StartPrice, -1, 1), (_xlpm.CurrentPrice / _xlpm.StartPrice)-1 ))} -> #REF! | AC10: {=IF($X10="", "", _xlfn.LET( _xlpm.SheetName, AC$1, _xlpm.CurrentDate, $X10, _xlpm.StartDate, $X$2, _xlpm.Dates, INDIRECT("'"&_xlpm.SheetName&"'!A:A"), _xlpm.Prices, INDIRECT("'"&_xlpm.SheetName&"'!E:E"), _xlpm.StartPrice, _xlfn.XLOOKUP(_xlpm.StartDate, _xlpm.Dates, _xlpm.Prices, , 0, 1), _xlpm.CurrentPrice, _xlfn.XLOOKUP(_xlpm.CurrentDate, _xlpm.Dates, _xlpm.Prices, _xlpm.StartPrice, -1, 1), (_xlpm.CurrentPrice / _xlpm.StartPrice)-1 ))} -> #REF! | AD10: {=IF($X10="", "", _xlfn.LET( _xlpm.SheetName, AD$1, _xlpm.CurrentDate, $X10, _xlpm.StartDate, $X$2, _xlpm.Dates, INDIRECT("'"&_xlpm.SheetName&"'!A:A"), _xlpm.Prices, INDIRECT("'"&_xlpm.SheetName&"'!E:E"), _xlpm.StartPrice, _xlfn.XLOOKUP(_xlpm.StartDate, _xlpm.Dates, _xlpm.Prices, , 0, 1), _xlpm.CurrentPrice, _xlfn.XLOOKUP(_xlpm.CurrentDate, _xlpm.Dates, _xlpm.Prices, _xlpm.StartPrice, -1, 1), (_xlpm.CurrentPrice / _xlpm.StartPrice)-1 ))} -> #REF!
X11: =IF(X10="", "", IF(X10 >= TODAY(), "", X10+1)) -> 46089 | Y11: {=IF($X11="", "", _xlfn.LET( _xlpm.SheetName, Y$1, _xlpm.CurrentDate, $X11, _xlpm.StartDate, $X$2, _xlpm.Dates, INDIRECT("'"&_xlpm.SheetName&"'!A:A"), _xlpm.Prices, INDIRECT("'"&_xlpm.SheetName&"'!E:E"), _xlpm.StartPrice, _xlfn.XLOOKUP(_xlpm.StartDate, _xlpm.Dates, _xlpm.Prices, , 0, 1), _xlpm.CurrentPrice, _xlfn.XLOOKUP(_xlpm.CurrentDate, _xlpm.Dates, _xlpm.Prices, _xlpm.StartPrice, -1, 1), (_xlpm.CurrentPrice / _xlpm.StartPrice)-1 ))} -> #REF! | Z11: {=IF($X11="", "", _xlfn.LET( _xlpm.SheetName, Z$1, _xlpm.CurrentDate, $X11, _xlpm.StartDate, $X$2, _xlpm.Dates, INDIRECT("'"&_xlpm.SheetName&"'!A:A"), _xlpm.Prices, INDIRECT("'"&_xlpm.SheetName&"'!E:E"), _xlpm.StartPrice, _xlfn.XLOOKUP(_xlpm.StartDate, _xlpm.Dates, _xlpm.Prices, , 0, 1), _xlpm.CurrentPrice, _xlfn.XLOOKUP(_xlpm.CurrentDate, _xlpm.Dates, _xlpm.Prices, _xlpm.StartPrice, -1, 1), (_xlpm.CurrentPrice / _xlpm.StartPrice)-1 ))} -> #REF! | AA11: {=IF($X11="", "", _xlfn.LET( _xlpm.SheetName, AA$1, _xlpm.CurrentDate, $X11, _xlpm.StartDate, $X$2, _xlpm.Dates, INDIRECT("'"&_xlpm.SheetName&"'!A:A"), _xlpm.Prices, INDIRECT("'"&_xlpm.SheetName&"'!E:E"), _xlpm.StartPrice, _xlfn.XLOOKUP(_xlpm.StartDate, _xlpm.Dates, _xlpm.Prices, , 0, 1), _xlpm.CurrentPrice, _xlfn.XLOOKUP(_xlpm.CurrentDate, _xlpm.Dates, _xlpm.Prices, _xlpm.StartPrice, -1, 1), (_xlpm.CurrentPrice / _xlpm.StartPrice)-1 ))} -> #REF! | AB11: {=IF($X11="", "", _xlfn.LET( _xlpm.SheetName, AB$1, _xlpm.CurrentDate, $X11, _xlpm.StartDate, $X$2, _xlpm.Dates, INDIRECT("'"&_xlpm.SheetName&"'!A:A"), _xlpm.Prices, INDIRECT("'"&_xlpm.SheetName&"'!E:E"), _xlpm.StartPrice, _xlfn.XLOOKUP(_xlpm.StartDate, _xlpm.Dates, _xlpm.Prices, , 0, 1), _xlpm.CurrentPrice, _xlfn.XLOOKUP(_xlpm.CurrentDate, _xlpm.Dates, _xlpm.Prices, _xlpm.StartPrice, -1, 1), (_xlpm.CurrentPrice / _xlpm.StartPrice)-1 ))} -> #REF! | AC11: {=IF($X11="", "", _xlfn.LET( _xlpm.SheetName, AC$1, _xlpm.CurrentDate, $X11, _xlpm.StartDate, $X$2, _xlpm.Dates, INDIRECT("'"&_xlpm.SheetName&"'!A:A"), _xlpm.Prices, INDIRECT("'"&_xlpm.SheetName&"'!E:E"), _xlpm.StartPrice, _xlfn.XLOOKUP(_xlpm.StartDate, _xlpm.Dates, _xlpm.Prices, , 0, 1), _xlpm.CurrentPrice, _xlfn.XLOOKUP(_xlpm.CurrentDate, _xlpm.Dates, _xlpm.Prices, _xlpm.StartPrice, -1, 1), (_xlpm.CurrentPrice / _xlpm.StartPrice)-1 ))} -> #REF! | AD11: {=IF($X11="", "", _xlfn.LET( _xlpm.SheetName, AD$1, _xlpm.CurrentDate, $X11, _xlpm.StartDate, $X$2, _xlpm.Dates, INDIRECT("'"&_xlpm.SheetName&"'!A:A"), _xlpm.Prices, INDIRECT("'"&_xlpm.SheetName&"'!E:E"), _xlpm.StartPrice, _xlfn.XLOOKUP(_xlpm.StartDate, _xlpm.Dates, _xlpm.Prices, , 0, 1), _xlpm.CurrentPrice, _xlfn.XLOOKUP(_xlpm.CurrentDate, _xlpm.Dates, _xlpm.Prices, _xlpm.StartPrice, -1, 1), (_xlpm.CurrentPrice / _xlpm.StartPrice)-1 ))} -> #REF!
X12: =IF(X11="", "", IF(X11 >= TODAY(), "", X11+1)) -> 46090 | Y12: {=IF($X12="", "", _xlfn.LET( _xlpm.SheetName, Y$1, _xlpm.CurrentDate, $X12, _xlpm.StartDate, $X$2, _xlpm.Dates, INDIRECT("'"&_xlpm.SheetName&"'!A:A"), _xlpm.Prices, INDIRECT("'"&_xlpm.SheetName&"'!E:E"), _xlpm.StartPrice, _xlfn.XLOOKUP(_xlpm.StartDate, _xlpm.Dates, _xlpm.Prices, , 0, 1), _xlpm.CurrentPrice, _xlfn.XLOOKUP(_xlpm.CurrentDate, _xlpm.Dates, _xlpm.Prices, _xlpm.StartPrice, -1, 1), (_xlpm.CurrentPrice / _xlpm.StartPrice)-1 ))} -> #REF! | Z12: {=IF($X12="", "", _xlfn.LET( _xlpm.SheetName, Z$1, _xlpm.CurrentDate, $X12, _xlpm.StartDate, $X$2, _xlpm.Dates, INDIRECT("'"&_xlpm.SheetName&"'!A:A"), _xlpm.Prices, INDIRECT("'"&_xlpm.SheetName&"'!E:E"), _xlpm.StartPrice, _xlfn.XLOOKUP(_xlpm.StartDate, _xlpm.Dates, _xlpm.Prices, , 0, 1), _xlpm.CurrentPrice, _xlfn.XLOOKUP(_xlpm.CurrentDate, _xlpm.Dates, _xlpm.Prices, _xlpm.StartPrice, -1, 1), (_xlpm.CurrentPrice / _xlpm.StartPrice)-1 ))} -> #REF! | AA12: {=IF($X12="", "", _xlfn.LET( _xlpm.SheetName, AA$1, _xlpm.CurrentDate, $X12, _xlpm.StartDate, $X$2, _xlpm.Dates, INDIRECT("'"&_xlpm.SheetName&"'!A:A"), _xlpm.Prices, INDIRECT("'"&_xlpm.SheetName&"'!E:E"), _xlpm.StartPrice, _xlfn.XLOOKUP(_xlpm.StartDate, _xlpm.Dates, _xlpm.Prices, , 0, 1), _xlpm.CurrentPrice, _xlfn.XLOOKUP(_xlpm.CurrentDate, _xlpm.Dates, _xlpm.Prices, _xlpm.StartPrice, -1, 1), (_xlpm.CurrentPrice / _xlpm.StartPrice)-1 ))} -> #REF! | AB12: {=IF($X12="", "", _xlfn.LET( _xlpm.SheetName, AB$1, _xlpm.CurrentDate, $X12, _xlpm.StartDate, $X$2, _xlpm.Dates, INDIRECT("'"&_xlpm.SheetName&"'!A:A"), _xlpm.Prices, INDIRECT("'"&_xlpm.SheetName&"'!E:E"), _xlpm.StartPrice, _xlfn.XLOOKUP(_xlpm.StartDate, _xlpm.Dates, _xlpm.Prices, , 0, 1), _xlpm.CurrentPrice, _xlfn.XLOOKUP(_xlpm.CurrentDate, _xlpm.Dates, _xlpm.Prices, _xlpm.StartPrice, -1, 1), (_xlpm.CurrentPrice / _xlpm.StartPrice)-1 ))} -> #REF! | AC12: {=IF($X12="", "", _xlfn.LET( _xlpm.SheetName, AC$1, _xlpm.CurrentDate, $X12, _xlpm.StartDate, $X$2, _xlpm.Dates, INDIRECT("'"&_xlpm.SheetName&"'!A:A"), _xlpm.Prices, INDIRECT("'"&_xlpm.SheetName&"'!E:E"), _xlpm.StartPrice, _xlfn.XLOOKUP(_xlpm.StartDate, _xlpm.Dates, _xlpm.Prices, , 0, 1), _xlpm.CurrentPrice, _xlfn.XLOOKUP(_xlpm.CurrentDate, _xlpm.Dates, _xlpm.Prices, _xlpm.StartPrice, -1, 1), (_xlpm.CurrentPrice / _xlpm.StartPrice)-1 ))} -> #REF! | AD12: {=IF($X12="", "", _xlfn.LET( _xlpm.SheetName, AD$1, _xlpm.CurrentDate, $X12, _xlpm.StartDate, $X$2, _xlpm.Dates, INDIRECT("'"&_xlpm.SheetName&"'!A:A"), _xlpm.Prices, INDIRECT("'"&_xlpm.SheetName&"'!E:E"), _xlpm.StartPrice, _xlfn.XLOOKUP(_xlpm.StartDate, _xlpm.Dates, _xlpm.Prices, , 0, 1), _xlpm.CurrentPrice, _xlfn.XLOOKUP(_xlpm.CurrentDate, _xlpm.Dates, _xlpm.Prices, _xlpm.StartPrice, -1, 1), (_xlpm.CurrentPrice / _xlpm.StartPrice)-1 ))} -> #REF!
X13: =IF(X12="", "", IF(X12 >= TODAY(), "", X12+1)) -> 46091 | Y13: {=IF($X13="", "", _xlfn.LET( _xlpm.SheetName, Y$1, _xlpm.CurrentDate, $X13, _xlpm.StartDate, $X$2, _xlpm.Dates, INDIRECT("'"&_xlpm.SheetName&"'!A:A"), _xlpm.Prices, INDIRECT("'"&_xlpm.SheetName&"'!E:E"), _xlpm.StartPrice, _xlfn.XLOOKUP(_xlpm.StartDate, _xlpm.Dates, _xlpm.Prices, , 0, 1), _xlpm.CurrentPrice, _xlfn.XLOOKUP(_xlpm.CurrentDate, _xlpm.Dates, _xlpm.Prices, _xlpm.StartPrice, -1, 1), (_xlpm.CurrentPrice / _xlpm.StartPrice)-1 ))} -> #REF! | Z13: {=IF($X13="", "", _xlfn.LET( _xlpm.SheetName, Z$1, _xlpm.CurrentDate, $X13, _xlpm.StartDate, $X$2, _xlpm.Dates, INDIRECT("'"&_xlpm.SheetName&"'!A:A"), _xlpm.Prices, INDIRECT("'"&_xlpm.SheetName&"'!E:E"), _xlpm.StartPrice, _xlfn.XLOOKUP(_xlpm.StartDate, _xlpm.Dates, _xlpm.Prices, , 0, 1), _xlpm.CurrentPrice, _xlfn.XLOOKUP(_xlpm.CurrentDate, _xlpm.Dates, _xlpm.Prices, _xlpm.StartPrice, -1, 1), (_xlpm.CurrentPrice / _xlpm.StartPrice)-1 ))} -> #REF! | AA13: {=IF($X13="", "", _xlfn.LET( _xlpm.SheetName, AA$1, _xlpm.CurrentDate, $X13, _xlpm.StartDate, $X$2, _xlpm.Dates, INDIRECT("'"&_xlpm.SheetName&"'!A:A"), _xlpm.Prices, INDIRECT("'"&_xlpm.SheetName&"'!E:E"), _xlpm.StartPrice, _xlfn.XLOOKUP(_xlpm.StartDate, _xlpm.Dates, _xlpm.Prices, , 0, 1), _xlpm.CurrentPrice, _xlfn.XLOOKUP(_xlpm.CurrentDate, _xlpm.Dates, _xlpm.Prices, _xlpm.StartPrice, -1, 1), (_xlpm.CurrentPrice / _xlpm.StartPrice)-1 ))} -> #REF! | AB13: {=IF($X13="", "", _xlfn.LET( _xlpm.SheetName, AB$1, _xlpm.CurrentDate, $X13, _xlpm.StartDate, $X$2, _xlpm.Dates, INDIRECT("'"&_xlpm.SheetName&"'!A:A"), _xlpm.Prices, INDIRECT("'"&_xlpm.SheetName&"'!E:E"), _xlpm.StartPrice, _xlfn.XLOOKUP(_xlpm.StartDate, _xlpm.Dates, _xlpm.Prices, , 0, 1), _xlpm.CurrentPrice, _xlfn.XLOOKUP(_xlpm.CurrentDate, _xlpm.Dates, _xlpm.Prices, _xlpm.StartPrice, -1, 1), (_xlpm.CurrentPrice / _xlpm.StartPrice)-1 ))} -> #REF! | AC13: {=IF($X13="", "", _xlfn.LET( _xlpm.SheetName, AC$1, _xlpm.CurrentDate, $X13, _xlpm.StartDate, $X$2, _xlpm.Dates, INDIRECT("'"&_xlpm.SheetName&"'!A:A"), _xlpm.Prices, INDIRECT("'"&_xlpm.SheetName&"'!E:E"), _xlpm.StartPrice, _xlfn.XLOOKUP(_xlpm.StartDate, _xlpm.Dates, _xlpm.Prices, , 0, 1), _xlpm.CurrentPrice, _xlfn.XLOOKUP(_xlpm.CurrentDate, _xlpm.Dates, _xlpm.Prices, _xlpm.StartPrice, -1, 1), (_xlpm.CurrentPrice / _xlpm.StartPrice)-1 ))} -> #REF! | AD13: {=IF($X13="", "", _xlfn.LET( _xlpm.SheetName, AD$1, _xlpm.CurrentDate, $X13, _xlpm.StartDate, $X$2, _xlpm.Dates, INDIRECT("'"&_xlpm.SheetName&"'!A:A"), _xlpm.Prices, INDIRECT("'"&_xlpm.SheetName&"'!E:E"), _xlpm.StartPrice, _xlfn.XLOOKUP(_xlpm.StartDate, _xlpm.Dates, _xlpm.Prices, , 0, 1), _xlpm.CurrentPrice, _xlfn.XLOOKUP(_xlpm.CurrentDate, _xlpm.Dates, _xlpm.Prices, _xlpm.StartPrice, -1, 1), (_xlpm.CurrentPrice / _xlpm.StartPrice)-1 ))} -> #REF!
X14: =IF(X13="", "", IF(X13 >= TODAY(), "", X13+1)) -> 46092 | Y14: {=IF($X14="", "", _xlfn.LET( _xlpm.SheetName, Y$1, _xlpm.CurrentDate, $X14, _xlpm.StartDate, $X$2, _xlpm.Dates, INDIRECT("'"&_xlpm.SheetName&"'!A:A"), _xlpm.Prices, INDIRECT("'"&_xlpm.SheetName&"'!E:E"), _xlpm.StartPrice, _xlfn.XLOOKUP(_xlpm.StartDate, _xlpm.Dates, _xlpm.Prices, , 0, 1), _xlpm.CurrentPrice, _xlfn.XLOOKUP(_xlpm.CurrentDate, _xlpm.Dates, _xlpm.Prices, _xlpm.StartPrice, -1, 1), (_xlpm.CurrentPrice / _xlpm.StartPrice)-1 ))} -> #REF! | Z14: {=IF($X14="", "", _xlfn.LET( _xlpm.SheetName, Z$1, _xlpm.CurrentDate, $X14, _xlpm.StartDate, $X$2, _xlpm.Dates, INDIRECT("'"&_xlpm.SheetName&"'!A:A"), _xlpm.Prices, INDIRECT("'"&_xlpm.SheetName&"'!E:E"), _xlpm.StartPrice, _xlfn.XLOOKUP(_xlpm.StartDate, _xlpm.Dates, _xlpm.Prices, , 0, 1), _xlpm.CurrentPrice, _xlfn.XLOOKUP(_xlpm.CurrentDate, _xlpm.Dates, _xlpm.Prices, _xlpm.StartPrice, -1, 1), (_xlpm.CurrentPrice / _xlpm.StartPrice)-1 ))} -> #REF! | AA14: {=IF($X14="", "", _xlfn.LET( _xlpm.SheetName, AA$1, _xlpm.CurrentDate, $X14, _xlpm.StartDate, $X$2, _xlpm.Dates, INDIRECT("'"&_xlpm.SheetName&"'!A:A"), _xlpm.Prices, INDIRECT("'"&_xlpm.SheetName&"'!E:E"), _xlpm.StartPrice, _xlfn.XLOOKUP(_xlpm.StartDate, _xlpm.Dates, _xlpm.Prices, , 0, 1), _xlpm.CurrentPrice, _xlfn.XLOOKUP(_xlpm.CurrentDate, _xlpm.Dates, _xlpm.Prices, _xlpm.StartPrice, -1, 1), (_xlpm.CurrentPrice / _xlpm.StartPrice)-1 ))} -> #REF! | AB14: {=IF($X14="", "", _xlfn.LET( _xlpm.SheetName, AB$1, _xlpm.CurrentDate, $X14, _xlpm.StartDate, $X$2, _xlpm.Dates, INDIRECT("'"&_xlpm.SheetName&"'!A:A"), _xlpm.Prices, INDIRECT("'"&_xlpm.SheetName&"'!E:E"), _xlpm.StartPrice, _xlfn.XLOOKUP(_xlpm.StartDate, _xlpm.Dates, _xlpm.Prices, , 0, 1), _xlpm.CurrentPrice, _xlfn.XLOOKUP(_xlpm.CurrentDate, _xlpm.Dates, _xlpm.Prices, _xlpm.StartPrice, -1, 1), (_xlpm.CurrentPrice / _xlpm.StartPrice)-1 ))} -> #REF! | AC14: {=IF($X14="", "", _xlfn.LET( _xlpm.SheetName, AC$1, _xlpm.CurrentDate, $X14, _xlpm.StartDate, $X$2, _xlpm.Dates, INDIRECT("'"&_xlpm.SheetName&"'!A:A"), _xlpm.Prices, INDIRECT("'"&_xlpm.SheetName&"'!E:E"), _xlpm.StartPrice, _xlfn.XLOOKUP(_xlpm.StartDate, _xlpm.Dates, _xlpm.Prices, , 0, 1), _xlpm.CurrentPrice, _xlfn.XLOOKUP(_xlpm.CurrentDate, _xlpm.Dates, _xlpm.Prices, _xlpm.StartPrice, -1, 1), (_xlpm.CurrentPrice / _xlpm.StartPrice)-1 ))} -> #REF! | AD14: {=IF($X14="", "", _xlfn.LET( _xlpm.SheetName, AD$1, _xlpm.CurrentDate, $X14, _xlpm.StartDate, $X$2, _xlpm.Dates, INDIRECT("'"&_xlpm.SheetName&"'!A:A"), _xlpm.Prices, INDIRECT("'"&_xlpm.SheetName&"'!E:E"), _xlpm.StartPrice, _xlfn.XLOOKUP(_xlpm.StartDate, _xlpm.Dates, _xlpm.Prices, , 0, 1), _xlpm.CurrentPrice, _xlfn.XLOOKUP(_xlpm.CurrentDate, _xlpm.Dates, _xlpm.Prices, _xlpm.StartPrice, -1, 1), (_xlpm.CurrentPrice / _xlpm.StartPrice)-1 ))} -> #REF!
X15: =IF(X14="", "", IF(X14 >= TODAY(), "", X14+1)) -> 46093 | Y15: {=IF($X15="", "", _xlfn.LET( _xlpm.SheetName, Y$1, _xlpm.CurrentDate, $X15, _xlpm.StartDate, $X$2, _xlpm.Dates, INDIRECT("'"&_xlpm.SheetName&"'!A:A"), _xlpm.Prices, INDIRECT("'"&_xlpm.SheetName&"'!E:E"), _xlpm.StartPrice, _xlfn.XLOOKUP(_xlpm.StartDate, _xlpm.Dates, _xlpm.Prices, , 0, 1), _xlpm.CurrentPrice, _xlfn.XLOOKUP(_xlpm.CurrentDate, _xlpm.Dates, _xlpm.Prices, _xlpm.StartPrice, -1, 1), (_xlpm.CurrentPrice / _xlpm.StartPrice)-1 ))} -> #REF! | Z15: {=IF($X15="", "", _xlfn.LET( _xlpm.SheetName, Z$1, _xlpm.CurrentDate, $X15, _xlpm.StartDate, $X$2, _xlpm.Dates, INDIRECT("'"&_xlpm.SheetName&"'!A:A"), _xlpm.Prices, INDIRECT("'"&_xlpm.SheetName&"'!E:E"), _xlpm.StartPrice, _xlfn.XLOOKUP(_xlpm.StartDate, _xlpm.Dates, _xlpm.Prices, , 0, 1), _xlpm.CurrentPrice, _xlfn.XLOOKUP(_xlpm.CurrentDate, _xlpm.Dates, _xlpm.Prices, _xlpm.StartPrice, -1, 1), (_xlpm.CurrentPrice / _xlpm.StartPrice)-1 ))} -> #REF! | AA15: {=IF($X15="", "", _xlfn.LET( _xlpm.SheetName, AA$1, _xlpm.CurrentDate, $X15, _xlpm.StartDate, $X$2, _xlpm.Dates, INDIRECT("'"&_xlpm.SheetName&"'!A:A"), _xlpm.Prices, INDIRECT("'"&_xlpm.SheetName&"'!E:E"), _xlpm.StartPrice, _xlfn.XLOOKUP(_xlpm.StartDate, _xlpm.Dates, _xlpm.Prices, , 0, 1), _xlpm.CurrentPrice, _xlfn.XLOOKUP(_xlpm.CurrentDate, _xlpm.Dates, _xlpm.Prices, _xlpm.StartPrice, -1, 1), (_xlpm.CurrentPrice / _xlpm.StartPrice)-1 ))} -> #REF! | AB15: {=IF($X15="", "", _xlfn.LET( _xlpm.SheetName, AB$1, _xlpm.CurrentDate, $X15, _xlpm.StartDate, $X$2, _xlpm.Dates, INDIRECT("'"&_xlpm.SheetName&"'!A:A"), _xlpm.Prices, INDIRECT("'"&_xlpm.SheetName&"'!E:E"), _xlpm.StartPrice, _xlfn.XLOOKUP(_xlpm.StartDate, _xlpm.Dates, _xlpm.Prices, , 0, 1), _xlpm.CurrentPrice, _xlfn.XLOOKUP(_xlpm.CurrentDate, _xlpm.Dates, _xlpm.Prices, _xlpm.StartPrice, -1, 1), (_xlpm.CurrentPrice / _xlpm.StartPrice)-1 ))} -> #REF! | AC15: {=IF($X15="", "", _xlfn.LET( _xlpm.SheetName, AC$1, _xlpm.CurrentDate, $X15, _xlpm.StartDate, $X$2, _xlpm.Dates, INDIRECT("'"&_xlpm.SheetName&"'!A:A"), _xlpm.Prices, INDIRECT("'"&_xlpm.SheetName&"'!E:E"), _xlpm.StartPrice, _xlfn.XLOOKUP(_xlpm.StartDate, _xlpm.Dates, _xlpm.Prices, , 0, 1), _xlpm.CurrentPrice, _xlfn.XLOOKUP(_xlpm.CurrentDate, _xlpm.Dates, _xlpm.Prices, _xlpm.StartPrice, -1, 1), (_xlpm.CurrentPrice / _xlpm.StartPrice)-1 ))} -> #REF! | AD15: {=IF($X15="", "", _xlfn.LET( _xlpm.SheetName, AD$1, _xlpm.CurrentDate, $X15, _xlpm.StartDate, $X$2, _xlpm.Dates, INDIRECT("'"&_xlpm.SheetName&"'!A:A"), _xlpm.Prices, INDIRECT("'"&_xlpm.SheetName&"'!E:E"), _xlpm.StartPrice, _xlfn.XLOOKUP(_xlpm.StartDate, _xlpm.Dates, _xlpm.Prices, , 0, 1), _xlpm.CurrentPrice, _xlfn.XLOOKUP(_xlpm.CurrentDate, _xlpm.Dates, _xlpm.Prices, _xlpm.StartPrice, -1, 1), (_xlpm.CurrentPrice / _xlpm.StartPrice)-1 ))} -> #REF!
X16: =IF(X15="", "", IF(X15 >= TODAY(), "", X15+1)) -> 46094 | Y16: {=IF($X16="", "", _xlfn.LET( _xlpm.SheetName, Y$1, _xlpm.CurrentDate, $X16, _xlpm.StartDate, $X$2, _xlpm.Dates, INDIRECT("'"&_xlpm.SheetName&"'!A:A"), _xlpm.Prices, INDIRECT("'"&_xlpm.SheetName&"'!E:E"), _xlpm.StartPrice, _xlfn.XLOOKUP(_xlpm.StartDate, _xlpm.Dates, _xlpm.Prices, , 0, 1), _xlpm.CurrentPrice, _xlfn.XLOOKUP(_xlpm.CurrentDate, _xlpm.Dates, _xlpm.Prices, _xlpm.StartPrice, -1, 1), (_xlpm.CurrentPrice / _xlpm.StartPrice)-1 ))} -> #REF! | Z16: {=IF($X16="", "", _xlfn.LET( _xlpm.SheetName, Z$1, _xlpm.CurrentDate, $X16, _xlpm.StartDate, $X$2, _xlpm.Dates, INDIRECT("'"&_xlpm.SheetName&"'!A:A"), _xlpm.Prices, INDIRECT("'"&_xlpm.SheetName&"'!E:E"), _xlpm.StartPrice, _xlfn.XLOOKUP(_xlpm.StartDate, _xlpm.Dates, _xlpm.Prices, , 0, 1), _xlpm.CurrentPrice, _xlfn.XLOOKUP(_xlpm.CurrentDate, _xlpm.Dates, _xlpm.Prices, _xlpm.StartPrice, -1, 1), (_xlpm.CurrentPrice / _xlpm.StartPrice)-1 ))} -> #REF! | AA16: {=IF($X16="", "", _xlfn.LET( _xlpm.SheetName, AA$1, _xlpm.CurrentDate, $X16, _xlpm.StartDate, $X$2, _xlpm.Dates, INDIRECT("'"&_xlpm.SheetName&"'!A:A"), _xlpm.Prices, INDIRECT("'"&_xlpm.SheetName&"'!E:E"), _xlpm.StartPrice, _xlfn.XLOOKUP(_xlpm.StartDate, _xlpm.Dates, _xlpm.Prices, , 0, 1), _xlpm.CurrentPrice, _xlfn.XLOOKUP(_xlpm.CurrentDate, _xlpm.Dates, _xlpm.Prices, _xlpm.StartPrice, -1, 1), (_xlpm.CurrentPrice / _xlpm.StartPrice)-1 ))} -> #REF! | AB16: {=IF($X16="", "", _xlfn.LET( _xlpm.SheetName, AB$1, _xlpm.CurrentDate, $X16, _xlpm.StartDate, $X$2, _xlpm.Dates, INDIRECT("'"&_xlpm.SheetName&"'!A:A"), _xlpm.Prices, INDIRECT("'"&_xlpm.SheetName&"'!E:E"), _xlpm.StartPrice, _xlfn.XLOOKUP(_xlpm.StartDate, _xlpm.Dates, _xlpm.Prices, , 0, 1), _xlpm.CurrentPrice, _xlfn.XLOOKUP(_xlpm.CurrentDate, _xlpm.Dates, _xlpm.Prices, _xlpm.StartPrice, -1, 1), (_xlpm.CurrentPrice / _xlpm.StartPrice)-1 ))} -> #REF! | AC16: {=IF($X16="", "", _xlfn.LET( _xlpm.SheetName, AC$1, _xlpm.CurrentDate, $X16, _xlpm.StartDate, $X$2, _xlpm.Dates, INDIRECT("'"&_xlpm.SheetName&"'!A:A"), _xlpm.Prices, INDIRECT("'"&_xlpm.SheetName&"'!E:E"), _xlpm.StartPrice, _xlfn.XLOOKUP(_xlpm.StartDate, _xlpm.Dates, _xlpm.Prices, , 0, 1), _xlpm.CurrentPrice, _xlfn.XLOOKUP(_xlpm.CurrentDate, _xlpm.Dates, _xlpm.Prices, _xlpm.StartPrice, -1, 1), (_xlpm.CurrentPrice / _xlpm.StartPrice)-1 ))} -> #REF! | AD16: {=IF($X16="", "", _xlfn.LET( _xlpm.SheetName, AD$1, _xlpm.CurrentDate, $X16, _xlpm.StartDate, $X$2, _xlpm.Dates, INDIRECT("'"&_xlpm.SheetName&"'!A:A"), _xlpm.Prices, INDIRECT("'"&_xlpm.SheetName&"'!E:E"), _xlpm.StartPrice, _xlfn.XLOOKUP(_xlpm.StartDate, _xlpm.Dates, _xlpm.Prices, , 0, 1), _xlpm.CurrentPrice, _xlfn.XLOOKUP(_xlpm.CurrentDate, _xlpm.Dates, _xlpm.Prices, _xlpm.StartPrice, -1, 1), (_xlpm.CurrentPrice / _xlpm.StartPrice)-1 ))} -> #REF!
X17: =IF(X16="", "", IF(X16 >= TODAY(), "", X16+1)) -> 46095 | Y17: {=IF($X17="", "", _xlfn.LET( _xlpm.SheetName, Y$1, _xlpm.CurrentDate, $X17, _xlpm.StartDate, $X$2, _xlpm.Dates, INDIRECT("'"&_xlpm.SheetName&"'!A:A"), _xlpm.Prices, INDIRECT("'"&_xlpm.SheetName&"'!E:E"), _xlpm.StartPrice, _xlfn.XLOOKUP(_xlpm.StartDate, _xlpm.Dates, _xlpm.Prices, , 0, 1), _xlpm.CurrentPrice, _xlfn.XLOOKUP(_xlpm.CurrentDate, _xlpm.Dates, _xlpm.Prices, _xlpm.StartPrice, -1, 1), (_xlpm.CurrentPrice / _xlpm.StartPrice)-1 ))} -> #REF! | Z17: {=IF($X17="", "", _xlfn.LET( _xlpm.SheetName, Z$1, _xlpm.CurrentDate, $X17, _xlpm.StartDate, $X$2, _xlpm.Dates, INDIRECT("'"&_xlpm.SheetName&"'!A:A"), _xlpm.Prices, INDIRECT("'"&_xlpm.SheetName&"'!E:E"), _xlpm.StartPrice, _xlfn.XLOOKUP(_xlpm.StartDate, _xlpm.Dates, _xlpm.Prices, , 0, 1), _xlpm.CurrentPrice, _xlfn.XLOOKUP(_xlpm.CurrentDate, _xlpm.Dates, _xlpm.Prices, _xlpm.StartPrice, -1, 1), (_xlpm.CurrentPrice / _xlpm.StartPrice)-1 ))} -> #REF! | AA17: {=IF($X17="", "", _xlfn.LET( _xlpm.SheetName, AA$1, _xlpm.CurrentDate, $X17, _xlpm.StartDate, $X$2, _xlpm.Dates, INDIRECT("'"&_xlpm.SheetName&"'!A:A"), _xlpm.Prices, INDIRECT("'"&_xlpm.SheetName&"'!E:E"), _xlpm.StartPrice, _xlfn.XLOOKUP(_xlpm.StartDate, _xlpm.Dates, _xlpm.Prices, , 0, 1), _xlpm.CurrentPrice, _xlfn.XLOOKUP(_xlpm.CurrentDate, _xlpm.Dates, _xlpm.Prices, _xlpm.StartPrice, -1, 1), (_xlpm.CurrentPrice / _xlpm.StartPrice)-1 ))} -> #REF! | AB17: {=IF($X17="", "", _xlfn.LET( _xlpm.SheetName, AB$1, _xlpm.CurrentDate, $X17, _xlpm.StartDate, $X$2, _xlpm.Dates, INDIRECT("'"&_xlpm.SheetName&"'!A:A"), _xlpm.Prices, INDIRECT("'"&_xlpm.SheetName&"'!E:E"), _xlpm.StartPrice, _xlfn.XLOOKUP(_xlpm.StartDate, _xlpm.Dates, _xlpm.Prices, , 0, 1), _xlpm.CurrentPrice, _xlfn.XLOOKUP(_xlpm.CurrentDate, _xlpm.Dates, _xlpm.Prices, _xlpm.StartPrice, -1, 1), (_xlpm.CurrentPrice / _xlpm.StartPrice)-1 ))} -> #REF! | AC17: {=IF($X17="", "", _xlfn.LET( _xlpm.SheetName, AC$1, _xlpm.CurrentDate, $X17, _xlpm.StartDate, $X$2, _xlpm.Dates, INDIRECT("'"&_xlpm.SheetName&"'!A:A"), _xlpm.Prices, INDIRECT("'"&_xlpm.SheetName&"'!E:E"), _xlpm.StartPrice, _xlfn.XLOOKUP(_xlpm.StartDate, _xlpm.Dates, _xlpm.Prices, , 0, 1), _xlpm.CurrentPrice, _xlfn.XLOOKUP(_xlpm.CurrentDate, _xlpm.Dates, _xlpm.Prices, _xlpm.StartPrice, -1, 1), (_xlpm.CurrentPrice / _xlpm.StartPrice)-1 ))} -> #REF! | AD17: {=IF($X17="", "", _xlfn.LET( _xlpm.SheetName, AD$1, _xlpm.CurrentDate, $X17, _xlpm.StartDate, $X$2, _xlpm.Dates, INDIRECT("'"&_xlpm.SheetName&"'!A:A"), _xlpm.Prices, INDIRECT("'"&_xlpm.SheetName&"'!E:E"), _xlpm.StartPrice, _xlfn.XLOOKUP(_xlpm.StartDate, _xlpm.Dates, _xlpm.Prices, , 0, 1), _xlpm.CurrentPrice, _xlfn.XLOOKUP(_xlpm.CurrentDate, _xlpm.Dates, _xlpm.Prices, _xlpm.StartPrice, -1, 1), (_xlpm.CurrentPrice / _xlpm.StartPrice)-1 ))} -> #REF!
X18: =IF(X17="", "", IF(X17 >= TODAY(), "", X17+1)) -> 46096 | Y18: {=IF($X18="", "", _xlfn.LET( _xlpm.SheetName, Y$1, _xlpm.CurrentDate, $X18, _xlpm.StartDate, $X$2, _xlpm.Dates, INDIRECT("'"&_xlpm.SheetName&"'!A:A"), _xlpm.Prices, INDIRECT("'"&_xlpm.SheetName&"'!E:E"), _xlpm.StartPrice, _xlfn.XLOOKUP(_xlpm.StartDate, _xlpm.Dates, _xlpm.Prices, , 0, 1), _xlpm.CurrentPrice, _xlfn.XLOOKUP(_xlpm.CurrentDate, _xlpm.Dates, _xlpm.Prices, _xlpm.StartPrice, -1, 1), (_xlpm.CurrentPrice / _xlpm.StartPrice)-1 ))} -> #REF! | Z18: {=IF($X18="", "", _xlfn.LET( _xlpm.SheetName, Z$1, _xlpm.CurrentDate, $X18, _xlpm.StartDate, $X$2, _xlpm.Dates, INDIRECT("'"&_xlpm.SheetName&"'!A:A"), _xlpm.Prices, INDIRECT("'"&_xlpm.SheetName&"'!E:E"), _xlpm.StartPrice, _xlfn.XLOOKUP(_xlpm.StartDate, _xlpm.Dates, _xlpm.Prices, , 0, 1), _xlpm.CurrentPrice, _xlfn.XLOOKUP(_xlpm.CurrentDate, _xlpm.Dates, _xlpm.Prices, _xlpm.StartPrice, -1, 1), (_xlpm.CurrentPrice / _xlpm.StartPrice)-1 ))} -> #REF! | AA18: {=IF($X18="", "", _xlfn.LET( _xlpm.SheetName, AA$1, _xlpm.CurrentDate, $X18, _xlpm.StartDate, $X$2, _xlpm.Dates, INDIRECT("'"&_xlpm.SheetName&"'!A:A"), _xlpm.Prices, INDIRECT("'"&_xlpm.SheetName&"'!E:E"), _xlpm.StartPrice, _xlfn.XLOOKUP(_xlpm.StartDate, _xlpm.Dates, _xlpm.Prices, , 0, 1), _xlpm.CurrentPrice, _xlfn.XLOOKUP(_xlpm.CurrentDate, _xlpm.Dates, _xlpm.Prices, _xlpm.StartPrice, -1, 1), (_xlpm.CurrentPrice / _xlpm.StartPrice)-1 ))} -> #REF! | AB18: {=IF($X18="", "", _xlfn.LET( _xlpm.SheetName, AB$1, _xlpm.CurrentDate, $X18, _xlpm.StartDate, $X$2, _xlpm.Dates, INDIRECT("'"&_xlpm.SheetName&"'!A:A"), _xlpm.Prices, INDIRECT("'"&_xlpm.SheetName&"'!E:E"), _xlpm.StartPrice, _xlfn.XLOOKUP(_xlpm.StartDate, _xlpm.Dates, _xlpm.Prices, , 0, 1), _xlpm.CurrentPrice, _xlfn.XLOOKUP(_xlpm.CurrentDate, _xlpm.Dates, _xlpm.Prices, _xlpm.StartPrice, -1, 1), (_xlpm.CurrentPrice / _xlpm.StartPrice)-1 ))} -> #REF! | AC18: {=IF($X18="", "", _xlfn.LET( _xlpm.SheetName, AC$1, _xlpm.CurrentDate, $X18, _xlpm.StartDate, $X$2, _xlpm.Dates, INDIRECT("'"&_xlpm.SheetName&"'!A:A"), _xlpm.Prices, INDIRECT("'"&_xlpm.SheetName&"'!E:E"), _xlpm.StartPrice, _xlfn.XLOOKUP(_xlpm.StartDate, _xlpm.Dates, _xlpm.Prices, , 0, 1), _xlpm.CurrentPrice, _xlfn.XLOOKUP(_xlpm.CurrentDate, _xlpm.Dates, _xlpm.Prices, _xlpm.StartPrice, -1, 1), (_xlpm.CurrentPrice / _xlpm.StartPrice)-1 ))} -> #REF! | AD18: {=IF($X18="", "", _xlfn.LET( _xlpm.SheetName, AD$1, _xlpm.CurrentDate, $X18, _xlpm.StartDate, $X$2, _xlpm.Dates, INDIRECT("'"&_xlpm.SheetName&"'!A:A"), _xlpm.Prices, INDIRECT("'"&_xlpm.SheetName&"'!E:E"), _xlpm.StartPrice, _xlfn.XLOOKUP(_xlpm.StartDate, _xlpm.Dates, _xlpm.Prices, , 0, 1), _xlpm.CurrentPrice, _xlfn.XLOOKUP(_xlpm.CurrentDate, _xlpm.Dates, _xlpm.Prices, _xlpm.StartPrice, -1, 1), (_xlpm.CurrentPrice / _xlpm.StartPrice)-1 ))} -> #REF!
X19: =IF(X18="", "", IF(X18 >= TODAY(), "", X18+1)) -> 46097 | Y19: {=IF($X19="", "", _xlfn.LET( _xlpm.SheetName, Y$1, _xlpm.CurrentDate, $X19, _xlpm.StartDate, $X$2, _xlpm.Dates, INDIRECT("'"&_xlpm.SheetName&"'!A:A"), _xlpm.Prices, INDIRECT("'"&_xlpm.SheetName&"'!E:E"), _xlpm.StartPrice, _xlfn.XLOOKUP(_xlpm.StartDate, _xlpm.Dates, _xlpm.Prices, , 0, 1), _xlpm.CurrentPrice, _xlfn.XLOOKUP(_xlpm.CurrentDate, _xlpm.Dates, _xlpm.Prices, _xlpm.StartPrice, -1, 1), (_xlpm.CurrentPrice / _xlpm.StartPrice)-1 ))} -> #REF! | Z19: {=IF($X19="", "", _xlfn.LET( _xlpm.SheetName, Z$1, _xlpm.CurrentDate, $X19, _xlpm.StartDate, $X$2, _xlpm.Dates, INDIRECT("'"&_xlpm.SheetName&"'!A:A"), _xlpm.Prices, INDIRECT("'"&_xlpm.SheetName&"'!E:E"), _xlpm.StartPrice, _xlfn.XLOOKUP(_xlpm.StartDate, _xlpm.Dates, _xlpm.Prices, , 0, 1), _xlpm.CurrentPrice, _xlfn.XLOOKUP(_xlpm.CurrentDate, _xlpm.Dates, _xlpm.Prices, _xlpm.StartPrice, -1, 1), (_xlpm.CurrentPrice / _xlpm.StartPrice)-1 ))} -> #REF! | AA19: {=IF($X19="", "", _xlfn.LET( _xlpm.SheetName, AA$1, _xlpm.CurrentDate, $X19, _xlpm.StartDate, $X$2, _xlpm.Dates, INDIRECT("'"&_xlpm.SheetName&"'!A:A"), _xlpm.Prices, INDIRECT("'"&_xlpm.SheetName&"'!E:E"), _xlpm.StartPrice, _xlfn.XLOOKUP(_xlpm.StartDate, _xlpm.Dates, _xlpm.Prices, , 0, 1), _xlpm.CurrentPrice, _xlfn.XLOOKUP(_xlpm.CurrentDate, _xlpm.Dates, _xlpm.Prices, _xlpm.StartPrice, -1, 1), (_xlpm.CurrentPrice / _xlpm.StartPrice)-1 ))} -> #REF! | AB19: {=IF($X19="", "", _xlfn.LET( _xlpm.SheetName, AB$1, _xlpm.CurrentDate, $X19, _xlpm.StartDate, $X$2, _xlpm.Dates, INDIRECT("'"&_xlpm.SheetName&"'!A:A"), _xlpm.Prices, INDIRECT("'"&_xlpm.SheetName&"'!E:E"), _xlpm.StartPrice, _xlfn.XLOOKUP(_xlpm.StartDate, _xlpm.Dates, _xlpm.Prices, , 0, 1), _xlpm.CurrentPrice, _xlfn.XLOOKUP(_xlpm.CurrentDate, _xlpm.Dates, _xlpm.Prices, _xlpm.StartPrice, -1, 1), (_xlpm.CurrentPrice / _xlpm.StartPrice)-1 ))} -> #REF! | AC19: {=IF($X19="", "", _xlfn.LET( _xlpm.SheetName, AC$1, _xlpm.CurrentDate, $X19, _xlpm.StartDate, $X$2, _xlpm.Dates, INDIRECT("'"&_xlpm.SheetName&"'!A:A"), _xlpm.Prices, INDIRECT("'"&_xlpm.SheetName&"'!E:E"), _xlpm.StartPrice, _xlfn.XLOOKUP(_xlpm.StartDate, _xlpm.Dates, _xlpm.Prices, , 0, 1), _xlpm.CurrentPrice, _xlfn.XLOOKUP(_xlpm.CurrentDate, _xlpm.Dates, _xlpm.Prices, _xlpm.StartPrice, -1, 1), (_xlpm.CurrentPrice / _xlpm.StartPrice)-1 ))} -> #REF! | AD19: {=IF($X19="", "", _xlfn.LET( _xlpm.SheetName, AD$1, _xlpm.CurrentDate, $X19, _xlpm.StartDate, $X$2, _xlpm.Dates, INDIRECT("'"&_xlpm.SheetName&"'!A:A"), _xlpm.Prices, INDIRECT("'"&_xlpm.SheetName&"'!E:E"), _xlpm.StartPrice, _xlfn.XLOOKUP(_xlpm.StartDate, _xlpm.Dates, _xlpm.Prices, , 0, 1), _xlpm.CurrentPrice, _xlfn.XLOOKUP(_xlpm.CurrentDate, _xlpm.Dates, _xlpm.Prices, _xlpm.StartPrice, -1, 1), (_xlpm.CurrentPrice / _xlpm.StartPrice)-1 ))} -> #REF!
... X378: =IF(X377="", "", IF(X377 >= TODAY(), "", X377+1)) | Y378: {=IF($X378="", "", _xlfn.LET( _xlpm.SheetName, Y$1, _xlpm.CurrentDate, $X378, _xlpm.StartDate, $X$2, _xlpm.Dates, INDIRECT("'"&_xlpm.SheetName&"'!A:A"), _xlpm.Prices, INDIRECT("'"&_xlpm.SheetName&"'!E:E"), _xlpm.StartPrice, _xlfn.XLOOKUP(_xlpm.StartDate, _xlpm.Dates, _xlpm.Prices, , 0, 1), _xlpm.CurrentPrice, _xlfn.XLOOKUP(_xlpm.CurrentDate, _xlpm.Dates, _xlpm.Prices, _xlpm.StartPrice, -1, 1), (_xlpm.CurrentPrice / _xlpm.StartPrice)-1 ))} | Z378: {=IF($X378="", "", _xlfn.LET( _xlpm.SheetName, Z$1, _xlpm.CurrentDate, $X378, _xlpm.StartDate, $X$2, _xlpm.Dates, INDIRECT("'"&_xlpm.SheetName&"'!A:A"), _xlpm.Prices, INDIRECT("'"&_xlpm.SheetName&"'!E:E"), _xlpm.StartPrice, _xlfn.XLOOKUP(_xlpm.StartDate, _xlpm.Dates, _xlpm.Prices, , 0, 1), _xlpm.CurrentPrice, _xlfn.XLOOKUP(_xlpm.CurrentDate, _xlpm.Dates, _xlpm.Prices, _xlpm.StartPrice, -1, 1), (_xlpm.CurrentPrice / _xlpm.StartPrice)-1 ))} | AA378: {=IF($X378="", "", _xlfn.LET( _xlpm.SheetName, AA$1, _xlpm.CurrentDate, $X378, _xlpm.StartDate, $X$2, _xlpm.Dates, INDIRECT("'"&_xlpm.SheetName&"'!A:A"), _xlpm.Prices, INDIRECT("'"&_xlpm.SheetName&"'!E:E"), _xlpm.StartPrice, _xlfn.XLOOKUP(_xlpm.StartDate, _xlpm.Dates, _xlpm.Prices, , 0, 1), _xlpm.CurrentPrice, _xlfn.XLOOKUP(_xlpm.CurrentDate, _xlpm.Dates, _xlpm.Prices, _xlpm.StartPrice, -1, 1), (_xlpm.CurrentPrice / _xlpm.StartPrice)-1 ))} | AB378: {=IF($X378="", "", _xlfn.LET( _xlpm.SheetName, AB$1, _xlpm.CurrentDate, $X378, _xlpm.StartDate, $X$2, _xlpm.Dates, INDIRECT("'"&_xlpm.SheetName&"'!A:A"), _xlpm.Prices, INDIRECT("'"&_xlpm.SheetName&"'!E:E"), _xlpm.StartPrice, _xlfn.XLOOKUP(_xlpm.StartDate, _xlpm.Dates, _xlpm.Prices, , 0, 1), _xlpm.CurrentPrice, _xlfn.XLOOKUP(_xlpm.CurrentDate, _xlpm.Dates, _xlpm.Prices, _xlpm.StartPrice, -1, 1), (_xlpm.CurrentPrice / _xlpm.StartPrice)-1 ))} | AC378: {=IF($X378="", "", _xlfn.LET( _xlpm.SheetName, AC$1, _xlpm.CurrentDate, $X378, _xlpm.StartDate, $X$2, _xlpm.Dates, INDIRECT("'"&_xlpm.SheetName&"'!A:A"), _xlpm.Prices, INDIRECT("'"&_xlpm.SheetName&"'!E:E"), _xlpm.StartPrice, _xlfn.XLOOKUP(_xlpm.StartDate, _xlpm.Dates, _xlpm.Prices, , 0, 1), _xlpm.CurrentPrice, _xlfn.XLOOKUP(_xlpm.CurrentDate, _xlpm.Dates, _xlpm.Prices, _xlpm.StartPrice, -1, 1), (_xlpm.CurrentPrice / _xlpm.StartPrice)-1 ))} | AD378: {=IF($X378="", "", _xlfn.LET( _xlpm.SheetName, AD$1, _xlpm.CurrentDate, $X378, _xlpm.StartDate, $X$2, _xlpm.Dates, INDIRECT("'"&_xlpm.SheetName&"'!A:A"), _xlpm.Prices, INDIRECT("'"&_xlpm.SheetName&"'!E:E"), _xlpm.StartPrice, _xlfn.XLOOKUP(_xlpm.StartDate, _xlpm.Dates, _xlpm.Prices, , 0, 1), _xlpm.CurrentPrice, _xlfn.XLOOKUP(_xlpm.CurrentDate, _xlpm.Dates, _xlpm.Prices, _xlpm.StartPrice, -1, 1), (_xlpm.CurrentPrice / _xlpm.StartPrice)-1 ))}

Sheet HSBC Pension
A1: Fund Code | B1: Fund Name | C1: Unit Price Date | D1: Currency code | E1: Unit Price
A2: HAPE | B2: Asia Pacific (ex Japan) Equities - passive | C2: 45293 | D2: GBP | E2: 2.595
A3: HAPE | B3: Asia Pacific (ex Japan) Equities - passive | C3: 45294 | D3: GBP | E3: 2.545
A4: HAPE | B4: Asia Pacific (ex Japan) Equities - passive | C4: 45295 | D4: GBP | E4: 2.521
A5: HAPE | B5: Asia Pacific (ex Japan) Equities - passive | C5: 45296 | D5: GBP | E5: 2.519
A6: HAPE | B6: Asia Pacific (ex Japan) Equities - passive | C6: 45299 | D6: GBP | E6: 2.489
A7: HAPE | B7: Asia Pacific (ex Japan) Equities - passive | C7: 45300 | D7: GBP | E7: 2.493
A8: HAPE | B8: Asia Pacific (ex Japan) Equities - passive | C8: 45301 | D8: GBP | E8: 2.479
A9: HAPE | B9: Asia Pacific (ex Japan) Equities - passive | C9: 45302 | D9: GBP | E9: 2.479
A10: HAPE | B10: Asia Pacific (ex Japan) Equities - passive | C10: 45303 | D10: GBP | E10: 2.483
A11: HAPE | B11: Asia Pacific (ex Japan) Equities - passive | C11: 45306 | D11: GBP | E11: 2.469
A12: HAPE | B12: Asia Pacific (ex Japan) Equities - passive | C12: 45307 | D12: GBP | E12: 2.442
A13: HAPE | B13: Asia Pacific (ex Japan) Equities - passive | C13: 45308 | D13: GBP | E13: 2.376
... A7642: HUKA | B7642: UK Equities - active | C7642: 45734 | D7642: GBP | E7642: 3.026

Sheet Ahmet Dashboard
A1: Fund Code | B1: Fund Name | C1: Lastest Price | D1: 1D% | E1: 1W% | F1: 1M% | G1: 3M% | I1: Since Portfolio change | U1: Portfolio update date | V1: 46080 | Y1: Date | Z1: HSHL | AA1: HEME | AB1: HJEP | AC1: HAPE
A2: HAPE | B2: Asia Pacific (ex Japan) Equities - passive | C2: {=_xlfn.LET( _xlpm.FundCode, $A2, _xlpm.Dates, _xlfn._xlws.FILTER('HSBC Pension'!$C:$C, 'HSBC Pension'!$A:$A=_xlpm.FundCode), _xlpm.Prices, _xlfn._xlws.FILTER('HSBC Pension'!$E:$E, 'HSBC Pension'!$A:$A=_xlpm.FundCode), _xlfn.XLOOKUP(MAX(_xlpm.Dates), _xlpm.Dates, _xlpm.Prices) )} -> 3.75 | D2: {=_xlfn.LET( _xlpm.FundCode, $A2, _xlpm.SourceSheet, 'HSBC Pension'!$A:$A, _xlpm.REM_FilterData, "Get only the dates and prices for this specific fund", _xlpm.Dates, _xlfn._xlws.FILTER('HSBC Pension'!$C:$C, _xlpm.SourceSheet=_xlpm.FundCode), _xlpm.Prices, _xlfn._xlws.FILTER('HSBC Pension'!$E:$E, _xlpm.SourceSheet=_xlpm.FundCode), _xlpm.REM_Calculation, "Same math as before", _xlpm.LatestDate, MAX(_xlpm.Dates), _xlpm.LatestPrice, _xlfn.XLOOKUP(_xlpm.LatestDate, _xlpm.Dates, _xlpm.Prices, , 0, -1), _xlpm.PrevPrice, _xlfn.XLOOKUP(WORKDAY(_xlpm.LatestDate, -1), _xlpm.Dates, _xlpm.Prices, _xlpm.LatestPrice, -1, -1), (_xlpm.LatestPrice / _xlpm.PrevPrice) - 1 )} -> -0.017295597 | E2: {=_xlfn.LET( _xlpm.FundCode, $A2, _xlpm.Dates, _xlfn._xlws.FILTER('HSBC Pension'!$C:$C, 'HSBC Pension'!$A:$A=_xlpm.FundCode), _xlpm.Prices, _xlfn._xlws.FILTER('HSBC Pension'!$E:$E, 'HSBC Pension'!$A:$A=_xlpm.FundCode), _xlpm.LatestDate, MAX(_xlpm.Dates), _xlpm.LatestPrice, _xlfn.XLOOKUP(_xlpm.LatestDate, _xlpm.Dates, _xlpm.Prices, , 0, -1), _xlpm.REM_Lookback, "Find price 7 days ago", _xlpm.PrevPrice, _xlfn.XLOOKUP(_xlpm.LatestDate - 7, _xlpm.Dates, _xlpm.Prices, _xlpm.LatestPrice, -1, -1), (_xlpm.LatestPrice / _xlpm.PrevPrice) - 1 )} -> -0.040429887 | F2: {=_xlfn.LET( _xlpm.FundCode, $A2, _xlpm.Dates, _xlfn._xlws.FILTER('HSBC Pension'!$C:$C, 'HSBC Pension'!$A:$A=_xlpm.FundCode), _xlpm.Prices, _xlfn._xlws.FILTER('HSBC Pension'!$E:$E, 'HSBC Pension'!$A:$A=_xlpm.FundCode), _xlpm.LatestDate, MAX(_xlpm.Dates), _xlpm.LatestPrice, _xlfn.XLOOKUP(_xlpm.LatestDate, _xlpm.Dates, _xlpm.Prices, , 0, -1), _xlpm.REM_Lookback, "Find price 1 month ago using EDATE", _xlpm.PrevPrice, _xlfn.XLOOKUP(EDATE(_xlpm.LatestDate, -1), _xlpm.Dates, _xlpm.Prices, _xlpm.LatestPrice, -1, -1), (_xlpm.LatestPrice / _xlpm.PrevPrice) - 1 )} -> -0.11305582 | G2: {=_xlfn.LET( _xlpm.FundCode, $A2, _xlpm.Dates, _xlfn._xlws.FILTER('HSBC Pension'!$C:$C, 'HSBC Pension'!$A:$A=_xlpm.FundCode), _xlpm.Prices, _xlfn._xlws.FILTER('HSBC Pension'!$E:$E, 'HSBC Pension'!$A:$A=_xlpm.FundCode), _xlpm.LatestDate, MAX(_xlpm.Dates), _xlpm.LatestPrice, _xlfn.XLOOKUP(_xlpm.LatestDate, _xlpm.Dates, _xlpm.Prices, , 0, -1), _xlpm.REM_Lookback, "Find price 3 months ago", _xlpm.PrevPrice, _xlfn.XLOOKUP(EDATE(_xlpm.LatestDate, -3), _xlpm.Dates, _xlpm.Prices, _xlpm.LatestPrice, -1, -1), (_xlpm.LatestPrice / _xlpm.PrevPrice) - 1 )} -> 0.16968185 | I2: {=_xlfn.LET( _xlpm.FundCode, $A2, _xlpm.TargetDate, $V$1, _xlpm.Dates, _xlfn._xlws.FILTER('HSBC Pension'!$C:$C, 'HSBC Pension'!$A:$A=_xlpm.FundCode), _xlpm.Prices, _xlfn._xlws.FILTER('HSBC Pension'!$E:$E, 'HSBC Pension'!$A:$A=_xlpm.FundCode), _xlpm.LatestDate, MAX(_xlpm.Dates), _xlpm.LatestPrice, _xlfn.XLOOKUP(_xlpm.LatestDate, _xlpm.Dates, _xlpm.Prices, , 0, -1), _xlpm.REM_StartPoint, "Find price on or immediately after the date in V1", _xlpm.StartPrice, _xlfn.XLOOKUP(_xlpm.TargetDate, _xlpm.Dates, _xlpm.Prices, _xlpm.LatestPrice, 1, 1), (_xlpm.LatestPrice / _xlpm.StartPrice) - 1 )} -> -0.11010916 | Y2: =V1 -> 46080 | Z2: {=IF($Y2="", "", _xlfn.LET( _xlpm.FundCode, Z$1, _xlpm.CurrentDate, $Y2, _xlpm.StartDate, $Y$2, _xlpm.REM_FilterData, "Grab only the relevant rows from the master sheet", _xlpm.SourceCodes, 'HSBC Pension'!$A:$A, _xlpm.Dates, _xlfn._xlws.FILTER('HSBC Pension'!$C:$C, _xlpm.SourceCodes=_xlpm.FundCode), _xlpm.Prices, _xlfn._xlws.FILTER('HSBC Pension'!$E:$E, _xlpm.SourceCodes=_xlpm.FundCode), _xlpm.REM_Math, "Calculate the growth from StartDate", _xlpm.StartPrice, _xlfn.XLOOKUP(_xlpm.StartDate, _xlpm.Dates, _xlpm.Prices, , 0, 1), _xlpm.CurrentPrice, _xlfn.XLOOKUP(_xlpm.CurrentDate, _xlpm.Dates, _xlpm.Prices, _xlpm.StartPrice, -1, 1), (_xlpm.CurrentPrice / _xlpm.StartPrice) - 1 ))} -> 0 | AA2: {=IF($Y2="", "", _xlfn.LET( _xlpm.FundCode, AA$1, _xlpm.CurrentDate, $Y2, _xlpm.StartDate, $Y$2, _xlpm.REM_FilterData, "Grab only the relevant rows from the master sheet", _xlpm.SourceCodes, 'HSBC Pension'!$A:$A, _xlpm.Dates, _xlfn._xlws.FILTER('HSBC Pension'!$C:$C, _xlpm.SourceCodes=_xlpm.FundCode), _xlpm.Prices, _xlfn._xlws.FILTER('HSBC Pension'!$E:$E, _xlpm.SourceCodes=_xlpm.FundCode), _xlpm.REM_Math, "Calculate the growth from StartDate", _xlpm.StartPrice, _xlfn.XLOOKUP(_xlpm.StartDate, _xlpm.Dates, _xlpm.Prices, , 0, 1), _xlpm.CurrentPrice, _xlfn.XLOOKUP(_xlpm.CurrentDate, _xlpm.Dates, _xlpm.Prices, _xlpm.StartPrice, -1, 1), (_xlpm.CurrentPrice / _xlpm.StartPrice) - 1 ))} -> 0 | AB2: {=IF($Y2="", "", _xlfn.LET( _xlpm.FundCode, AB$1, _xlpm.CurrentDate, $Y2, _xlpm.StartDate, $Y$2, _xlpm.REM_FilterData, "Grab only the relevant rows from the master sheet", _xlpm.SourceCodes, 'HSBC Pension'!$A:$A, _xlpm.Dates, _xlfn._xlws.FILTER('HSBC Pension'!$C:$C, _xlpm.SourceCodes=_xlpm.FundCode), _xlpm.Prices, _xlfn._xlws.FILTER('HSBC Pension'!$E:$E, _xlpm.SourceCodes=_xlpm.FundCode), _xlpm.REM_Math, "Calculate the growth from StartDate", _xlpm.StartPrice, _xlfn.XLOOKUP(_xlpm.StartDate, _xlpm.Dates, _xlpm.Prices, , 0, 1), _xlpm.CurrentPrice, _xlfn.XLOOKUP(_xlpm.CurrentDate, _xlpm.Dates, _xlpm.Prices, _xlpm.StartPrice, -1, 1), (_xlpm.CurrentPrice / _xlpm.StartPrice) - 1 ))} -> 0 | AC2: {=IF($Y2="", "", _xlfn.LET( _xlpm.FundCode, AC$1, _xlpm.CurrentDate, $Y2, _xlpm.StartDate, $Y$2, _xlpm.REM_FilterData, "Grab only the relevant rows from the master sheet", _xlpm.SourceCodes, 'HSBC Pension'!$A:$A, _xlpm.Dates, _xlfn._xlws.FILTER('HSBC Pension'!$C:$C, _xlpm.SourceCodes=_xlpm.FundCode), _xlpm.Prices, _xlfn._xlws.FILTER('HSBC Pension'!$E:$E, _xlpm.SourceCodes=_xlpm.FundCode), _xlpm.REM_Math, "Calculate the growth from StartDate", _xlpm.StartPrice, _xlfn.XLOOKUP(_xlpm.StartDate, _xlpm.Dates, _xlpm.Prices, , 0, 1), _xlpm.CurrentPrice, _xlfn.XLOOKUP(_xlpm.CurrentDate, _xlpm.Dates, _xlpm.Prices, _xlpm.StartPrice, -1, 1), (_xlpm.CurrentPrice / _xlpm.StartPrice) - 1 ))} -> 0
A3: HEEP | B3: European (ex UK) Equities - passive | C3: {=_xlfn.LET( _xlpm.FundCode, $A3, _xlpm.Dates, _xlfn._xlws.FILTER('HSBC Pension'!$C:$C, 'HSBC Pension'!$A:$A=_xlpm.FundCode), _xlpm.Prices, _xlfn._xlws.FILTER('HSBC Pension'!$E:$E, 'HSBC Pension'!$A:$A=_xlpm.FundCode), _xlfn.XLOOKUP(MAX(_xlpm.Dates), _xlpm.Dates, _xlpm.Prices) )} -> 3.735 | D3: {=_xlfn.LET( _xlpm.FundCode, $A3, _xlpm.SourceSheet, 'HSBC Pension'!$A:$A, _xlpm.REM_FilterData, "Get only the dates and prices for this specific fund", _xlpm.Dates, _xlfn._xlws.FILTER('HSBC Pension'!$C:$C, _xlpm.SourceSheet=_xlpm.FundCode), _xlpm.Prices, _xlfn._xlws.FILTER('HSBC Pension'!$E:$E, _xlpm.SourceSheet=_xlpm.FundCode), _xlpm.REM_Calculation, "Same math as before", _xlpm.LatestDate, MAX(_xlpm.Dates), _xlpm.LatestPrice, _xlfn.XLOOKUP(_xlpm.LatestDate, _xlpm.Dates, _xlpm.Prices, , 0, -1), _xlpm.PrevPrice, _xlfn.XLOOKUP(WORKDAY(_xlpm.LatestDate, -1), _xlpm.Dates, _xlpm.Prices, _xlpm.LatestPrice, -1, -1), (_xlpm.LatestPrice / _xlpm.PrevPrice) - 1 )} -> -0.013731186 | E3: {=_xlfn.LET( _xlpm.FundCode, $A3, _xlpm.Dates, _xlfn._xlws.FILTER('HSBC Pension'!$C:$C, 'HSBC Pension'!$A:$A=_xlpm.FundCode), _xlpm.Prices, _xlfn._xlws.FILTER('HSBC Pension'!$E:$E, 'HSBC Pension'!$A:$A=_xlpm.FundCode), _xlpm.LatestDate, MAX(_xlpm.Dates), _xlpm.LatestPrice, _xlfn.XLOOKUP(_xlpm.LatestDate, _xlpm.Dates, _xlpm.Prices, , 0, -1), _xlpm.REM_Lookback, "Find price 7 days ago", _xlpm.PrevPrice, _xlfn.XLOOKUP(_xlpm.LatestDate - 7, _xlpm.Dates, _xlpm.Prices, _xlpm.LatestPrice, -1, -1), (_xlpm.LatestPrice / _xlpm.PrevPrice) - 1 )} -> -0.004 | F3: {=_xlfn.LET( _xlpm.FundCode, $A3, _xlpm.Dates, _xlfn._xlws.FILTER('HSBC Pension'!$C:$C, 'HSBC Pension'!$A:$A=_xlpm.FundCode), _xlpm.Prices, _xlfn._xlws.FILTER('HSBC Pension'!$E:$E, 'HSBC Pension'!$A:$A=_xlpm.FundCode), _xlpm.LatestDate, MAX(_xlpm.Dates), _xlpm.LatestPrice, _xlfn.XLOOKUP(_xlpm.LatestDate, _xlpm.Dates, _xlpm.Prices, , 0, -1), _xlpm.REM_Lookback, "Find price 1 month ago using EDATE", _xlpm.PrevPrice, _xlfn.XLOOKUP(EDATE(_xlpm.LatestDate, -1), _xlpm.Dates, _xlpm.Prices, _xlpm.LatestPrice, -1, -1), (_xlpm.LatestPrice / _xlpm.PrevPrice) - 1 )} -> -0.098043951 | G3: {=_xlfn.LET( _xlpm.FundCode, $A3, _xlpm.Dates, _xlfn._xlws.FILTER('HSBC Pension'!$C:$C, 'HSBC Pension'!$A:$A=_xlpm.FundCode), _xlpm.Prices, _xlfn._xlws.FILTER('HSBC Pension'!$E:$E, 'HSBC Pension'!$A:$A=_xlpm.FundCode), _xlpm.LatestDate, MAX(_xlpm.Dates), _xlpm.LatestPrice, _xlfn.XLOOKUP(_xlpm.LatestDate, _xlpm.Dates, _xlpm.Prices, , 0, -1), _xlpm.REM_Lookback, "Find price 3 months ago", _xlpm.PrevPrice, _xlfn.XLOOKUP(EDATE(_xlpm.LatestDate, -3), _xlpm.Dates, _xlpm.Prices, _xlpm.LatestPrice, -1, -1), (_xlpm.LatestPrice / _xlpm.PrevPrice) - 1 )} -> -0.029113595 | I3: {=_xlfn.LET( _xlpm.FundCode, $A3, _xlpm.TargetDate, $V$1, _xlpm.Dates, _xlfn._xlws.FILTER('HSBC Pension'!$C:$C, 'HSBC Pension'!$A:$A=_xlpm.FundCode), _xlpm.Prices, _xlfn._xlws.FILTER('HSBC Pension'!$E:$E, 'HSBC Pension'!$A:$A=_xlpm.FundCode), _xlpm.LatestDate, MAX(_xlpm.Dates), _xlpm.LatestPrice, _xlfn.XLOOKUP(_xlpm.LatestDate, _xlpm.Dates, _xlpm.Prices, , 0, -1), _xlpm.REM_StartPoint, "Find price on or immediately after the date in V1", _xlpm.StartPrice, _xlfn.XLOOKUP(_xlpm.TargetDate, _xlpm.Dates, _xlpm.Prices, _xlpm.LatestPrice, 1, 1), (_xlpm.LatestPrice / _xlpm.StartPrice) - 1 )} -> -0.1 | Y3: =IF(Y2="", "", IF(Y2 >= TODAY(), "", Y2+1)) -> 46081 | Z3: {=IF($Y3="", "", _xlfn.LET( _xlpm.FundCode, Z$1, _xlpm.CurrentDate, $Y3, _xlpm.StartDate, $Y$2, _xlpm.REM_FilterData, "Grab only the relevant rows from the master sheet", _xlpm.SourceCodes, 'HSBC Pension'!$A:$A, _xlpm.Dates, _xlfn._xlws.FILTER('HSBC Pension'!$C:$C, _xlpm.SourceCodes=_xlpm.FundCode), _xlpm.Prices, _xlfn._xlws.FILTER('HSBC Pension'!$E:$E, _xlpm.SourceCodes=_xlpm.FundCode), _xlpm.REM_Math, "Calculate the growth from StartDate", _xlpm.StartPrice, _xlfn.XLOOKUP(_xlpm.StartDate, _xlpm.Dates, _xlpm.Prices, , 0, 1), _xlpm.CurrentPrice, _xlfn.XLOOKUP(_xlpm.CurrentDate, _xlpm.Dates, _xlpm.Prices, _xlpm.StartPrice, -1, 1), (_xlpm.CurrentPrice / _xlpm.StartPrice) - 1 ))} -> 0 | AA3: {=IF($Y3="", "", _xlfn.LET( _xlpm.FundCode, AA$1, _xlpm.CurrentDate, $Y3, _xlpm.StartDate, $Y$2, _xlpm.REM_FilterData, "Grab only the relevant rows from the master sheet", _xlpm.SourceCodes, 'HSBC Pension'!$A:$A, _xlpm.Dates, _xlfn._xlws.FILTER('HSBC Pension'!$C:$C, _xlpm.SourceCodes=_xlpm.FundCode), _xlpm.Prices, _xlfn._xlws.FILTER('HSBC Pension'!$E:$E, _xlpm.SourceCodes=_xlpm.FundCode), _xlpm.REM_Math, "Calculate the growth from StartDate", _xlpm.StartPrice, _xlfn.XLOOKUP(_xlpm.StartDate, _xlpm.Dates, _xlpm.Prices, , 0, 1), _xlpm.CurrentPrice, _xlfn.XLOOKUP(_xlpm.CurrentDate, _xlpm.Dates, _xlpm.Prices, _xlpm.StartPrice, -1, 1), (_xlpm.CurrentPrice / _xlpm.StartPrice) - 1 ))} -> 0 | AB3: {=IF($Y3="", "", _xlfn.LET( _xlpm.FundCode, AB$1, _xlpm.CurrentDate, $Y3, _xlpm.StartDate, $Y$2, _xlpm.REM_FilterData, "Grab only the relevant rows from the master sheet", _xlpm.SourceCodes, 'HSBC Pension'!$A:$A, _xlpm.Dates, _xlfn._xlws.FILTER('HSBC Pension'!$C:$C, _xlpm.SourceCodes=_xlpm.FundCode), _xlpm.Prices, _xlfn._xlws.FILTER('HSBC Pension'!$E:$E, _xlpm.SourceCodes=_xlpm.FundCode), _xlpm.REM_Math, "Calculate the growth from StartDate", _xlpm.StartPrice, _xlfn.XLOOKUP(_xlpm.StartDate, _xlpm.Dates, _xlpm.Prices, , 0, 1), _xlpm.CurrentPrice, _xlfn.XLOOKUP(_xlpm.CurrentDate, _xlpm.Dates, _xlpm.Prices, _xlpm.StartPrice, -1, 1), (_xlpm.CurrentPrice / _xlpm.StartPrice) - 1 ))} -> 0 | AC3: {=IF($Y3="", "", _xlfn.LET( _xlpm.FundCode, AC$1, _xlpm.CurrentDate, $Y3, _xlpm.StartDate, $Y$2, _xlpm.REM_FilterData, "Grab only the relevant rows from the master sheet", _xlpm.SourceCodes, 'HSBC Pension'!$A:$A, _xlpm.Dates, _xlfn._xlws.FILTER('HSBC Pension'!$C:$C, _xlpm.SourceCodes=_xlpm.FundCode), _xlpm.Prices, _xlfn._xlws.FILTER('HSBC Pension'!$E:$E, _xlpm.SourceCodes=_xlpm.FundCode), _xlpm.REM_Math, "Calculate the growth from StartDate", _xlpm.StartPrice, _xlfn.XLOOKUP(_xlpm.StartDate, _xlpm.Dates, _xlpm.Prices, , 0, 1), _xlpm.CurrentPrice, _xlfn.XLOOKUP(_xlpm.CurrentDate, _xlpm.Dates, _xlpm.Prices, _xlpm.StartPrice, -1, 1), (_xlpm.CurrentPrice / _xlpm.StartPrice) - 1 ))} -> 0
A4: HEME | B4: Emerging Markets Equities - active | C4: {=_xlfn.LET( _xlpm.FundCode, $A4, _xlpm.Dates, _xlfn._xlws.FILTER('HSBC Pension'!$C:$C, 'HSBC Pension'!$A:$A=_xlpm.FundCode), _xlpm.Prices, _xlfn._xlws.FILTER('HSBC Pension'!$E:$E, 'HSBC Pension'!$A:$A=_xlpm.FundCode), _xlfn.XLOOKUP(MAX(_xlpm.Dates), _xlpm.Dates, _xlpm.Prices) )} -> 2.83 | D4: {=_xlfn.LET( _xlpm.FundCode, $A4, _xlpm.SourceSheet, 'HSBC Pension'!$A:$A, _xlpm.REM_FilterData, "Get only the dates and prices for this specific fund", _xlpm.Dates, _xlfn._xlws.FILTER('HSBC Pension'!$C:$C, _xlpm.SourceSheet=_xlpm.FundCode), _xlpm.Prices, _xlfn._xlws.FILTER('HSBC Pension'!$E:$E, _xlpm.SourceSheet=_xlpm.FundCode), _xlpm.REM_Calculation, "Same math as before", _xlpm.LatestDate, MAX(_xlpm.Dates), _xlpm.LatestPrice, _xlfn.XLOOKUP(_xlpm.LatestDate, _xlpm.Dates, _xlpm.Prices, , 0, -1), _xlpm.PrevPrice, _xlfn.XLOOKUP(WORKDAY(_xlpm.LatestDate, -1), _xlpm.Dates, _xlpm.Prices, _xlpm.LatestPrice, -1, -1), (_xlpm.LatestPrice / _xlpm.PrevPrice) - 1 )} -> -0.0038718761 | E4: {=_xlfn.LET( _xlpm.FundCode, $A4, _xlpm.Dates, _xlfn._xlws.FILTER('HSBC Pension'!$C:$C, 'HSBC Pension'!$A:$A=_xlpm.FundCode), _xlpm.Prices, _xlfn._xlws.FILTER('HSBC Pension'!$E:$E, 'HSBC Pension'!$A:$A=_xlpm.FundCode), _xlpm.LatestDate, MAX(_xlpm.Dates), _xlpm.LatestPrice, _xlfn.XLOOKUP(_xlpm.LatestDate, _xlpm.Dates, _xlpm.Prices, , 0, -1), _xlpm.REM_Lookback, "Find price 7 days ago", _xlpm.PrevPrice, _xlfn.XLOOKUP(_xlpm.LatestDate - 7, _xlpm.Dates, _xlpm.Prices, _xlpm.LatestPrice, -1, -1), (_xlpm.LatestPrice / _xlpm.PrevPrice) - 1 )} -> -0.019404019 | F4: {=_xlfn.LET( _xlpm.FundCode, $A4, _xlpm.Dates, _xlfn._xlws.FILTER('HSBC Pension'!$C:$C, 'HSBC Pension'!$A:$A=_xlpm.FundCode), _xlpm.Prices, _xlfn._xlws.FILTER('HSBC Pension'!$E:$E, 'HSBC Pension'!$A:$A=_xlpm.FundCode), _xlpm.LatestDate, MAX(_xlpm.Dates), _xlpm.LatestPrice, _xlfn.XLOOKUP(_xlpm.LatestDate, _xlpm.Dates, _xlpm.Prices, , 0, -1), _xlpm.REM_Lookback, "Find price 1 month ago using EDATE", _xlpm.PrevPrice, _xlfn.XLOOKUP(EDATE(_xlpm.LatestDate, -1), _xlpm.Dates, _xlpm.Prices, _xlpm.LatestPrice, -1, -1), (_xlpm.LatestPrice / _xlpm.PrevPrice) - 1 )} -> -0.085030715 | G4: {=_xlfn.LET( _xlpm.FundCode, $A4, _xlpm.Dates, _xlfn._xlws.FILTER('HSBC Pension'!$C:$C, 'HSBC Pension'!$A:$A=_xlpm.FundCode), _xlpm.Prices, _xlfn._xlws.FILTER('HSBC Pension'!$E:$E, 'HSBC Pension'!$A:$A=_xlpm.FundCode), _xlpm.LatestDate, MAX(_xlpm.Dates), _xlpm.LatestPrice, _xlfn.XLOOKUP(_xlpm.LatestDate, _xlpm.Dates, _xlpm.Prices, , 0, -1), _xlpm.REM_Lookback, "Find price 3 months ago", _xlpm.PrevPrice, _xlfn.XLOOKUP(EDATE(_xlpm.LatestDate, -3), _xlpm.Dates, _xlpm.Prices, _xlpm.LatestPrice, -1, -1), (_xlpm.LatestPrice / _xlpm.PrevPrice) - 1 )} -> 0.067924528 | I4: {=_xlfn.LET( _xlpm.FundCode, $A4, _xlpm.TargetDate, $V$1, _xlpm.Dates, _xlfn._xlws.FILTER('HSBC Pension'!$C:$C, 'HSBC Pension'!$A:$A=_xlpm.FundCode), _xlpm.Prices, _xlfn._xlws.FILTER('HSBC Pension'!$E:$E, 'HSBC Pension'!$A:$A=_xlpm.FundCode), _xlpm.LatestDate, MAX(_xlpm.Dates), _xlpm.LatestPrice, _xlfn.XLOOKUP(_xlpm.LatestDate, _xlpm.Dates, _xlpm.Prices, , 0, -1), _xlpm.REM_StartPoint, "Find price on or immediately after the date in V1", _xlpm.StartPrice, _xlfn.XLOOKUP(_xlpm.TargetDate, _xlpm.Dates, _xlpm.Prices, _xlpm.LatestPrice, 1, 1), (_xlpm.LatestPrice / _xlpm.StartPrice) - 1 )} -> -0.086212464 | Y4: =IF(Y3="", "", IF(Y3 >= TODAY(), "", Y3+1)) -> 46082 | Z4: {=IF($Y4="", "", _xlfn.LET( _xlpm.FundCode, Z$1, _xlpm.CurrentDate, $Y4, _xlpm.StartDate, $Y$2, _xlpm.REM_FilterData, "Grab only the relevant rows from the master sheet", _xlpm.SourceCodes, 'HSBC Pension'!$A:$A, _xlpm.Dates, _xlfn._xlws.FILTER('HSBC Pension'!$C:$C, _xlpm.SourceCodes=_xlpm.FundCode), _xlpm.Prices, _xlfn._xlws.FILTER('HSBC Pension'!$E:$E, _xlpm.SourceCodes=_xlpm.FundCode), _xlpm.REM_Math, "Calculate the growth from StartDate", _xlpm.StartPrice, _xlfn.XLOOKUP(_xlpm.StartDate, _xlpm.Dates, _xlpm.Prices, , 0, 1), _xlpm.CurrentPrice, _xlfn.XLOOKUP(_xlpm.CurrentDate, _xlpm.Dates, _xlpm.Prices, _xlpm.StartPrice, -1, 1), (_xlpm.CurrentPrice / _xlpm.StartPrice) - 1 ))} -> 0 | AA4: {=IF($Y4="", "", _xlfn.LET( _xlpm.FundCode, AA$1, _xlpm.CurrentDate, $Y4, _xlpm.StartDate, $Y$2, _xlpm.REM_FilterData, "Grab only the relevant rows from the master sheet", _xlpm.SourceCodes, 'HSBC Pension'!$A:$A, _xlpm.Dates, _xlfn._xlws.FILTER('HSBC Pension'!$C:$C, _xlpm.SourceCodes=_xlpm.FundCode), _xlpm.Prices, _xlfn._xlws.FILTER('HSBC Pension'!$E:$E, _xlpm.SourceCodes=_xlpm.FundCode), _xlpm.REM_Math, "Calculate the growth from StartDate", _xlpm.StartPrice, _xlfn.XLOOKUP(_xlpm.StartDate, _xlpm.Dates, _xlpm.Prices, , 0, 1), _xlpm.CurrentPrice, _xlfn.XLOOKUP(_xlpm.CurrentDate, _xlpm.Dates, _xlpm.Prices, _xlpm.StartPrice, -1, 1), (_xlpm.CurrentPrice / _xlpm.StartPrice) - 1 ))} -> 0 | AB4: {=IF($Y4="", "", _xlfn.LET( _xlpm.FundCode, AB$1, _xlpm.CurrentDate, $Y4, _xlpm.StartDate, $Y$2, _xlpm.REM_FilterData, "Grab only the relevant rows from the master sheet", _xlpm.SourceCodes, 'HSBC Pension'!$A:$A, _xlpm.Dates, _xlfn._xlws.FILTER('HSBC Pension'!$C:$C, _xlpm.SourceCodes=_xlpm.FundCode), _xlpm.Prices, _xlfn._xlws.FILTER('HSBC Pension'!$E:$E, _xlpm.SourceCodes=_xlpm.FundCode), _xlpm.REM_Math, "Calculate the growth from StartDate", _xlpm.StartPrice, _xlfn.XLOOKUP(_xlpm.StartDate, _xlpm.Dates, _xlpm.Prices, , 0, 1), _xlpm.CurrentPrice, _xlfn.XLOOKUP(_xlpm.CurrentDate, _xlpm.Dates, _xlpm.Prices, _xlpm.StartPrice, -1, 1), (_xlpm.CurrentPrice / _xlpm.StartPrice) - 1 ))} -> 0 | AC4: {=IF($Y4="", "", _xlfn.LET( _xlpm.FundCode, AC$1, _xlpm.CurrentDate, $Y4, _xlpm.StartDate, $Y$2, _xlpm.REM_FilterData, "Grab only the relevant rows from the master sheet", _xlpm.SourceCodes, 'HSBC Pension'!$A:$A, _xlpm.Dates, _xlfn._xlws.FILTER('HSBC Pension'!$C:$C, _xlpm.SourceCodes=_xlpm.FundCode), _xlpm.Prices, _xlfn._xlws.FILTER('HSBC Pension'!$E:$E, _xlpm.SourceCodes=_xlpm.FundCode), _xlpm.REM_Math, "Calculate the growth from StartDate", _xlpm.StartPrice, _xlfn.XLOOKUP(_xlpm.StartDate, _xlpm.Dates, _xlpm.Prices, , 0, 1), _xlpm.CurrentPrice, _xlfn.XLOOKUP(_xlpm.CurrentDate, _xlpm.Dates, _xlpm.Prices, _xlpm.StartPrice, -1, 1), (_xlpm.CurrentPrice / _xlpm.StartPrice) - 1 ))} -> 0
A5: HGEA | B5: Global Equities - active | C5: {=_xlfn.LET( _xlpm.FundCode, $A5, _xlpm.Dates, _xlfn._xlws.FILTER('HSBC Pension'!$C:$C, 'HSBC Pension'!$A:$A=_xlpm.FundCode), _xlpm.Prices, _xlfn._xlws.FILTER('HSBC Pension'!$E:$E, 'HSBC Pension'!$A:$A=_xlpm.FundCode), _xlfn.XLOOKUP(MAX(_xlpm.Dates), _xlpm.Dates, _xlpm.Prices) )} -> 4.356 | D5: {=_xlfn.LET( _xlpm.FundCode, $A5, _xlpm.SourceSheet, 'HSBC Pension'!$A:$A, _xlpm.REM_FilterData, "Get only the dates and prices for this specific fund", _xlpm.Dates, _xlfn._xlws.FILTER('HSBC Pension'!$C:$C, _xlpm.SourceSheet=_xlpm.FundCode), _xlpm.Prices, _xlfn._xlws.FILTER('HSBC Pension'!$E:$E, _xlpm.SourceSheet=_xlpm.FundCode), _xlpm.REM_Calculation, "Same math as before", _xlpm.LatestDate, MAX(_xlpm.Dates), _xlpm.LatestPrice, _xlfn.XLOOKUP(_xlpm.LatestDate, _xlpm.Dates, _xlpm.Prices, , 0, -1), _xlpm.PrevPrice, _xlfn.XLOOKUP(WORKDAY(_xlpm.LatestDate, -1), _xlpm.Dates, _xlpm.Prices, _xlpm.LatestPrice, -1, -1), (_xlpm.LatestPrice / _xlpm.PrevPrice) - 1 )} -> -0.00091743119 | E5: {=_xlfn.LET( _xlpm.FundCode, $A5, _xlpm.Dates, _xlfn._xlws.FILTER('HSBC Pension'!$C:$C, 'HSBC Pension'!$A:$A=_xlpm.FundCode), _xlpm.Prices, _xlfn._xlws.FILTER('HSBC Pension'!$E:$E, 'HSBC Pension'!$A:$A=_xlpm.FundCode), _xlpm.LatestDate, MAX(_xlpm.Dates), _xlpm.LatestPrice, _xlfn.XLOOKUP(_xlpm.LatestDate, _xlpm.Dates, _xlpm.Prices, , 0, -1), _xlpm.REM_Lookback, "Find price 7 days ago", _xlpm.PrevPrice, _xlfn.XLOOKUP(_xlpm.LatestDate - 7, _xlpm.Dates, _xlpm.Prices, _xlpm.LatestPrice, -1, -1), (_xlpm.LatestPrice / _xlpm.PrevPrice) - 1 )} -> -0.011123723 | F5: {=_xlfn.LET( _xlpm.FundCode, $A5, _xlpm.Dates, _xlfn._xlws.FILTER('HSBC Pension'!$C:$C, 'HSBC Pension'!$A:$A=_xlpm.FundCode), _xlpm.Prices, _xlfn._xlws.FILTER('HSBC Pension'!$E:$E, 'HSBC Pension'!$A:$A=_xlpm.FundCode), _xlpm.LatestDate, MAX(_xlpm.Dates), _xlpm.LatestPrice, _xlfn.XLOOKUP(_xlpm.LatestDate, _xlpm.Dates, _xlpm.Prices, , 0, -1), _xlpm.REM_Lookback, "Find price 1 month ago using EDATE", _xlpm.PrevPrice, _xlfn.XLOOKUP(EDATE(_xlpm.LatestDate, -1), _xlpm.Dates, _xlpm.Prices, _xlpm.LatestPrice, -1, -1), (_xlpm.LatestPrice / _xlpm.PrevPrice) - 1 )} -> -0.069230769 | G5: {=_xlfn.LET( _xlpm.FundCode, $A5, _xlpm.Dates, _xlfn._xlws.FILTER('HSBC Pension'!$C:$C, 'HSBC Pension'!$A:$A=_xlpm.FundCode), _xlpm.Prices, _xlfn._xlws.FILTER('HSBC Pension'!$E:$E, 'HSBC Pension'!$A:$A=_xlpm.FundCode), _xlpm.LatestDate, MAX(_xlpm.Dates), _xlpm.LatestPrice, _xlfn.XLOOKUP(_xlpm.LatestDate, _xlpm.Dates, _xlpm.Prices, , 0, -1), _xlpm.REM_Lookback, "Find price 3 months ago", _xlpm.PrevPrice, _xlfn.XLOOKUP(EDATE(_xlpm.LatestDate, -3), _xlpm.Dates, _xlpm.Prices, _xlpm.LatestPrice, -1, -1), (_xlpm.LatestPrice / _xlpm.PrevPrice) - 1 )} -> -0.023756163 | I5: {=_xlfn.LET( _xlpm.FundCode, $A5, _xlpm.TargetDate, $V$1, _xlpm.Dates, _xlfn._xlws.FILTER('HSBC Pension'!$C:$C, 'HSBC Pension'!$A:$A=_xlpm.FundCode), _xlpm.Prices, _xlfn._xlws.FILTER('HSBC Pension'!$E:$E, 'HSBC Pension'!$A:$A=_xlpm.FundCode), _xlpm.LatestDate, MAX(_xlpm.Dates), _xlpm.LatestPrice, _xlfn.XLOOKUP(_xlpm.LatestDate, _xlpm.Dates, _xlpm.Prices, , 0, -1), _xlpm.REM_StartPoint, "Find price on or immediately after the date in V1", _xlpm.StartPrice, _xlfn.XLOOKUP(_xlpm.TargetDate, _xlpm.Dates, _xlpm.Prices, _xlpm.LatestPrice, 1, 1), (_xlpm.LatestPrice / _xlpm.StartPrice) - 1 )} -> -0.073191489 | Y5: =IF(Y4="", "", IF(Y4 >= TODAY(), "", Y4+1)) -> 46083 | Z5: {=IF($Y5="", "", _xlfn.LET( _xlpm.FundCode, Z$1, _xlpm.CurrentDate, $Y5, _xlpm.StartDate, $Y$2, _xlpm.REM_FilterData, "Grab only the relevant rows from the master sheet", _xlpm.SourceCodes, 'HSBC Pension'!$A:$A, _xlpm.Dates, _xlfn._xlws.FILTER('HSBC Pension'!$C:$C, _xlpm.SourceCodes=_xlpm.FundCode), _xlpm.Prices, _xlfn._xlws.FILTER('HSBC Pension'!$E:$E, _xlpm.SourceCodes=_xlpm.FundCode), _xlpm.REM_Math, "Calculate the growth from StartDate", _xlpm.StartPrice, _xlfn.XLOOKUP(_xlpm.StartDate, _xlpm.Dates, _xlpm.Prices, , 0, 1), _xlpm.CurrentPrice, _xlfn.XLOOKUP(_xlpm.CurrentDate, _xlpm.Dates, _xlpm.Prices, _xlpm.StartPrice, -1, 1), (_xlpm.CurrentPrice / _xlpm.StartPrice) - 1 ))} -> 0.0015540016 | AA5: {=IF($Y5="", "", _xlfn.LET( _xlpm.FundCode, AA$1, _xlpm.CurrentDate, $Y5, _xlpm.StartDate, $Y$2, _xlpm.REM_FilterData, "Grab only the relevant rows from the master sheet", _xlpm.SourceCodes, 'HSBC Pension'!$A:$A, _xlpm.Dates, _xlfn._xlws.FILTER('HSBC Pension'!$C:$C, _xlpm.SourceCodes=_xlpm.FundCode), _xlpm.Prices, _xlfn._xlws.FILTER('HSBC Pension'!$E:$E, _xlpm.SourceCodes=_xlpm.FundCode), _xlpm.REM_Math, "Calculate the growth from StartDate", _xlpm.StartPrice, _xlfn.XLOOKUP(_xlpm.StartDate, _xlpm.Dates, _xlpm.Prices, , 0, 1), _xlpm.CurrentPrice, _xlfn.XLOOKUP(_xlpm.CurrentDate, _xlpm.Dates, _xlpm.Prices, _xlpm.StartPrice, -1, 1), (_xlpm.CurrentPrice / _xlpm.StartPrice) - 1 ))} -> -0.0077494349 | AB5: {=IF($Y5="", "", _xlfn.LET( _xlpm.FundCode, AB$1, _xlpm.CurrentDate, $Y5, _xlpm.StartDate, $Y$2, _xlpm.REM_FilterData, "Grab only the relevant rows from the master sheet", _xlpm.SourceCodes, 'HSBC Pension'!$A:$A, _xlpm.Dates, _xlfn._xlws.FILTER('HSBC Pension'!$C:$C, _xlpm.SourceCodes=_xlpm.FundCode), _xlpm.Prices, _xlfn._xlws.FILTER('HSBC Pension'!$E:$E, _xlpm.SourceCodes=_xlpm.FundCode), _xlpm.REM_Math, "Calculate the growth from StartDate", _xlpm.StartPrice, _xlfn.XLOOKUP(_xlpm.StartDate, _xlpm.Dates, _xlpm.Prices, , 0, 1), _xlpm.CurrentPrice, _xlfn.XLOOKUP(_xlpm.CurrentDate, _xlpm.Dates, _xlpm.Prices, _xlpm.StartPrice, -1, 1), (_xlpm.CurrentPrice / _xlpm.StartPrice) - 1 ))} -> -0.012927757 | AC5: {=IF($Y5="", "", _xlfn.LET( _xlpm.FundCode, AC$1, _xlpm.CurrentDate, $Y5, _xlpm.StartDate, $Y$2, _xlpm.REM_FilterData, "Grab only the relevant rows from the master sheet", _xlpm.SourceCodes, 'HSBC Pension'!$A:$A, _xlpm.Dates, _xlfn._xlws.FILTER('HSBC Pension'!$C:$C, _xlpm.SourceCodes=_xlpm.FundCode), _xlpm.Prices, _xlfn._xlws.FILTER('HSBC Pension'!$E:$E, _xlpm.SourceCodes=_xlpm.FundCode), _xlpm.REM_Math, "Calculate the growth from StartDate", _xlpm.StartPrice, _xlfn.XLOOKUP(_xlpm.StartDate, _xlpm.Dates, _xlpm.Prices, , 0, 1), _xlpm.CurrentPrice, _xlfn.XLOOKUP(_xlpm.CurrentDate, _xlpm.Dates, _xlpm.Prices, _xlpm.StartPrice, -1, 1), (_xlpm.CurrentPrice / _xlpm.StartPrice) - 1 ))} -> -0.0059326056
